Workbook

Sheet Cover
A1: Project Lumière – LBO model
A2: ARCHIMED Investment Director case study (practice). Fictional company; €m unless stated.
A4: How to use
A5: Change inputs only on the Inputs sheet (and the sensitivity axes on Returns). Every other number is a formula.
A6: Colour code: blue text = hardcoded input · yellow fill = key lever to flex live · black = formula · green = link to another sheet.
A7: Three full LBOs run side by side: LBO_Base (ARCHIMED case), LBO_Mgmt (vendor plan restated), LBO_Down (downside).
A8: Interview levers: entry multiple (Inputs C9), leverage (C28), earn-out (C21), growth and margin flex (C52–C53), exit multiples (D59–F59).
A9: Interest is charged on opening balances, so the model has no circular references and needs no iterative calculation.
A11: Sheet guide
A12: Sheet | B12: What it does
A13: Inputs | B13: Every assumption, with its source in column I
A14: Case_Data | B14: Information-memo data: history, vendor vs. ARCHIMED EBITDA bridge, vendor plan, KPIs
A15: Transaction | B15: Sources and uses, ownership, entry metrics
A16: LBO_Base / LBO_Mgmt / LBO_Down | B16: Revenue and EBITDA build, add-ons, free cash flow, tax, debt, credit stats, returns, equity bridge
A17: Returns | B17: Case comparison, value bridge, bid ladder, IRR and MOIC grids, model checks
A19: Key outputs (live)
A20: Metric | C20: Base | D20: Management | E20: Downside
A21: Entry enterprise value (€m) | C21: =Inputs!C10 -> 540
A22: Entry EV / underwritten EBITDA | C22: =Inputs!C9 -> 13.5
A23: Entry EV / vendor Adjusted EBITDA | C23: =Inputs!C11 -> 12.413793
A24: Total equity invested (€m) | C24: =Transaction!C20 -> 328.2
A25: ARCHIMED equity (€m) | C25: =Transaction!C15 -> 282.2
A26: IRR | C26: =Returns!C18 -> 0.19985379 | D26: =Returns!D18 -> 0.23980895 | E26: =Returns!E18 -> 0.033350564
A27: MOIC | C27: =Returns!C17 -> 2.4868045 | D27: =Returns!D17 -> 2.9293673 | E27: =Returns!E17 -> 1.1782526
A28: All model checks OK (1 = yes) | C28: =Returns!C87 -> 1

Sheet Inputs
A1: Project Lumière – inputs and assumptions
A2: Blue = hardcoded input · yellow fill = key lever to flex · black = formula · green = link to another sheet. €m unless stated.
A4: 1. Transaction and valuation
A5: FY2026E revenue | B5: €m | C5: =Case_Data!G9 -> 150 | I5: Case_Data
A6: FY2026E reported EBITDA (IFRS 16) | B6: €m | C6: =Case_Data!G16 -> 41.9 | I6: Case_Data
A7: FY2026E vendor Adjusted EBITDA | B7: €m | C7: =Case_Data!G23 -> 43.5 | I7: Case_Data: vendor definition
A8: FY2026E underwritten EBITDA (ARCHIMED definition) | B8: €m | C8: =Case_Data!G28 -> 40 | I8: Case_Data: pre-IFRS 16, IVDR costs treated as recurring, standalone costs included
A9: Entry EV / underwritten EBITDA | B9: x | C9: 13.5 | I9: ARCHIMED bid: highest price at which the base case clears 20% IRR / 2.5x MOIC
A10: Entry enterprise value | B10: €m | C10: =C9*C8 -> 540
A11: Implied EV / vendor Adjusted EBITDA | B11: x | C11: =C10/C7 -> 12.413793
A12: Implied EV / FY2026E revenue | B12: x | C12: =C10/C5 -> 3.6
A13: Vendor price expectation | B13: €m | C13: 600 | I13: Case brief: sell-side guidance, cash-free / debt-free
A14: Vendor price / underwritten EBITDA | B14: x | C14: =C13/C8 -> 15
A15: Vendor price / vendor Adjusted EBITDA | B15: x | C15: =C13/C7 -> 13.793103
A16: Transaction costs (% of EV) | B16: % | C16: 0.02 | I16: Case brief: M&A, due diligence, legal, W&I insurance, registration duties
A17: Minimum cash (funded at closing) | B17: €m | C17: 10 | I17: Case brief
A18: Founder rollover | B18: €m | C18: 40 | I18: Case brief: founder reinvests c.€40m alongside ARCHIMED (same instrument strip)
A19: Management rollover | B19: €m | C19: 6 | I19: ARCHIMED proposal: existing managers reinvest part of their 8% stake
A20: MIP: management share of capital gain | B20: % | C20: 0.1 | I20: ARCHIMED proposal: sweet equity worth 10% of the equity gain at exit
A21: Earn-out: maximum payment | B21: €m | C21: 40 | I21: ARCHIMED proposal: bridges the gap to the vendor price only if the plan is delivered
A22: Earn-out: measurement year (organic EBITDA) | B22: year | C22: 2028 | I22: ARCHIMED proposal
A23: Earn-out: payment year | B23: year | C23: 2029 | I23: ARCHIMED proposal
A24: Earn-out: organic EBITDA floor (0% paid) | B24: €m | C24: 50 | I24: Linear payout between floor and cap; base case FY2028 organic EBITDA is c.€49m
A25: Earn-out: organic EBITDA cap (100% paid) | B25: €m | C25: 53.5 | I25: Management plan FY2028 EBITDA on the ARCHIMED definition is c.€54m, so the plan earns 100%
A27: 2. Financing
A28: Unitranche leverage (x underwritten EBITDA) | B28: x | C28: 6 | I28: Case brief: indicative terms, up to 6.0x
A29: Unitranche at closing | B29: €m | C29: =C28*C8 -> 240
A30: Unitranche upfront fee | B30: % | C30: 0.025 | I30: Case brief
A31: Capex and acquisition facility (CAF) commitment | B31: €m | C31: 110 | I31: Case brief
A32: Revolving credit facility (RCF) commitment | B32: €m | C32: 30 | I32: Case brief
A33: Upfront fee on CAF and RCF | B33: % | C33: 0.01 | I33: Case brief
A34: 3-month Euribor (flat) | B34: % | C34: 0.02 | I34: Case brief assumption
A35: Unitranche margin | B35: % | C35: 0.0475 | I35: Case brief
A36: CAF margin | B36: % | C36: 0.0475 | I36: Case brief
A37: RCF margin | B37: % | C37: 0.04 | I37: Case brief
A38: Commitment fee (% of margin, on undrawn amounts) | B38: % | C38: 0.35 | I38: Case brief
A39: Interest income on cash | B39: % | C39: 0.015 | I39: Assumption
A40: Excess cash used to prepay the unitranche | B40: % | C40: 1 | I40: Assumption: voluntary prepayment at par of cash above the minimum
A41: Net leverage covenant (maintenance test) | B41: x | C41: 8.25 | I41: Assumption: set with c.30% EBITDA headroom to closing leverage of 5.75x
A43: 3. Operating cases (organic, ARCHIMED EBITDA definition)
A44: Assumption | B44: Unit | D44: FY2027 | E44: FY2028 | F44: FY2029 | G44: FY2030 | H44: FY2031 | I44: Source / rationale
A45: Revenue growth – Base (ARCHIMED) | B45: % | D45: 0.075 | E45: 0.08 | F45: 0.085 | G45: 0.085 | H45: 0.08 | I45: c.75% of plan growth: market 6–7% + CLIA migration + measured US ramp; history 6.4–7.0%
A46: Revenue growth – Management (vendor plan) | B46: % | D46: =Case_Data!C42 -> 0.1 | E46: =Case_Data!D42 -> 0.11 | F46: =Case_Data!E42 -> 0.115 | G46: =Case_Data!F42 -> 0.115 | H46: =Case_Data!G42 -> 0.11 | I46: Case_Data: vendor business plan
A47: Revenue growth – Downside | B47: % | D47: 0.04 | E47: 0.04 | F47: 0.045 | G47: 0.045 | H47: 0.045 | I47: France tariff cuts, US launch slips two years, IVDR delays
A48: EBITDA margin – Base (ARCHIMED) | B48: % | D48: 0.275 | E48: 0.284 | F48: 0.293 | G48: 0.301 | H48: 0.308 | I48: +410bp over five years (vendor plan +580bp): CLIA mix, pricing, plant automation, G&A leverage
A49: EBITDA margin – Management (vendor plan, restated) | B49: % | D49: =Case_Data!C44-$C$51 -> 0.27966667 | E49: =Case_Data!D44-$C$51 -> 0.29466667 | F49: =Case_Data!E44-$C$51 -> 0.30966667 | G49: =Case_Data!F44-$C$51 -> 0.31966667 | H49: =Case_Data!G44-$C$51 -> 0.32466667 | I49: Vendor margins less the FY2026E definitional gap in C51
A50: EBITDA margin – Downside | B50: % | D50: 0.265 | E50: 0.265 | F50: 0.265 | G50: 0.265 | H50: 0.265 | I50: No margin expansion: price pressure and IVDR costs absorb operating leverage
A51: Definitional gap: vendor Adjusted vs. underwritten margin (FY2026E) | B51: % | C51: =(C7-C8)/C5 -> 0.023333333 | I51: Held constant to restate the vendor plan to the ARCHIMED EBITDA definition
A52: Flex: revenue growth delta, all cases (e.g. -1.0%) | B52: % | C52: 0 | I52: Interview lever: adds to every year of every case
A53: Flex: EBITDA margin delta, all cases (e.g. -1.0%) | B53: % | C53: 0 | I53: Interview lever: adds to every year of every case
A55: 4. Case settings
A56: Setting | B56: Unit | D56: Base | E56: Management | F56: Downside
A57: Include add-on A (1 = yes, 0 = no) | B57: flag | D57: 1 | E57: 1 | F57: 0 | I57: Downside assumes no M&A (capital preserved for the core business)
A58: Include add-on B (1 = yes, 0 = no) | B58: flag | D58: 1 | E58: 1 | F58: 0
A59: Exit EV / EBITDA multiple | B59: x | D59: 13.5 | E59: 13.5 | F59: 12 | I59: Base = entry multiple (no multiple expansion); downside = 1.5x compression
A61: 5. Cash flow, tax and exit
A62: D&A (% of revenue) | B62: % | C62: 0.05 | I62: Case brief
A63: Maintenance and placed-analyzer capex (% of revenue) | B63: % | C63: 0.04 | I63: Case brief
A64: Capitalised R&D (% of revenue) | B64: % | C64: 0.015 | I64: Case brief
A65: Growth capex (CLIA industrialisation, US hub) | B65: €m | D65: 5 | E65: 4 | F65: 2 | G65: 0 | H65: 0 | I65: Case brief: €5m, €4m, €2m in FY2027–FY2029 (entered in the year columns D–H)
A66: Net working capital (% of revenue) | B66: % | C66: 0.22 | I66: Case brief; FY2026E actual 22.0%
A67: Corporate income tax rate | B67: % | C67: 0.25 | I67: Case brief: French statutory rate
A68: Interest cap: % of tax EBITDA | B68: % | C68: 0.3 | I68: Case brief: French interest limitation (EBITDA approximates tax EBITDA)
A69: Interest cap: safe harbour | B69: €m | C69: 3 | I69: Case brief
A70: Exit costs (% of exit EV) | B70: % | C70: 0.015 | I70: Case brief
A72: 6. Add-on acquisitions
A73: Assumption | B73: Unit | D73: Add-on A (DE) | E73: Add-on B (US)
A74: Acquisition year (closes 1 January) | B74: year | D74: 2028 | E74: 2029 | I74: ARCHIMED plan: A in year 2 (after 100-day plan), B in year 3
A75: Revenue in the year before acquisition | B75: €m | D75: 28 | E75: 18 | I75: Case brief: add-on pipeline
A76: Revenue growth after acquisition | B76: % | D76: 0.04 | E76: 0.12 | I76: A: mature ELISA menu; B: US autoimmune and allergy growth
A77: Standalone EBITDA margin | B77: % | D77: 0.22 | E77: 0.2 | I77: Case brief
A78: Purchase multiple (EV / pre-acquisition EBITDA) | B78: x | D78: 8 | E78: 10 | I78: Case brief price indications
A79: Deal costs (% of EV) | B79: % | D79: 0.03 | E79: 0.03 | I79: Assumption
A80: One-off integration costs (acquisition year) | B80: €m | D80: 2.5 | E80: 1.5 | I80: Assumption: A plant transfer and IVDR file migration; B systems
A81: Run-rate cost synergies | B81: €m | D81: 1.8 | E81: 0.5 | I81: A: manufacturing in Lyon, procurement, DACH sales overlap; B: back office. Revenue synergies excluded
A82: Synergy phasing – year 1 | B82: % | D82: 0.25 | E82: 0.5 | I82: Assumption
A83: Synergy phasing – year 2 | B83: % | D83: 0.75 | E83: 1 | I83: Assumption
A84: Synergy phasing – year 3 onwards | B84: % | D84: 1 | E84: 1 | I84: Assumption
A85: Purchase enterprise value | B85: €m | D85: =D87*D78 -> 49.28 | E85: =E87*E78 -> 36
A86: Purchase price incl. deal costs | B86: €m | D86: =D85*(1+D79) -> 50.7584 | E86: =E85*(1+E79) -> 37.08
A87: Pre-acquisition EBITDA | B87: €m | D87: =D75*D77 -> 6.16 | E87: =E75*E77 -> 3.6

Sheet Case_Data
A1: Project Lumière – case data from the information memo
A2: Fictional company. All figures as given in the case brief; €m, financial year to December.
A4: Historical P&L
A5: €m | B5: Unit | C5: FY2022A | D5: FY2023A | E5: FY2024A | F5: FY2025A | G5: FY2026E
A6: Revenue – autoimmunity | B6: €m | C6: 72 | D6: 78 | E6: 84 | F6: 89.9 | G6: 96
A7: Revenue – allergy | B7: €m | C7: 33.5 | D7: 35 | E7: 37 | F7: 39.6 | G7: 42
A8: Revenue – other serology | B8: €m | C8: 10.3 | D8: 10.9 | E8: 11.4 | F8: 11.4 | G8: 12
A9: Total revenue | B9: €m | C9: =SUM(C6:C8) -> 115.8 | D9: =SUM(D6:D8) -> 123.9 | E9: =SUM(E6:E8) -> 132.4 | F9: =SUM(F6:F8) -> 140.9 | G9: =SUM(G6:G8) -> 150
A10: Revenue growth | B10: % | D10: =D9/C9-1 -> 0.069948187 | E10: =E9/D9-1 -> 0.068603713 | F10: =F9/E9-1 -> 0.064199396 | G10: =G9/F9-1 -> 0.064584812
A11: Gross profit | B11: €m | C11: 70.6 | D11: 76 | E11: 81.6 | F11: 87.1 | G11: 93 | I11: Information memo; reagent gross margins improve with the shift to automated CLIA
A12: Gross margin | B12: % | C12: =C11/C9 -> 0.60967185 | D12: =D11/D9 -> 0.6133979 | E12: =E11/E9 -> 0.6163142 | F12: =F11/F9 -> 0.61816891 | G12: =G11/G9 -> 0.62
A13: Sales and marketing | B13: €m | C13: -23.4 | D13: -24.9 | E13: -26.4 | F13: -27.9 | G13: -29.7
A14: R&D (expensed) | B14: €m | C14: -8 | D14: -8.5 | E14: -8.9 | F14: -9.3 | G14: -9.8
A15: G&A | B15: €m | C15: -9.8 | D15: -10.6 | E15: -11 | F15: -11.3 | G15: -11.6
A16: Reported EBITDA (IFRS 16) | B16: €m | C16: =C11+C13+C14+C15 -> 29.4 | D16: =D11+D13+D14+D15 -> 32 | E16: =E11+E13+E14+E15 -> 35.3 | F16: =F11+F13+F14+F15 -> 38.6 | G16: =G11+G13+G14+G15 -> 41.9
A17: Reported EBITDA margin | B17: % | C17: =C16/C9 -> 0.25388601 | D17: =D16/D9 -> 0.2582728 | E17: =E16/E9 -> 0.26661631 | F17: =F16/F9 -> 0.27395316 | G17: =G16/G9 -> 0.27933333
A19: EBITDA bridge: vendor presentation vs. ARCHIMED underwriting
A20: €m | B20: Unit | C20: FY2022A | D20: FY2023A | E20: FY2024A | F20: FY2025A | G20: FY2026E
A21: Reported EBITDA (IFRS 16) | B21: €m | C21: =C16 -> 29.4 | D21: =D16 -> 32 | E21: =E16 -> 35.3 | F21: =F16 -> 38.6 | G21: =G16 -> 41.9
A22: Vendor add-back: IVDR remediation ("one-off") | B22: €m | C22: 0.4 | D22: 0.9 | E22: 1.4 | F22: 1.5 | G22: 1.6 | I22: Vendor adds back IVDR costs every year; 45 assays still to certify by end-2028/2029
A23: Vendor Adjusted EBITDA | B23: €m | C23: =C21+C22 -> 29.8 | D23: =D21+D22 -> 32.9 | E23: =E21+E22 -> 36.7 | F23: =F21+F22 -> 40.1 | G23: =G21+G22 -> 43.5
A24: Vendor Adjusted EBITDA margin | B24: % | C24: =C23/C9 -> 0.25734024 | D24: =D23/D9 -> 0.26553672 | E24: =E23/E9 -> 0.27719033 | F24: =F23/F9 -> 0.28459901 | G24: =G23/G9 -> 0.29
A25: ARCHIMED: reverse IVDR add-back (cost recurs until 2029) | B25: €m | C25: =-C22 -> -0.4 | D25: =-D22 -> -0.9 | E25: =-E22 -> -1.4 | F25: =-F22 -> -1.5 | G25: =-G22 -> -1.6 | I25: ARCHIMED view: a cost incurred five years running is recurring until the transition ends
A26: ARCHIMED: IFRS 16 lease costs (restate to pre-IFRS 16) | B26: €m | C26: -1 | D26: -1.1 | E26: -1.2 | F26: -1.2 | G26: -1.3 | I26: Information memo note: plant, office and car leases; lenders and peers use pre-IFRS 16 EBITDA
A27: ARCHIMED: standalone costs (market-rate CEO, CFO, board) | B27: €m | C27: -0.6 | D27: -0.6 | E27: -0.6 | F27: -0.6 | G27: -0.6 | I27: Information memo note: founder paid €0.4m; replacement team costs c.€0.6m more a year
A28: Underwritten EBITDA (pre-IFRS 16, fully loaded) | B28: €m | C28: =C23+C25+C26+C27 -> 27.8 | D28: =D23+D25+D26+D27 -> 30.3 | E28: =E23+E25+E26+E27 -> 33.5 | F28: =F23+F25+F26+F27 -> 36.8 | G28: =G23+G25+G26+G27 -> 40
A29: Underwritten EBITDA margin | B29: % | C29: =C28/C9 -> 0.24006908 | D29: =D28/D9 -> 0.24455206 | E29: =E28/E9 -> 0.25302115 | F29: =F28/F9 -> 0.26117814 | G29: =G28/G9 -> 0.26666667
A30: Vendor Adjusted minus underwritten EBITDA | B30: €m | C30: =C23-C28 -> 2 | D30: =D23-D28 -> 2.6 | E30: =E23-E28 -> 3.2 | F30: =F23-F28 -> 3.3 | G30: =G23-G28 -> 3.5
A32: Cash flow items
A33: €m | B33: Unit | C33: FY2022A | D33: FY2023A | E33: FY2024A | F33: FY2025A | G33: FY2026E
A34: Capex incl. placed analyzers and capitalised R&D | B34: €m | C34: 6.9 | D34: 7.4 | E34: 7.9 | F34: 8.4 | G34: 8.9
A35: Capex, % of revenue | B35: % | C35: =C34/C9 -> 0.059585492 | D35: =D34/D9 -> 0.059725585 | E35: =E34/E9 -> 0.059667674 | F35: =F34/F9 -> 0.059616749 | G35: =G34/G9 -> 0.059333333
A36: Net working capital | B36: €m | C36: 25 | D36: 27.4 | E36: 29.7 | F36: 31 | G36: 33
A37: Net working capital, % of revenue | B37: % | C37: =C36/C9 -> 0.21588946 | D37: =D36/D9 -> 0.22114609 | E37: =E36/E9 -> 0.22432024 | F37: =F36/F9 -> 0.22001419 | G37: =G36/G9 -> 0.22
A38: Cash conversion: (underwritten EBITDA – capex – ΔNWC) / EBITDA | B38: % | D38: =(D28-D34-(D36-C36))/D28 -> 0.67656766 | E38: =(E28-E34-(E36-D36))/E28 -> 0.69552239 | F38: =(F28-F34-(F36-E36))/F28 -> 0.73641304 | G38: =(G28-G34-(G36-F36))/G28 -> 0.7275
A40: Management business plan (vendor case, no M&A)
A41: €m | B41: Unit | C41: FY2027 | D41: FY2028 | E41: FY2029 | F41: FY2030 | G41: FY2031
A42: Revenue growth | B42: % | C42: 0.1 | D42: 0.11 | E42: 0.115 | F42: 0.115 | G42: 0.11 | I42: Drivers: US push (30 new FDA submissions), next-gen CLIA analyzer in 2028, price, automation
A43: Revenue | B43: €m | C43: =$G$9*(1+C42) -> 165 | D43: =C43*(1+D42) -> 183.15 | E43: =D43*(1+E42) -> 204.21225 | F43: =E43*(1+F42) -> 227.69666 | G43: =F43*(1+G42) -> 252.74329
A44: Adjusted EBITDA margin (vendor definition) | B44: % | C44: 0.303 | D44: 0.318 | E44: 0.333 | F44: 0.343 | G44: 0.348
A45: Adjusted EBITDA (vendor definition) | B45: €m | C45: =C43*C44 -> 49.995 | D45: =D43*D44 -> 58.2417 | E45: =E43*E44 -> 68.002679 | F45: =F43*F44 -> 78.099954 | G45: =G43*G44 -> 87.954665
A47: Operating KPIs and revenue mix (FY2026E)
A48: KPI | B48: Unit | C48: FY2026E
A49: Installed base – total analyzers | B49: # | C49: 2350
A50: of which automated CLIA analyzers | B50: # | C50: 950
A51: of which legacy ELISA / immunoblot processors | B51: # | C51: =C49-C50 -> 1400
A52: Assay menu | B52: # | C52: 185
A53: Assays certified under IVDR | B53: # | C53: 140
A54: Assays cleared by the FDA | B54: # | C54: 22
A55: Employees (FTE) | B55: # | C55: 620
A56: Recurring revenue share | B56: % | C56: 0.9
A57: Top-10 customers, share of revenue | B57: % | C57: 0.27
A58: Largest customer, share of revenue | B58: % | C58: 0.07
A60: Revenue by geography – France | B60: % | C60: 0.34
A61: Revenue by geography – DACH | B61: % | C61: 0.17
A62: Revenue by geography – Italy | B62: % | C62: 0.12
A63: Revenue by geography – Iberia | B63: % | C63: 0.09
A64: Revenue by geography – rest of Europe | B64: % | C64: 0.11
... A66: Revenue by geography – rest of world (distributors) | B66: % | C66: 0.12
A67: Total geography | B67: % | C67: =SUM(C60:C66) -> 1
A69: Revenue by type – reagents and consumables | B69: % | C69: 0.81
A70: Revenue by type – service and other | B70: % | C70: 0.12
A71: Revenue by type – instruments | B71: % | C71: 0.07
A72: Total revenue by type | B72: % | C72: =SUM(C69:C71) -> 1

Sheet Transaction
A1: Project Lumière – sources and uses at closing (31 December 2026)
A2: €m unless stated. All cells are formulas driven by the Inputs sheet.
A4: Uses | C4: €m | D4: % of total
A5: Enterprise value (cash-free, debt-free) | B5: €m | C5: =Inputs!C10 -> 540 | D5: =C5/$C$9 -> 0.95036959
A6: Transaction costs (M&A, due diligence, legal, W&I) | B6: €m | C6: =Inputs!C16*C5 -> 10.8 | D6: =C6/$C$9 -> 0.019007392
A7: Financing fees (unitranche, CAF and RCF upfront fees) | B7: €m | C7: =Inputs!C29*Inputs!C30+(Inputs!C31+Inputs!C32)*Inputs!C33 -> 7.4 | D7: =C7/$C$9 -> 0.013023583
A8: Cash funded to the balance sheet | B8: €m | C8: =Inputs!C17 -> 10 | D8: =C8/$C$9 -> 0.017599437
A9: Total uses | B9: €m | C9: =SUM(C5:C8) -> 568.2 | D9: =SUM(D5:D8) -> 1
A11: Sources
A12: Unitranche | B12: €m | C12: =Inputs!C29 -> 240 | D12: =C12/$C$16 -> 0.42238648
A13: Founder rollover | B13: €m | C13: =Inputs!C18 -> 40 | D13: =C13/$C$16 -> 0.070397747
A14: Management rollover | B14: €m | C14: =Inputs!C19 -> 6 | D14: =C14/$C$16 -> 0.010559662
A15: ARCHIMED equity (MED Platform II and co-investors) | B15: €m | C15: =C9-C12-C13-C14 -> 282.2 | D15: =C15/$C$16 -> 0.49665611 | E15: Plug: total uses less debt and rollovers
A16: Total sources | B16: €m | C16: =SUM(C12:C15) -> 568.2 | D16: =SUM(D12:D15) -> 1
A17: Check: sources minus uses (should be 0) | C17: =C16-C9 -> 0
A19: Equity and ownership (before MIP dilution)
A20: Total equity invested | B20: €m | C20: =C13+C14+C15 -> 328.2 | D20: =SUM(D21:D23) -> 1
A21: ARCHIMED | B21: €m | C21: =C15 -> 282.2 | D21: =C21/$C$20 -> 0.85984156 | E21: All holders invest in the same strip; management MIP comes on top (see Inputs C20)
A22: Founder | B22: €m | C22: =C13 -> 40 | D22: =C22/$C$20 -> 0.1218769
A23: Management | B23: €m | C23: =C14 -> 6 | D23: =C23/$C$20 -> 0.018281536
A25: Entry metrics
A26: EV / underwritten FY2026E EBITDA | B26: x | C26: =C5/Inputs!C8 -> 13.5
A27: EV / vendor Adjusted FY2026E EBITDA | B27: x | C27: =C5/Inputs!C7 -> 12.413793
A28: EV / FY2026E revenue | B28: x | C28: =C5/Inputs!C5 -> 3.6
A29: Unitranche / underwritten EBITDA | B29: x | C29: =C12/Inputs!C8 -> 6
A30: Net debt at closing / underwritten EBITDA | B30: x | C30: =(C12-C8)/Inputs!C8 -> 5.75
A31: Equity / total sources | B31: % | C31: =C20/C16 -> 0.57761352
A32: Unitranche / EV (loan-to-value) | B32: % | C32: =C12/C5 -> 0.44444444
A33: Total fees / EV | B33: % | C33: =(C6+C7)/C5 -> 0.033703704

Sheet LBO_Base
A1: Project Lumière – LBO model: Base (ARCHIMED) case
A2: €m unless stated · financial year to December · closing 31 December 2026 · exit 31 December 2031
A3: Case index (1 = Base, 2 = Management, 3 = Downside) | C3: 1
A5: €m | B5: Unit | C5: FY2026E | D5: FY2027 | E5: FY2028 | F5: FY2029 | G5: FY2030 | H5: FY2031
A6: Years from closing | C6: 0 | D6: =C6+1 -> 1 | E6: =D6+1 -> 2 | F6: =E6+1 -> 3 | G6: =F6+1 -> 4 | H6: =G6+1 -> 5
A7: Financial year | C7: 2026 | D7: =C7+1 -> 2027 | E7: =D7+1 -> 2028 | F7: =E7+1 -> 2029 | G7: =F7+1 -> 2030 | H7: =G7+1 -> 2031
A9: Revenue
A10: Organic revenue growth | B10: % | D10: =INDEX(Inputs!D$45:D$47,$C$3)+Inputs!$C$52 -> 0.075 | E10: =INDEX(Inputs!E$45:E$47,$C$3)+Inputs!$C$52 -> 0.08 | F10: =INDEX(Inputs!F$45:F$47,$C$3)+Inputs!$C$52 -> 0.085 | G10: =INDEX(Inputs!G$45:G$47,$C$3)+Inputs!$C$52 -> 0.085 | H10: =INDEX(Inputs!H$45:H$47,$C$3)+Inputs!$C$52 -> 0.08 | I10: Inputs rows 45–47 picked by case index, plus the flex delta
A11: Organic revenue | B11: €m | C11: =Inputs!$C$5 -> 150 | D11: =C11*(1+D10) -> 161.25 | E11: =D11*(1+E10) -> 174.15 | F11: =E11*(1+F10) -> 188.95275 | G11: =F11*(1+G10) -> 205.01373 | H11: =G11*(1+H10) -> 221.41483
A12: Add-on A revenue (Germany) | B12: €m | C12: 0 | D12: =IF(AND(INDEX(Inputs!$D$57:$F$57,$C$3)=1,D$7>=Inputs!$D$74),Inputs!$D$75*(1+Inputs!$D$76)^(D$7-Inputs!$D$74+1),0) -> 0 | E12: =IF(AND(INDEX(Inputs!$D$57:$F$57,$C$3)=1,E$7>=Inputs!$D$74),Inputs!$D$75*(1+Inputs!$D$76)^(E$7-Inputs!$D$74+1),0) -> 29.12 | F12: =IF(AND(INDEX(Inputs!$D$57:$F$57,$C$3)=1,F$7>=Inputs!$D$74),Inputs!$D$75*(1+Inputs!$D$76)^(F$7-Inputs!$D$74+1),0) -> 30.2848 | G12: =IF(AND(INDEX(Inputs!$D$57:$F$57,$C$3)=1,G$7>=Inputs!$D$74),Inputs!$D$75*(1+Inputs!$D$76)^(G$7-Inputs!$D$74+1),0) -> 31.496192 | H12: =IF(AND(INDEX(Inputs!$D$57:$F$57,$C$3)=1,H$7>=Inputs!$D$74),Inputs!$D$75*(1+Inputs!$D$76)^(H$7-Inputs!$D$74+1),0) -> 32.75604 | I12: Consolidated from 1 January of the acquisition year
A13: Add-on B revenue (US) | B13: €m | C13: 0 | D13: =IF(AND(INDEX(Inputs!$D$58:$F$58,$C$3)=1,D$7>=Inputs!$E$74),Inputs!$E$75*(1+Inputs!$E$76)^(D$7-Inputs!$E$74+1),0) -> 0 | E13: =IF(AND(INDEX(Inputs!$D$58:$F$58,$C$3)=1,E$7>=Inputs!$E$74),Inputs!$E$75*(1+Inputs!$E$76)^(E$7-Inputs!$E$74+1),0) -> 0 | F13: =IF(AND(INDEX(Inputs!$D$58:$F$58,$C$3)=1,F$7>=Inputs!$E$74),Inputs!$E$75*(1+Inputs!$E$76)^(F$7-Inputs!$E$74+1),0) -> 20.16 | G13: =IF(AND(INDEX(Inputs!$D$58:$F$58,$C$3)=1,G$7>=Inputs!$E$74),Inputs!$E$75*(1+Inputs!$E$76)^(G$7-Inputs!$E$74+1),0) -> 22.5792 | H13: =IF(AND(INDEX(Inputs!$D$58:$F$58,$C$3)=1,H$7>=Inputs!$E$74),Inputs!$E$75*(1+Inputs!$E$76)^(H$7-Inputs!$E$74+1),0) -> 25.288704
A14: Total revenue | B14: €m | C14: =SUM(C11:C13) -> 150 | D14: =SUM(D11:D13) -> 161.25 | E14: =SUM(E11:E13) -> 203.27 | F14: =SUM(F11:F13) -> 239.39755 | G14: =SUM(G11:G13) -> 259.08913 | H14: =SUM(H11:H13) -> 279.45958
A15: Total revenue growth | B15: % | D15: =D14/C14-1 -> 0.075 | E15: =E14/D14-1 -> 0.26058915 | F15: =F14/E14-1 -> 0.17773183 | G15: =G14/F14-1 -> 0.082254709 | H15: =H14/G14-1 -> 0.078623332
A17: EBITDA (ARCHIMED definition: pre-IFRS 16, fully loaded)
A18: Organic EBITDA margin | B18: % | C18: =C19/C11 -> 0.26666667 | D18: =INDEX(Inputs!D$48:D$50,$C$3)+Inputs!$C$53 -> 0.275 | E18: =INDEX(Inputs!E$48:E$50,$C$3)+Inputs!$C$53 -> 0.284 | F18: =INDEX(Inputs!F$48:F$50,$C$3)+Inputs!$C$53 -> 0.293 | G18: =INDEX(Inputs!G$48:G$50,$C$3)+Inputs!$C$53 -> 0.301 | H18: =INDEX(Inputs!H$48:H$50,$C$3)+Inputs!$C$53 -> 0.308
A19: Organic EBITDA | B19: €m | C19: =Inputs!$C$8 -> 40 | D19: =D11*D18 -> 44.34375 | E19: =E11*E18 -> 49.4586 | F19: =F11*F18 -> 55.363156 | G19: =G11*G18 -> 61.709134 | H19: =H11*H18 -> 68.195768
A20: Add-on A EBITDA (standalone) | B20: €m | C20: 0 | D20: =D12*Inputs!$D$77 -> 0 | E20: =E12*Inputs!$D$77 -> 6.4064 | F20: =F12*Inputs!$D$77 -> 6.662656 | G20: =G12*Inputs!$D$77 -> 6.9291622 | H20: =H12*Inputs!$D$77 -> 7.2063287
A21: Add-on A cost synergies | B21: €m | C21: 0 | D21: =IF(D12>0,Inputs!$D$81*IF(D$7-Inputs!$D$74=0,Inputs!$D$82,IF(D$7-Inputs!$D$74=1,Inputs!$D$83,Inputs!$D$84)),0) -> 0 | E21: =IF(E12>0,Inputs!$D$81*IF(E$7-Inputs!$D$74=0,Inputs!$D$82,IF(E$7-Inputs!$D$74=1,Inputs!$D$83,Inputs!$D$84)),0) -> 0.45 | F21: =IF(F12>0,Inputs!$D$81*IF(F$7-Inputs!$D$74=0,Inputs!$D$82,IF(F$7-Inputs!$D$74=1,Inputs!$D$83,Inputs!$D$84)),0) -> 1.35 | G21: =IF(G12>0,Inputs!$D$81*IF(G$7-Inputs!$D$74=0,Inputs!$D$82,IF(G$7-Inputs!$D$74=1,Inputs!$D$83,Inputs!$D$84)),0) -> 1.8 | H21: =IF(H12>0,Inputs!$D$81*IF(H$7-Inputs!$D$74=0,Inputs!$D$82,IF(H$7-Inputs!$D$74=1,Inputs!$D$83,Inputs!$D$84)),0) -> 1.8
A22: Add-on B EBITDA (standalone) | B22: €m | C22: 0 | D22: =D13*Inputs!$E$77 -> 0 | E22: =E13*Inputs!$E$77 -> 0 | F22: =F13*Inputs!$E$77 -> 4.032 | G22: =G13*Inputs!$E$77 -> 4.51584 | H22: =H13*Inputs!$E$77 -> 5.0577408
A23: Add-on B cost synergies | B23: €m | C23: 0 | D23: =IF(D13>0,Inputs!$E$81*IF(D$7-Inputs!$E$74=0,Inputs!$E$82,IF(D$7-Inputs!$E$74=1,Inputs!$E$83,Inputs!$E$84)),0) -> 0 | E23: =IF(E13>0,Inputs!$E$81*IF(E$7-Inputs!$E$74=0,Inputs!$E$82,IF(E$7-Inputs!$E$74=1,Inputs!$E$83,Inputs!$E$84)),0) -> 0 | F23: =IF(F13>0,Inputs!$E$81*IF(F$7-Inputs!$E$74=0,Inputs!$E$82,IF(F$7-Inputs!$E$74=1,Inputs!$E$83,Inputs!$E$84)),0) -> 0.25 | G23: =IF(G13>0,Inputs!$E$81*IF(G$7-Inputs!$E$74=0,Inputs!$E$82,IF(G$7-Inputs!$E$74=1,Inputs!$E$83,Inputs!$E$84)),0) -> 0.5 | H23: =IF(H13>0,Inputs!$E$81*IF(H$7-Inputs!$E$74=0,Inputs!$E$82,IF(H$7-Inputs!$E$74=1,Inputs!$E$83,Inputs!$E$84)),0) -> 0.5
A24: Total EBITDA | B24: €m | C24: =SUM(C19:C23) -> 40 | D24: =SUM(D19:D23) -> 44.34375 | E24: =SUM(E19:E23) -> 56.315 | F24: =SUM(F19:F23) -> 67.657812 | G24: =SUM(G19:G23) -> 75.454136 | H24: =SUM(H19:H23) -> 82.759838
A25: EBITDA margin | B25: % | C25: =C24/C14 -> 0.26666667 | D25: =D24/D14 -> 0.275 | E25: =E24/E14 -> 0.27704531 | F25: =F24/F14 -> 0.28261698 | G25: =G24/G14 -> 0.29122849 | H25: =H24/H14 -> 0.29614243
A26: EBITDA growth | B26: % | D26: =D24/C24-1 -> 0.10859375 | E26: =E24/D24-1 -> 0.26996476 | F26: =F24/E24-1 -> 0.20141724 | G26: =G24/F24-1 -> 0.1152317 | H26: =H24/G24-1 -> 0.09682308
A28: Free cash flow
A29: EBITDA | B29: €m | D29: =D24 -> 44.34375 | E29: =E24 -> 56.315 | F29: =F24 -> 67.657812 | G29: =G24 -> 75.454136 | H29: =H24 -> 82.759838
A30: One-off integration costs | B30: €m | D30: =-(IF(AND(INDEX(Inputs!$D$57:$F$57,$C$3)=1,D$7=Inputs!$D$74),Inputs!$D$80,0)+IF(AND(INDEX(Inputs!$D$58:$F$58,$C$3)=1,D$7=Inputs!$E$74),Inputs!$E$80,0)) -> 0 | E30: =-(IF(AND(INDEX(Inputs!$D$57:$F$57,$C$3)=1,E$7=Inputs!$D$74),Inputs!$D$80,0)+IF(AND(INDEX(Inputs!$D$58:$F$58,$C$3)=1,E$7=Inputs!$E$74),Inputs!$E$80,0)) -> -2.5 | F30: =-(IF(AND(INDEX(Inputs!$D$57:$F$57,$C$3)=1,F$7=Inputs!$D$74),Inputs!$D$80,0)+IF(AND(INDEX(Inputs!$D$58:$F$58,$C$3)=1,F$7=Inputs!$E$74),Inputs!$E$80,0)) -> -1.5 | G30: =-(IF(AND(INDEX(Inputs!$D$57:$F$57,$C$3)=1,G$7=Inputs!$D$74),Inputs!$D$80,0)+IF(AND(INDEX(Inputs!$D$58:$F$58,$C$3)=1,G$7=Inputs!$E$74),Inputs!$E$80,0)) -> 0 | H30: =-(IF(AND(INDEX(Inputs!$D$57:$F$57,$C$3)=1,H$7=Inputs!$D$74),Inputs!$D$80,0)+IF(AND(INDEX(Inputs!$D$58:$F$58,$C$3)=1,H$7=Inputs!$E$74),Inputs!$E$80,0)) -> 0
A31: Maintenance and placed-analyzer capex | B31: €m | D31: =-D14*Inputs!$C$63 -> -6.45 | E31: =-E14*Inputs!$C$63 -> -8.1308 | F31: =-F14*Inputs!$C$63 -> -9.575902 | G31: =-G14*Inputs!$C$63 -> -10.363565 | H31: =-H14*Inputs!$C$63 -> -11.178383
A32: Capitalised R&D | B32: €m | D32: =-D14*Inputs!$C$64 -> -2.41875 | E32: =-E14*Inputs!$C$64 -> -3.04905 | F32: =-F14*Inputs!$C$64 -> -3.5909633 | G32: =-G14*Inputs!$C$64 -> -3.8863369 | H32: =-H14*Inputs!$C$64 -> -4.1918936
A33: Growth capex | B33: €m | D33: =-Inputs!D$65 -> -5 | E33: =-Inputs!E$65 -> -4 | F33: =-Inputs!F$65 -> -2 | G33: =-Inputs!G$65 -> 0 | H33: =-Inputs!H$65 -> 0
A34: Change in net working capital | B34: €m | D34: =-(D57-C57-D58) -> -2.475 | E34: =-(E57-D57-E58) -> -3.0844 | F34: =-(F57-E57-F58) -> -3.988061 | G34: =-(G57-F57-G58) -> -4.3321467 | H34: =-(H57-G57-H58) -> -4.4814991 | I34: Excludes the working capital bought with add-ons (paid for in the purchase price)
A35: Cash taxes | B35: €m | D35: =-D54 -> -5.7445312 | E35: =-E54 -> -6.68925 | F35: =-F54 -> -8.4726477 | G35: =-G54 -> -9.9658597 | H35: =-H54 -> -10.989727
A36: Net interest expense | B36: €m | D36: =-D86 -> -18.29875 | E36: =-E86 -> -20.614005 | F36: =-F86 -> -21.943744 | G36: =-G86 -> -20.824156 | H36: =-H86 -> -19.063616
A37: Free cash flow | B37: €m | D37: =SUM(D29:D36) -> 3.9567187 | E37: =SUM(E29:E36) -> 8.2474949 | F37: =SUM(F29:F36) -> 16.586494 | G37: =SUM(G29:G36) -> 26.082072 | H37: =SUM(H29:H36) -> 32.854719
A38: Earn-out paid to the vendor | B38: €m | D38: =-IF(D$7=Inputs!$C$23,$C$137,0) -> 0 | E38: =-IF(E$7=Inputs!$C$23,$C$137,0) -> 0 | F38: =-IF(F$7=Inputs!$C$23,$C$137,0) -> 0 | G38: =-IF(G$7=Inputs!$C$23,$C$137,0) -> 0 | H38: =-IF(H$7=Inputs!$C$23,$C$137,0) -> 0 | I38: Paid by the company in the payment year; reduces debt paydown
A39: Add-on acquisitions incl. deal costs | B39: €m | D39: =-(IF(AND(INDEX(Inputs!$D$57:$F$57,$C$3)=1,D$7=Inputs!$D$74),Inputs!$D$86,0)+IF(AND(INDEX(Inputs!$D$58:$F$58,$C$3)=1,D$7=Inputs!$E$74),Inputs!$E$86,0)) -> 0 | E39: =-(IF(AND(INDEX(Inputs!$D$57:$F$57,$C$3)=1,E$7=Inputs!$D$74),Inputs!$D$86,0)+IF(AND(INDEX(Inputs!$D$58:$F$58,$C$3)=1,E$7=Inputs!$E$74),Inputs!$E$86,0)) -> -50.7584 | F39: =-(IF(AND(INDEX(Inputs!$D$57:$F$57,$C$3)=1,F$7=Inputs!$D$74),Inputs!$D$86,0)+IF(AND(INDEX(Inputs!$D$58:$F$58,$C$3)=1,F$7=Inputs!$E$74),Inputs!$E$86,0)) -> -37.08 | G39: =-(IF(AND(INDEX(Inputs!$D$57:$F$57,$C$3)=1,G$7=Inputs!$D$74),Inputs!$D$86,0)+IF(AND(INDEX(Inputs!$D$58:$F$58,$C$3)=1,G$7=Inputs!$E$74),Inputs!$E$86,0)) -> 0 | H39: =-(IF(AND(INDEX(Inputs!$D$57:$F$57,$C$3)=1,H$7=Inputs!$D$74),Inputs!$D$86,0)+IF(AND(INDEX(Inputs!$D$58:$F$58,$C$3)=1,H$7=Inputs!$E$74),Inputs!$E$86,0)) -> 0
A40: Cash flow before debt movements | B40: €m | D40: =D37+D38+D39 -> 3.9567187 | E40: =E37+E38+E39 -> -42.510905 | F40: =F37+F38+F39 -> -20.493506 | G40: =G37+G38+G39 -> 26.082072 | H40: =H37+H38+H39 -> 32.854719
A41: Cash conversion: (EBITDA – capex – ΔNWC) / EBITDA | B41: % | D41: =(D29+D31+D32+D33+D34)/D29 -> 0.63143058 | E41: =(E29+E31+E32+E33+E34)/E29 -> 0.675677 | F41: =(F29+F31+F32+F33+F34)/F29 -> 0.71688522 | G41: =(G29+G31+G32+G33+G34)/G29 -> 0.75373055 | H41: =(H29+H31+H32+H33+H34)/H29 -> 0.7601279
A43: Corporate tax (French interest cap)
A44: EBITDA | B44: €m | D44: =D24 -> 44.34375 | E44: =E24 -> 56.315 | F44: =F24 -> 67.657812 | G44: =G24 -> 75.454136 | H44: =H24 -> 82.759838
A45: One-off integration costs | B45: €m | D45: =D30 -> 0 | E45: =E30 -> -2.5 | F45: =F30 -> -1.5 | G45: =G30 -> 0 | H45: =H30 -> 0
A46: Depreciation and amortisation | B46: €m | D46: =-D14*Inputs!$C$62 -> -8.0625 | E46: =-E14*Inputs!$C$62 -> -10.1635 | F46: =-F14*Inputs!$C$62 -> -11.969878 | G46: =-G14*Inputs!$C$62 -> -12.954456 | H46: =-H14*Inputs!$C$62 -> -13.972979
A47: EBIT | B47: €m | D47: =SUM(D44:D46) -> 36.28125 | E47: =SUM(E44:E46) -> 43.6515 | F47: =SUM(F44:F46) -> 54.187934 | G47: =SUM(G44:G46) -> 62.49968 | H47: =SUM(H44:H46) -> 68.786859
A48: Net interest expense | B48: €m | D48: =D86 -> 18.29875 | E48: =E86 -> 20.614005 | F48: =F86 -> 21.943744 | G48: =G86 -> 20.824156 | H48: =H86 -> 19.063616
A49: Interest deduction capacity (higher of 30% of EBITDA or €3m) | B49: €m | D49: =MAX(Inputs!$C$69,Inputs!$C$68*D44) -> 13.303125 | E49: =MAX(Inputs!$C$69,Inputs!$C$68*E44) -> 16.8945 | F49: =MAX(Inputs!$C$69,Inputs!$C$68*F44) -> 20.297344 | G49: =MAX(Inputs!$C$69,Inputs!$C$68*G44) -> 22.636241 | H49: =MAX(Inputs!$C$69,Inputs!$C$68*H44) -> 24.827951 | I49: French rule: net interest deductible up to the higher of 30% of tax EBITDA or €3m; excess carried forward
A50: Disallowed interest brought forward | B50: €m | D50: =C52 -> 0 | E50: =D52 -> 4.995625 | F50: =E52 -> 8.7151301 | G50: =F52 -> 10.361531 | H50: =G52 -> 8.5494458
A51: Deductible interest | B51: €m | D51: =MAX(0,MIN(D48+D50,D49)) -> 13.303125 | E51: =MAX(0,MIN(E48+E50,E49)) -> 16.8945 | F51: =MAX(0,MIN(F48+F50,F49)) -> 20.297344 | G51: =MAX(0,MIN(G48+G50,G49)) -> 22.636241 | H51: =MAX(0,MIN(H48+H50,H49)) -> 24.827951
A52: Disallowed interest carried forward | B52: €m | C52: 0 | D52: =MAX(0,D48+D50-D51) -> 4.995625 | E52: =MAX(0,E48+E50-E51) -> 8.7151301 | F52: =MAX(0,F48+F50-F51) -> 10.361531 | G52: =MAX(0,G48+G50-G51) -> 8.5494458 | H52: =MAX(0,H48+H50-H51) -> 2.7851104
A53: Taxable income | B53: €m | D53: =MAX(0,D47-D51) -> 22.978125 | E53: =MAX(0,E47-E51) -> 26.757 | F53: =MAX(0,F47-F51) -> 33.890591 | G53: =MAX(0,G47-G51) -> 39.863439 | H53: =MAX(0,H47-H51) -> 43.958908
A54: Cash tax | B54: €m | D54: =D53*Inputs!$C$67 -> 5.7445312 | E54: =E53*Inputs!$C$67 -> 6.68925 | F54: =F53*Inputs!$C$67 -> 8.4726477 | G54: =G53*Inputs!$C$67 -> 9.9658597 | H54: =H53*Inputs!$C$67 -> 10.989727
A56: Net working capital (memo)
A57: Net working capital | B57: €m | C57: =C14*Inputs!$C$66 -> 33 | D57: =D14*Inputs!$C$66 -> 35.475 | E57: =E14*Inputs!$C$66 -> 44.7194 | F57: =F14*Inputs!$C$66 -> 52.667461 | G57: =G14*Inputs!$C$66 -> 56.999608 | H57: =H14*Inputs!$C$66 -> 61.481107
A58: Net working capital acquired with add-ons | B58: €m | D58: =(IF(AND(INDEX(Inputs!$D$57:$F$57,$C$3)=1,D$7=Inputs!$D$74),Inputs!$D$75,0)+IF(AND(INDEX(Inputs!$D$58:$F$58,$C$3)=1,D$7=Inputs!$E$74),Inputs!$E$75,0))*Inputs!$C$66 -> 0 | E58: =(IF(AND(INDEX(Inputs!$D$57:$F$57,$C$3)=1,E$7=Inputs!$D$74),Inputs!$D$75,0)+IF(AND(INDEX(Inputs!$D$58:$F$58,$C$3)=1,E$7=Inputs!$E$74),Inputs!$E$75,0))*Inputs!$C$66 -> 6.16 | F58: =(IF(AND(INDEX(Inputs!$D$57:$F$57,$C$3)=1,F$7=Inputs!$D$74),Inputs!$D$75,0)+IF(AND(INDEX(Inputs!$D$58:$F$58,$C$3)=1,F$7=Inputs!$E$74),Inputs!$E$75,0))*Inputs!$C$66 -> 3.96 | G58: =(IF(AND(INDEX(Inputs!$D$57:$F$57,$C$3)=1,G$7=Inputs!$D$74),Inputs!$D$75,0)+IF(AND(INDEX(Inputs!$D$58:$F$58,$C$3)=1,G$7=Inputs!$E$74),Inputs!$E$75,0))*Inputs!$C$66 -> 0 | H58: =(IF(AND(INDEX(Inputs!$D$57:$F$57,$C$3)=1,H$7=Inputs!$D$74),Inputs!$D$75,0)+IF(AND(INDEX(Inputs!$D$58:$F$58,$C$3)=1,H$7=Inputs!$E$74),Inputs!$E$75,0))*Inputs!$C$66 -> 0
A60: Debt and cash (interest on opening balances, so no circularity)
A61: Unitranche – opening | B61: €m | D61: =C63 -> 240 | E61: =D63 -> 236.04328 | F61: =E63 -> 227.79579 | G61: =F63 -> 211.20929 | H61: =G63 -> 185.12722
A62: Unitranche – prepayment from excess cash | B62: €m | D62: =D77 -> -3.9567187 | E62: =E77 -> -8.2474949 | F62: =F77 -> -16.586494 | G62: =G77 -> -26.082072 | H62: =H77 -> -32.854719
A63: Unitranche – closing | B63: €m | C63: =Inputs!$C$29 -> 240 | D63: =D61+D62 -> 236.04328 | E63: =E61+E62 -> 227.79579 | F63: =F61+F62 -> 211.20929 | G63: =G61+G62 -> 185.12722 | H63: =H61+H62 -> 152.2725
A64: Capex and acquisition facility – opening | B64: €m | D64: =C66 -> 0 | E64: =D66 -> 0 | F64: =E66 -> 50.7584 | G64: =F66 -> 87.8384 | H64: =G66 -> 87.8384
A65: Capex and acquisition facility – drawdown | B65: €m | D65: =MIN(-D39,Inputs!$C$31-D64) -> 0 | E65: =MIN(-E39,Inputs!$C$31-E64) -> 50.7584 | F65: =MIN(-F39,Inputs!$C$31-F64) -> 37.08 | G65: =MIN(-G39,Inputs!$C$31-G64) -> 0 | H65: =MIN(-H39,Inputs!$C$31-H64) -> 0 | I65: Add-ons funded 100% by the CAF; any shortfall falls to cash and the RCF
A66: Capex and acquisition facility – closing | B66: €m | C66: 0 | D66: =D64+D65 -> 0 | E66: =E64+E65 -> 50.7584 | F66: =F64+F65 -> 87.8384 | G66: =G64+G65 -> 87.8384 | H66: =H64+H65 -> 87.8384
A67: Revolving credit facility – opening | B67: €m | D67: =C70 -> 0 | E67: =D70 -> 0 | F67: =E70 -> 0 | G67: =F70 -> 0 | H67: =G70 -> 0
A68: Revolving credit facility – drawdown | B68: €m | D68: =MIN(MAX(0,Inputs!$C$17-D74),Inputs!$C$32-D67) -> 0 | E68: =MIN(MAX(0,Inputs!$C$17-E74),Inputs!$C$32-E67) -> 0 | F68: =MIN(MAX(0,Inputs!$C$17-F74),Inputs!$C$32-F67) -> 0 | G68: =MIN(MAX(0,Inputs!$C$17-G74),Inputs!$C$32-G67) -> 0 | H68: =MIN(MAX(0,Inputs!$C$17-H74),Inputs!$C$32-H67) -> 0
A69: Revolving credit facility – repayment | B69: €m | D69: =-MIN(D67,MAX(0,D74-Inputs!$C$17)) -> 0 | E69: =-MIN(E67,MAX(0,E74-Inputs!$C$17)) -> 0 | F69: =-MIN(F67,MAX(0,F74-Inputs!$C$17)) -> 0 | G69: =-MIN(G67,MAX(0,G74-Inputs!$C$17)) -> 0 | H69: =-MIN(H67,MAX(0,H74-Inputs!$C$17)) -> 0
A70: Revolving credit facility – closing | B70: €m | C70: 0 | D70: =D67+D68+D69 -> 0 | E70: =E67+E68+E69 -> 0 | F70: =F67+F68+F69 -> 0 | G70: =G67+G68+G69 -> 0 | H70: =H67+H68+H69 -> 0
A71: Cash – opening | B71: €m | D71: =C78 -> 10 | E71: =D78 -> 10 | F71: =E78 -> 10 | G71: =F78 -> 10 | H71: =G78 -> 10
A72: Cash flow before debt movements | B72: €m | D72: =D40 -> 3.9567187 | E72: =E40 -> -42.510905 | F72: =F40 -> -20.493506 | G72: =G40 -> 26.082072 | H72: =H40 -> 32.854719
A73: Drawdown of capex and acquisition facility | B73: €m | D73: =D65 -> 0 | E73: =E65 -> 50.7584 | F73: =F65 -> 37.08 | G73: =G65 -> 0 | H73: =H65 -> 0
A74: Cash available before RCF | B74: €m | D74: =D71+D72+D73 -> 13.956719 | E74: =E71+E72+E73 -> 18.247495 | F74: =F71+F72+F73 -> 26.586494 | G74: =G71+G72+G73 -> 36.082072 | H74: =H71+H72+H73 -> 42.854719
A75: RCF drawdown / (repayment) | B75: €m | D75: =D68+D69 -> 0 | E75: =E68+E69 -> 0 | F75: =F68+F69 -> 0 | G75: =G68+G69 -> 0 | H75: =H68+H69 -> 0
A76: Cash available before prepayment | B76: €m | D76: =D74+D75 -> 13.956719 | E76: =E74+E75 -> 18.247495 | F76: =F74+F75 -> 26.586494 | G76: =G74+G75 -> 36.082072 | H76: =H74+H75 -> 42.854719
A77: Unitranche prepayment | B77: €m | D77: =-MIN(D61,MAX(0,D76-Inputs!$C$17)*Inputs!$C$40) -> -3.9567187 | E77: =-MIN(E61,MAX(0,E76-Inputs!$C$17)*Inputs!$C$40) -> -8.2474949 | F77: =-MIN(F61,MAX(0,F76-Inputs!$C$17)*Inputs!$C$40) -> -16.586494 | G77: =-MIN(G61,MAX(0,G76-Inputs!$C$17)*Inputs!$C$40) -> -26.082072 | H77: =-MIN(H61,MAX(0,H76-Inputs!$C$17)*Inputs!$C$40) -> -32.854719 | I77: Cash above the minimum prepays the unitranche (Inputs C40)
A78: Cash – closing | B78: €m | C78: =Inputs!$C$17 -> 10 | D78: =D76+D77 -> 10 | E78: =E76+E77 -> 10 | F78: =F76+F77 -> 10 | G78: =G76+G77 -> 10 | H78: =H76+H77 -> 10
A80: Interest
A81: Unitranche interest | B81: €m | D81: =D61*(Inputs!$C$34+Inputs!$C$35) -> 16.2 | E81: =E61*(Inputs!$C$34+Inputs!$C$35) -> 15.932921 | F81: =F61*(Inputs!$C$34+Inputs!$C$35) -> 15.376216 | G81: =G61*(Inputs!$C$34+Inputs!$C$35) -> 14.256627 | H81: =H61*(Inputs!$C$34+Inputs!$C$35) -> 12.496087
A82: Capex and acquisition facility interest | B82: €m | D82: =(D64+D65)*(Inputs!$C$34+Inputs!$C$36) -> 0 | E82: =(E64+E65)*(Inputs!$C$34+Inputs!$C$36) -> 3.426192 | F82: =(F64+F65)*(Inputs!$C$34+Inputs!$C$36) -> 5.929092 | G82: =(G64+G65)*(Inputs!$C$34+Inputs!$C$36) -> 5.929092 | H82: =(H64+H65)*(Inputs!$C$34+Inputs!$C$36) -> 5.929092
A83: RCF interest | B83: €m | D83: =D67*(Inputs!$C$34+Inputs!$C$37) -> 0 | E83: =E67*(Inputs!$C$34+Inputs!$C$37) -> 0 | F83: =F67*(Inputs!$C$34+Inputs!$C$37) -> 0 | G83: =G67*(Inputs!$C$34+Inputs!$C$37) -> 0 | H83: =H67*(Inputs!$C$34+Inputs!$C$37) -> 0
A84: Commitment fees on undrawn facilities | B84: €m | D84: =Inputs!$C$38*(Inputs!$C$36*(Inputs!$C$31-D64-D65)+Inputs!$C$37*(Inputs!$C$32-D67)) -> 2.24875 | E84: =Inputs!$C$38*(Inputs!$C$36*(Inputs!$C$31-E64-E65)+Inputs!$C$37*(Inputs!$C$32-E67)) -> 1.4048916 | F84: =Inputs!$C$38*(Inputs!$C$36*(Inputs!$C$31-F64-F65)+Inputs!$C$37*(Inputs!$C$32-F67)) -> 0.7884366 | G84: =Inputs!$C$38*(Inputs!$C$36*(Inputs!$C$31-G64-G65)+Inputs!$C$37*(Inputs!$C$32-G67)) -> 0.7884366 | H84: =Inputs!$C$38*(Inputs!$C$36*(Inputs!$C$31-H64-H65)+Inputs!$C$37*(Inputs!$C$32-H67)) -> 0.7884366
A85: Interest income on cash | B85: €m | D85: =-D71*Inputs!$C$39 -> -0.15 | E85: =-E71*Inputs!$C$39 -> -0.15 | F85: =-F71*Inputs!$C$39 -> -0.15 | G85: =-G71*Inputs!$C$39 -> -0.15 | H85: =-H71*Inputs!$C$39 -> -0.15
A86: Net interest expense | B86: €m | D86: =SUM(D81:D85) -> 18.29875 | E86: =SUM(E81:E85) -> 20.614005 | F86: =SUM(F81:F85) -> 21.943744 | G86: =SUM(G81:G85) -> 20.824156 | H86: =SUM(H81:H85) -> 19.063616
A88: Credit statistics
A89: Total debt | B89: €m | C89: =C63+C66+C70 -> 240 | D89: =D63+D66+D70 -> 236.04328 | E89: =E63+E66+E70 -> 278.55419 | F89: =F63+F66+F70 -> 299.04769 | G89: =G63+G66+G70 -> 272.96562 | H89: =H63+H66+H70 -> 240.1109
A90: Net debt | B90: €m | C90: =C89-C78 -> 230 | D90: =D89-D78 -> 226.04328 | E90: =E89-E78 -> 268.55419 | F90: =F89-F78 -> 289.04769 | G90: =G89-G78 -> 262.96562 | H90: =H89-H78 -> 230.1109
A91: Net debt / EBITDA | B91: x | C91: =C90/C24 -> 5.75 | D91: =D90/D24 -> 5.0975229 | E91: =E90/E24 -> 4.768786 | F91: =F90/F24 -> 4.2721998 | G91: =G90/G24 -> 3.4851054 | H91: =H90/H24 -> 2.7804658
A92: EBITDA / net interest | B92: x | D92: =D24/D86 -> 2.4233213 | E92: =E24/E86 -> 2.7318806 | F92: =F24/F86 -> 3.0832392 | G92: =G24/G86 -> 3.6233947 | H92: =H24/H86 -> 4.3412455
A93: Covenant headroom (EBITDA could fall by) | B93: % | C93: =1-C91/Inputs!$C$41 -> 0.3030303 | D93: =1-D91/Inputs!$C$41 -> 0.38211844 | E93: =1-E91/Inputs!$C$41 -> 0.42196533 | F93: =1-F91/Inputs!$C$41 -> 0.48215759 | G93: =1-G91/Inputs!$C$41 -> 0.57756298 | H93: =1-H91/Inputs!$C$41 -> 0.66297384 | I93: How far EBITDA could fall before breaching the leverage covenant
A94: Check: net debt roll-forward (should be 0) | B94: €m | D94: =D90-(C90-D40) -> 0 | E94: =E90-(D90-E40) -> 0 | F94: =F90-(E90-F40) -> 0 | G94: =G90-(F90-G40) -> 0 | H94: =H90-(G90-H40) -> 0
A96: Returns – exit at the end of FY2031
A97: Exit-year EBITDA (FY2031) | B97: €m | C97: =H24 -> 82.759838
A98: Exit EV / EBITDA | B98: x | C98: =INDEX(Inputs!$D$59:$F$59,$C$3) -> 13.5
A99: Exit enterprise value | B99: €m | C99: =C97*C98 -> 1117.2578
A100: Exit costs | B100: €m | C100: =-C99*Inputs!$C$70 -> -16.758867
A101: Net debt at exit | B101: €m | C101: =-H90 -> -230.1109
A102: Exit equity value (100%) | B102: €m | C102: =SUM(C99:C101) -> 870.38804
A103: Equity invested at closing | B103: €m | C103: =Transaction!$C$20 -> 328.2 | I103: Total equity strip from Transaction sheet (ARCHIMED + founder + management)
A104: Capital gain before MIP | B104: €m | C104: =C102-C103 -> 542.18804
A105: MIP payout to management | B105: €m | C105: =-Inputs!$C$20*MAX(0,C104) -> -54.218804
A106: Exit equity to investors | B106: €m | C106: =C102+C105 -> 816.16924
A107: MOIC (investors) | B107: x | C107: =C106/C103 -> 2.4868045
A108: Investor cash flows | B108: €m | C108: =-C103 -> -328.2 | D108: 0 | E108: 0 | F108: 0 | G108: 0 | H108: =$C$106 -> 816.16924
A109: IRR (investors) | B109: % | C109: =IRR(C108:H108) -> 0.19985379 | I109: Single entry and exit cash flow: no interim equity injections or dividends
A110: Check: IRR equals MOIC^(1/5) – 1 (should be 0) | B110: % | C110: =C109-(C107^(1/H$6)-1) -> 0
...

Sheet LBO_Mgmt
A1: Project Lumière – LBO model: Management case
A2: €m unless stated · financial year to December · closing 31 December 2026 · exit 31 December 2031
A3: Case index (1 = Base, 2 = Management, 3 = Downside) | C3: 2
A5: €m | B5: Unit | C5: FY2026E | D5: FY2027 | E5: FY2028 | F5: FY2029 | G5: FY2030 | H5: FY2031
A6: Years from closing | C6: 0 | D6: =C6+1 -> 1 | E6: =D6+1 -> 2 | F6: =E6+1 -> 3 | G6: =F6+1 -> 4 | H6: =G6+1 -> 5
A7: Financial year | C7: 2026 | D7: =C7+1 -> 2027 | E7: =D7+1 -> 2028 | F7: =E7+1 -> 2029 | G7: =F7+1 -> 2030 | H7: =G7+1 -> 2031
A9: Revenue
A10: Organic revenue growth | B10: % | D10: =INDEX(Inputs!D$45:D$47,$C$3)+Inputs!$C$52 -> 0.1 | E10: =INDEX(Inputs!E$45:E$47,$C$3)+Inputs!$C$52 -> 0.11 | F10: =INDEX(Inputs!F$45:F$47,$C$3)+Inputs!$C$52 -> 0.115 | G10: =INDEX(Inputs!G$45:G$47,$C$3)+Inputs!$C$52 -> 0.115 | H10: =INDEX(Inputs!H$45:H$47,$C$3)+Inputs!$C$52 -> 0.11 | I10: Inputs rows 45–47 picked by case index, plus the flex delta
A11: Organic revenue | B11: €m | C11: =Inputs!$C$5 -> 150 | D11: =C11*(1+D10) -> 165 | E11: =D11*(1+E10) -> 183.15 | F11: =E11*(1+F10) -> 204.21225 | G11: =F11*(1+G10) -> 227.69666 | H11: =G11*(1+H10) -> 252.74329
A12: Add-on A revenue (Germany) | B12: €m | C12: 0 | D12: =IF(AND(INDEX(Inputs!$D$57:$F$57,$C$3)=1,D$7>=Inputs!$D$74),Inputs!$D$75*(1+Inputs!$D$76)^(D$7-Inputs!$D$74+1),0) -> 0 | E12: =IF(AND(INDEX(Inputs!$D$57:$F$57,$C$3)=1,E$7>=Inputs!$D$74),Inputs!$D$75*(1+Inputs!$D$76)^(E$7-Inputs!$D$74+1),0) -> 29.12 | F12: =IF(AND(INDEX(Inputs!$D$57:$F$57,$C$3)=1,F$7>=Inputs!$D$74),Inputs!$D$75*(1+Inputs!$D$76)^(F$7-Inputs!$D$74+1),0) -> 30.2848 | G12: =IF(AND(INDEX(Inputs!$D$57:$F$57,$C$3)=1,G$7>=Inputs!$D$74),Inputs!$D$75*(1+Inputs!$D$76)^(G$7-Inputs!$D$74+1),0) -> 31.496192 | H12: =IF(AND(INDEX(Inputs!$D$57:$F$57,$C$3)=1,H$7>=Inputs!$D$74),Inputs!$D$75*(1+Inputs!$D$76)^(H$7-Inputs!$D$74+1),0) -> 32.75604 | I12: Consolidated from 1 January of the acquisition year
A13: Add-on B revenue (US) | B13: €m | C13: 0 | D13: =IF(AND(INDEX(Inputs!$D$58:$F$58,$C$3)=1,D$7>=Inputs!$E$74),Inputs!$E$75*(1+Inputs!$E$76)^(D$7-Inputs!$E$74+1),0) -> 0 | E13: =IF(AND(INDEX(Inputs!$D$58:$F$58,$C$3)=1,E$7>=Inputs!$E$74),Inputs!$E$75*(1+Inputs!$E$76)^(E$7-Inputs!$E$74+1),0) -> 0 | F13: =IF(AND(INDEX(Inputs!$D$58:$F$58,$C$3)=1,F$7>=Inputs!$E$74),Inputs!$E$75*(1+Inputs!$E$76)^(F$7-Inputs!$E$74+1),0) -> 20.16 | G13: =IF(AND(INDEX(Inputs!$D$58:$F$58,$C$3)=1,G$7>=Inputs!$E$74),Inputs!$E$75*(1+Inputs!$E$76)^(G$7-Inputs!$E$74+1),0) -> 22.5792 | H13: =IF(AND(INDEX(Inputs!$D$58:$F$58,$C$3)=1,H$7>=Inputs!$E$74),Inputs!$E$75*(1+Inputs!$E$76)^(H$7-Inputs!$E$74+1),0) -> 25.288704
A14: Total revenue | B14: €m | C14: =SUM(C11:C13) -> 150 | D14: =SUM(D11:D13) -> 165 | E14: =SUM(E11:E13) -> 212.27 | F14: =SUM(F11:F13) -> 254.65705 | G14: =SUM(G11:G13) -> 281.77205 | H14: =SUM(H11:H13) -> 310.78803
A15: Total revenue growth | B15: % | D15: =D14/C14-1 -> 0.1 | E15: =E14/D14-1 -> 0.28648485 | F15: =F14/E14-1 -> 0.1996846 | G15: =G14/F14-1 -> 0.10647654 | H15: =H14/G14-1 -> 0.1029768
A17: EBITDA (ARCHIMED definition: pre-IFRS 16, fully loaded)
A18: Organic EBITDA margin | B18: % | C18: =C19/C11 -> 0.26666667 | D18: =INDEX(Inputs!D$48:D$50,$C$3)+Inputs!$C$53 -> 0.27966667 | E18: =INDEX(Inputs!E$48:E$50,$C$3)+Inputs!$C$53 -> 0.29466667 | F18: =INDEX(Inputs!F$48:F$50,$C$3)+Inputs!$C$53 -> 0.30966667 | G18: =INDEX(Inputs!G$48:G$50,$C$3)+Inputs!$C$53 -> 0.31966667 | H18: =INDEX(Inputs!H$48:H$50,$C$3)+Inputs!$C$53 -> 0.32466667
A19: Organic EBITDA | B19: €m | C19: =Inputs!$C$8 -> 40 | D19: =D11*D18 -> 46.145 | E19: =E11*E18 -> 53.9682 | F19: =F11*F18 -> 63.237727 | G19: =G11*G18 -> 72.787032 | H19: =H11*H18 -> 82.057322
A20: Add-on A EBITDA (standalone) | B20: €m | C20: 0 | D20: =D12*Inputs!$D$77 -> 0 | E20: =E12*Inputs!$D$77 -> 6.4064 | F20: =F12*Inputs!$D$77 -> 6.662656 | G20: =G12*Inputs!$D$77 -> 6.9291622 | H20: =H12*Inputs!$D$77 -> 7.2063287
A21: Add-on A cost synergies | B21: €m | C21: 0 | D21: =IF(D12>0,Inputs!$D$81*IF(D$7-Inputs!$D$74=0,Inputs!$D$82,IF(D$7-Inputs!$D$74=1,Inputs!$D$83,Inputs!$D$84)),0) -> 0 | E21: =IF(E12>0,Inputs!$D$81*IF(E$7-Inputs!$D$74=0,Inputs!$D$82,IF(E$7-Inputs!$D$74=1,Inputs!$D$83,Inputs!$D$84)),0) -> 0.45 | F21: =IF(F12>0,Inputs!$D$81*IF(F$7-Inputs!$D$74=0,Inputs!$D$82,IF(F$7-Inputs!$D$74=1,Inputs!$D$83,Inputs!$D$84)),0) -> 1.35 | G21: =IF(G12>0,Inputs!$D$81*IF(G$7-Inputs!$D$74=0,Inputs!$D$82,IF(G$7-Inputs!$D$74=1,Inputs!$D$83,Inputs!$D$84)),0) -> 1.8 | H21: =IF(H12>0,Inputs!$D$81*IF(H$7-Inputs!$D$74=0,Inputs!$D$82,IF(H$7-Inputs!$D$74=1,Inputs!$D$83,Inputs!$D$84)),0) -> 1.8
A22: Add-on B EBITDA (standalone) | B22: €m | C22: 0 | D22: =D13*Inputs!$E$77 -> 0 | E22: =E13*Inputs!$E$77 -> 0 | F22: =F13*Inputs!$E$77 -> 4.032 | G22: =G13*Inputs!$E$77 -> 4.51584 | H22: =H13*Inputs!$E$77 -> 5.0577408
A23: Add-on B cost synergies | B23: €m | C23: 0 | D23: =IF(D13>0,Inputs!$E$81*IF(D$7-Inputs!$E$74=0,Inputs!$E$82,IF(D$7-Inputs!$E$74=1,Inputs!$E$83,Inputs!$E$84)),0) -> 0 | E23: =IF(E13>0,Inputs!$E$81*IF(E$7-Inputs!$E$74=0,Inputs!$E$82,IF(E$7-Inputs!$E$74=1,Inputs!$E$83,Inputs!$E$84)),0) -> 0 | F23: =IF(F13>0,Inputs!$E$81*IF(F$7-Inputs!$E$74=0,Inputs!$E$82,IF(F$7-Inputs!$E$74=1,Inputs!$E$83,Inputs!$E$84)),0) -> 0.25 | G23: =IF(G13>0,Inputs!$E$81*IF(G$7-Inputs!$E$74=0,Inputs!$E$82,IF(G$7-Inputs!$E$74=1,Inputs!$E$83,Inputs!$E$84)),0) -> 0.5 | H23: =IF(H13>0,Inputs!$E$81*IF(H$7-Inputs!$E$74=0,Inputs!$E$82,IF(H$7-Inputs!$E$74=1,Inputs!$E$83,Inputs!$E$84)),0) -> 0.5
A24: Total EBITDA | B24: €m | C24: =SUM(C19:C23) -> 40 | D24: =SUM(D19:D23) -> 46.145 | E24: =SUM(E19:E23) -> 60.8246 | F24: =SUM(F19:F23) -> 75.532383 | G24: =SUM(G19:G23) -> 86.532034 | H24: =SUM(H19:H23) -> 96.621391
A25: EBITDA margin | B25: % | C25: =C24/C14 -> 0.26666667 | D25: =D24/D14 -> 0.27966667 | E25: =E24/E14 -> 0.28654355 | F25: =F24/F14 -> 0.29660433 | G25: =G24/G14 -> 0.30709942 | H25: =H24/H14 -> 0.31089161
A26: EBITDA growth | B26: % | D26: =D24/C24-1 -> 0.153625 | E26: =E24/D24-1 -> 0.31811897 | F26: =F24/E24-1 -> 0.24180649 | G26: =G24/F24-1 -> 0.14562829 | H26: =H24/G24-1 -> 0.11659679
A28: Free cash flow
A29: EBITDA | B29: €m | D29: =D24 -> 46.145 | E29: =E24 -> 60.8246 | F29: =F24 -> 75.532383 | G29: =G24 -> 86.532034 | H29: =H24 -> 96.621391
A30: One-off integration costs | B30: €m | D30: =-(IF(AND(INDEX(Inputs!$D$57:$F$57,$C$3)=1,D$7=Inputs!$D$74),Inputs!$D$80,0)+IF(AND(INDEX(Inputs!$D$58:$F$58,$C$3)=1,D$7=Inputs!$E$74),Inputs!$E$80,0)) -> 0 | E30: =-(IF(AND(INDEX(Inputs!$D$57:$F$57,$C$3)=1,E$7=Inputs!$D$74),Inputs!$D$80,0)+IF(AND(INDEX(Inputs!$D$58:$F$58,$C$3)=1,E$7=Inputs!$E$74),Inputs!$E$80,0)) -> -2.5 | F30: =-(IF(AND(INDEX(Inputs!$D$57:$F$57,$C$3)=1,F$7=Inputs!$D$74),Inputs!$D$80,0)+IF(AND(INDEX(Inputs!$D$58:$F$58,$C$3)=1,F$7=Inputs!$E$74),Inputs!$E$80,0)) -> -1.5 | G30: =-(IF(AND(INDEX(Inputs!$D$57:$F$57,$C$3)=1,G$7=Inputs!$D$74),Inputs!$D$80,0)+IF(AND(INDEX(Inputs!$D$58:$F$58,$C$3)=1,G$7=Inputs!$E$74),Inputs!$E$80,0)) -> 0 | H30: =-(IF(AND(INDEX(Inputs!$D$57:$F$57,$C$3)=1,H$7=Inputs!$D$74),Inputs!$D$80,0)+IF(AND(INDEX(Inputs!$D$58:$F$58,$C$3)=1,H$7=Inputs!$E$74),Inputs!$E$80,0)) -> 0
A31: Maintenance and placed-analyzer capex | B31: €m | D31: =-D14*Inputs!$C$63 -> -6.6 | E31: =-E14*Inputs!$C$63 -> -8.4908 | F31: =-F14*Inputs!$C$63 -> -10.186282 | G31: =-G14*Inputs!$C$63 -> -11.270882 | H31: =-H14*Inputs!$C$63 -> -12.431521
A32: Capitalised R&D | B32: €m | D32: =-D14*Inputs!$C$64 -> -2.475 | E32: =-E14*Inputs!$C$64 -> -3.18405 | F32: =-F14*Inputs!$C$64 -> -3.8198557 | G32: =-G14*Inputs!$C$64 -> -4.2265808 | H32: =-H14*Inputs!$C$64 -> -4.6618205
A33: Growth capex | B33: €m | D33: =-Inputs!D$65 -> -5 | E33: =-Inputs!E$65 -> -4 | F33: =-Inputs!F$65 -> -2 | G33: =-Inputs!G$65 -> 0 | H33: =-Inputs!H$65 -> 0
A34: Change in net working capital | B34: €m | D34: =-(D57-C57-D58) -> -3.3 | E34: =-(E57-D57-E58) -> -4.2394 | F34: =-(F57-E57-F58) -> -5.365151 | G34: =-(G57-F57-G58) -> -5.9653002 | H34: =-(H57-G57-H58) -> -6.3835165 | I34: Excludes the working capital bought with add-ons (paid for in the purchase price)
A35: Cash taxes | B35: €m | D35: =-D54 -> -6.012875 | E35: =-E54 -> -7.36593 | F35: =-F54 -> -9.6599539 | G35: =-G54 -> -11.620955 | H35: =-H54 -> -14.396023
A36: Net interest expense | B36: €m | D36: =-D86 -> -18.29875 | E36: =-E86 -> -20.580143 | F36: =-F86 -> -21.76025 | G36: =-G86 -> -22.623169 | H36: =-H86 -> -20.945792
A37: Free cash flow | B37: €m | D37: =SUM(D29:D36) -> 4.458375 | E37: =SUM(E29:E36) -> 10.464277 | F37: =SUM(F29:F36) -> 21.240891 | G37: =SUM(G29:G36) -> 30.825147 | H37: =SUM(H29:H36) -> 37.802718
A38: Earn-out paid to the vendor | B38: €m | D38: =-IF(D$7=Inputs!$C$23,$C$137,0) -> 0 | E38: =-IF(E$7=Inputs!$C$23,$C$137,0) -> 0 | F38: =-IF(F$7=Inputs!$C$23,$C$137,0) -> -40 | G38: =-IF(G$7=Inputs!$C$23,$C$137,0) -> 0 | H38: =-IF(H$7=Inputs!$C$23,$C$137,0) -> 0 | I38: Paid by the company in the payment year; reduces debt paydown
A39: Add-on acquisitions incl. deal costs | B39: €m | D39: =-(IF(AND(INDEX(Inputs!$D$57:$F$57,$C$3)=1,D$7=Inputs!$D$74),Inputs!$D$86,0)+IF(AND(INDEX(Inputs!$D$58:$F$58,$C$3)=1,D$7=Inputs!$E$74),Inputs!$E$86,0)) -> 0 | E39: =-(IF(AND(INDEX(Inputs!$D$57:$F$57,$C$3)=1,E$7=Inputs!$D$74),Inputs!$D$86,0)+IF(AND(INDEX(Inputs!$D$58:$F$58,$C$3)=1,E$7=Inputs!$E$74),Inputs!$E$86,0)) -> -50.7584 | F39: =-(IF(AND(INDEX(Inputs!$D$57:$F$57,$C$3)=1,F$7=Inputs!$D$74),Inputs!$D$86,0)+IF(AND(INDEX(Inputs!$D$58:$F$58,$C$3)=1,F$7=Inputs!$E$74),Inputs!$E$86,0)) -> -37.08 | G39: =-(IF(AND(INDEX(Inputs!$D$57:$F$57,$C$3)=1,G$7=Inputs!$D$74),Inputs!$D$86,0)+IF(AND(INDEX(Inputs!$D$58:$F$58,$C$3)=1,G$7=Inputs!$E$74),Inputs!$E$86,0)) -> 0 | H39: =-(IF(AND(INDEX(Inputs!$D$57:$F$57,$C$3)=1,H$7=Inputs!$D$74),Inputs!$D$86,0)+IF(AND(INDEX(Inputs!$D$58:$F$58,$C$3)=1,H$7=Inputs!$E$74),Inputs!$E$86,0)) -> 0
A40: Cash flow before debt movements | B40: €m | D40: =D37+D38+D39 -> 4.458375 | E40: =E37+E38+E39 -> -40.294123 | F40: =F37+F38+F39 -> -55.839109 | G40: =G37+G38+G39 -> 30.825147 | H40: =H37+H38+H39 -> 37.802718
A41: Cash conversion: (EBITDA – capex – ΔNWC) / EBITDA | B41: % | D41: =(D29+D31+D32+D33+D34)/D29 -> 0.6234695 | E41: =(E29+E31+E32+E33+E34)/E29 -> 0.67259546 | F41: =(F29+F31+F32+F33+F34)/F29 -> 0.71705793 | G41: =(G29+G31+G32+G33+G34)/G29 -> 0.75196743 | H41: =(H29+H31+H32+H33+H34)/H29 -> 0.75702215
A43: Corporate tax (French interest cap)
A44: EBITDA | B44: €m | D44: =D24 -> 46.145 | E44: =E24 -> 60.8246 | F44: =F24 -> 75.532383 | G44: =G24 -> 86.532034 | H44: =H24 -> 96.621391
A45: One-off integration costs | B45: €m | D45: =D30 -> 0 | E45: =E30 -> -2.5 | F45: =F30 -> -1.5 | G45: =G30 -> 0 | H45: =H30 -> 0
A46: Depreciation and amortisation | B46: €m | D46: =-D14*Inputs!$C$62 -> -8.25 | E46: =-E14*Inputs!$C$62 -> -10.6135 | F46: =-F14*Inputs!$C$62 -> -12.732852 | G46: =-G14*Inputs!$C$62 -> -14.088603 | H46: =-H14*Inputs!$C$62 -> -15.539402
A47: EBIT | B47: €m | D47: =SUM(D44:D46) -> 37.895 | E47: =SUM(E44:E46) -> 47.7111 | F47: =SUM(F44:F46) -> 61.29953 | G47: =SUM(G44:G46) -> 72.443432 | H47: =SUM(H44:H46) -> 81.08199
A48: Net interest expense | B48: €m | D48: =D86 -> 18.29875 | E48: =E86 -> 20.580143 | F48: =F86 -> 21.76025 | G48: =G86 -> 22.623169 | H48: =H86 -> 20.945792
A49: Interest deduction capacity (higher of 30% of EBITDA or €3m) | B49: €m | D49: =MAX(Inputs!$C$69,Inputs!$C$68*D44) -> 13.8435 | E49: =MAX(Inputs!$C$69,Inputs!$C$68*E44) -> 18.24738 | F49: =MAX(Inputs!$C$69,Inputs!$C$68*F44) -> 22.659715 | G49: =MAX(Inputs!$C$69,Inputs!$C$68*G44) -> 25.95961 | H49: =MAX(Inputs!$C$69,Inputs!$C$68*H44) -> 28.986417 | I49: French rule: net interest deductible up to the higher of 30% of tax EBITDA or €3m; excess carried forward
A50: Disallowed interest brought forward | B50: €m | D50: =C52 -> 0 | E50: =D52 -> 4.45525 | F50: =E52 -> 6.7880133 | G50: =F52 -> 5.8885481 | H50: =G52 -> 2.5521065
A51: Deductible interest | B51: €m | D51: =MAX(0,MIN(D48+D50,D49)) -> 13.8435 | E51: =MAX(0,MIN(E48+E50,E49)) -> 18.24738 | F51: =MAX(0,MIN(F48+F50,F49)) -> 22.659715 | G51: =MAX(0,MIN(G48+G50,G49)) -> 25.95961 | H51: =MAX(0,MIN(H48+H50,H49)) -> 23.497899
A52: Disallowed interest carried forward | B52: €m | C52: 0 | D52: =MAX(0,D48+D50-D51) -> 4.45525 | E52: =MAX(0,E48+E50-E51) -> 6.7880133 | F52: =MAX(0,F48+F50-F51) -> 5.8885481 | G52: =MAX(0,G48+G50-G51) -> 2.5521065 | H52: =MAX(0,H48+H50-H51) -> 0
A53: Taxable income | B53: €m | D53: =MAX(0,D47-D51) -> 24.0515 | E53: =MAX(0,E47-E51) -> 29.46372 | F53: =MAX(0,F47-F51) -> 38.639815 | G53: =MAX(0,G47-G51) -> 46.483821 | H53: =MAX(0,H47-H51) -> 57.584091
A54: Cash tax | B54: €m | D54: =D53*Inputs!$C$67 -> 6.012875 | E54: =E53*Inputs!$C$67 -> 7.36593 | F54: =F53*Inputs!$C$67 -> 9.6599539 | G54: =G53*Inputs!$C$67 -> 11.620955 | H54: =H53*Inputs!$C$67 -> 14.396023
A56: Net working capital (memo)
A57: Net working capital | B57: €m | C57: =C14*Inputs!$C$66 -> 33 | D57: =D14*Inputs!$C$66 -> 36.3 | E57: =E14*Inputs!$C$66 -> 46.6994 | F57: =F14*Inputs!$C$66 -> 56.024551 | G57: =G14*Inputs!$C$66 -> 61.989851 | H57: =H14*Inputs!$C$66 -> 68.373368
A58: Net working capital acquired with add-ons | B58: €m | D58: =(IF(AND(INDEX(Inputs!$D$57:$F$57,$C$3)=1,D$7=Inputs!$D$74),Inputs!$D$75,0)+IF(AND(INDEX(Inputs!$D$58:$F$58,$C$3)=1,D$7=Inputs!$E$74),Inputs!$E$75,0))*Inputs!$C$66 -> 0 | E58: =(IF(AND(INDEX(Inputs!$D$57:$F$57,$C$3)=1,E$7=Inputs!$D$74),Inputs!$D$75,0)+IF(AND(INDEX(Inputs!$D$58:$F$58,$C$3)=1,E$7=Inputs!$E$74),Inputs!$E$75,0))*Inputs!$C$66 -> 6.16 | F58: =(IF(AND(INDEX(Inputs!$D$57:$F$57,$C$3)=1,F$7=Inputs!$D$74),Inputs!$D$75,0)+IF(AND(INDEX(Inputs!$D$58:$F$58,$C$3)=1,F$7=Inputs!$E$74),Inputs!$E$75,0))*Inputs!$C$66 -> 3.96 | G58: =(IF(AND(INDEX(Inputs!$D$57:$F$57,$C$3)=1,G$7=Inputs!$D$74),Inputs!$D$75,0)+IF(AND(INDEX(Inputs!$D$58:$F$58,$C$3)=1,G$7=Inputs!$E$74),Inputs!$E$75,0))*Inputs!$C$66 -> 0 | H58: =(IF(AND(INDEX(Inputs!$D$57:$F$57,$C$3)=1,H$7=Inputs!$D$74),Inputs!$D$75,0)+IF(AND(INDEX(Inputs!$D$58:$F$58,$C$3)=1,H$7=Inputs!$E$74),Inputs!$E$75,0))*Inputs!$C$66 -> 0
A60: Debt and cash (interest on opening balances, so no circularity)
A61: Unitranche – opening | B61: €m | D61: =C63 -> 240 | E61: =D63 -> 235.54163 | F61: =E63 -> 225.07735 | G61: =F63 -> 225.07735 | H61: =G63 -> 213.01131
A62: Unitranche – prepayment from excess cash | B62: €m | D62: =D77 -> -4.458375 | E62: =E77 -> -10.464277 | F62: =F77 -> 0 | G62: =G77 -> -12.066038 | H62: =H77 -> -37.802718
A63: Unitranche – closing | B63: €m | C63: =Inputs!$C$29 -> 240 | D63: =D61+D62 -> 235.54163 | E63: =E61+E62 -> 225.07735 | F63: =F61+F62 -> 225.07735 | G63: =G61+G62 -> 213.01131 | H63: =H61+H62 -> 175.20859
A64: Capex and acquisition facility – opening | B64: €m | D64: =C66 -> 0 | E64: =D66 -> 0 | F64: =E66 -> 50.7584 | G64: =F66 -> 87.8384 | H64: =G66 -> 87.8384
A65: Capex and acquisition facility – drawdown | B65: €m | D65: =MIN(-D39,Inputs!$C$31-D64) -> 0 | E65: =MIN(-E39,Inputs!$C$31-E64) -> 50.7584 | F65: =MIN(-F39,Inputs!$C$31-F64) -> 37.08 | G65: =MIN(-G39,Inputs!$C$31-G64) -> 0 | H65: =MIN(-H39,Inputs!$C$31-H64) -> 0 | I65: Add-ons funded 100% by the CAF; any shortfall falls to cash and the RCF
A66: Capex and acquisition facility – closing | B66: €m | C66: 0 | D66: =D64+D65 -> 0 | E66: =E64+E65 -> 50.7584 | F66: =F64+F65 -> 87.8384 | G66: =G64+G65 -> 87.8384 | H66: =H64+H65 -> 87.8384
A67: Revolving credit facility – opening | B67: €m | D67: =C70 -> 0 | E67: =D70 -> 0 | F67: =E70 -> 0 | G67: =F70 -> 18.759109 | H67: =G70 -> 0
A68: Revolving credit facility – drawdown | B68: €m | D68: =MIN(MAX(0,Inputs!$C$17-D74),Inputs!$C$32-D67) -> 0 | E68: =MIN(MAX(0,Inputs!$C$17-E74),Inputs!$C$32-E67) -> 0 | F68: =MIN(MAX(0,Inputs!$C$17-F74),Inputs!$C$32-F67) -> 18.759109 | G68: =MIN(MAX(0,Inputs!$C$17-G74),Inputs!$C$32-G67) -> 0 | H68: =MIN(MAX(0,Inputs!$C$17-H74),Inputs!$C$32-H67) -> 0
A69: Revolving credit facility – repayment | B69: €m | D69: =-MIN(D67,MAX(0,D74-Inputs!$C$17)) -> 0 | E69: =-MIN(E67,MAX(0,E74-Inputs!$C$17)) -> 0 | F69: =-MIN(F67,MAX(0,F74-Inputs!$C$17)) -> 0 | G69: =-MIN(G67,MAX(0,G74-Inputs!$C$17)) -> -18.759109 | H69: =-MIN(H67,MAX(0,H74-Inputs!$C$17)) -> 0
A70: Revolving credit facility – closing | B70: €m | C70: 0 | D70: =D67+D68+D69 -> 0 | E70: =E67+E68+E69 -> 0 | F70: =F67+F68+F69 -> 18.759109 | G70: =G67+G68+G69 -> 0 | H70: =H67+H68+H69 -> 0
A71: Cash – opening | B71: €m | D71: =C78 -> 10 | E71: =D78 -> 10 | F71: =E78 -> 10 | G71: =F78 -> 10 | H71: =G78 -> 10
A72: Cash flow before debt movements | B72: €m | D72: =D40 -> 4.458375 | E72: =E40 -> -40.294123 | F72: =F40 -> -55.839109 | G72: =G40 -> 30.825147 | H72: =H40 -> 37.802718
A73: Drawdown of capex and acquisition facility | B73: €m | D73: =D65 -> 0 | E73: =E65 -> 50.7584 | F73: =F65 -> 37.08 | G73: =G65 -> 0 | H73: =H65 -> 0
A74: Cash available before RCF | B74: €m | D74: =D71+D72+D73 -> 14.458375 | E74: =E71+E72+E73 -> 20.464277 | F74: =F71+F72+F73 -> -8.7591095 | G74: =G71+G72+G73 -> 40.825147 | H74: =H71+H72+H73 -> 47.802718
A75: RCF drawdown / (repayment) | B75: €m | D75: =D68+D69 -> 0 | E75: =E68+E69 -> 0 | F75: =F68+F69 -> 18.759109 | G75: =G68+G69 -> -18.759109 | H75: =H68+H69 -> 0
A76: Cash available before prepayment | B76: €m | D76: =D74+D75 -> 14.458375 | E76: =E74+E75 -> 20.464277 | F76: =F74+F75 -> 10 | G76: =G74+G75 -> 22.066038 | H76: =H74+H75 -> 47.802718
A77: Unitranche prepayment | B77: €m | D77: =-MIN(D61,MAX(0,D76-Inputs!$C$17)*Inputs!$C$40) -> -4.458375 | E77: =-MIN(E61,MAX(0,E76-Inputs!$C$17)*Inputs!$C$40) -> -10.464277 | F77: =-MIN(F61,MAX(0,F76-Inputs!$C$17)*Inputs!$C$40) -> 0 | G77: =-MIN(G61,MAX(0,G76-Inputs!$C$17)*Inputs!$C$40) -> -12.066038 | H77: =-MIN(H61,MAX(0,H76-Inputs!$C$17)*Inputs!$C$40) -> -37.802718 | I77: Cash above the minimum prepays the unitranche (Inputs C40)
A78: Cash – closing | B78: €m | C78: =Inputs!$C$17 -> 10 | D78: =D76+D77 -> 10 | E78: =E76+E77 -> 10 | F78: =F76+F77 -> 10 | G78: =G76+G77 -> 10 | H78: =H76+H77 -> 10
A80: Interest
A81: Unitranche interest | B81: €m | D81: =D61*(Inputs!$C$34+Inputs!$C$35) -> 16.2 | E81: =E61*(Inputs!$C$34+Inputs!$C$35) -> 15.89906 | F81: =F61*(Inputs!$C$34+Inputs!$C$35) -> 15.192721 | G81: =G61*(Inputs!$C$34+Inputs!$C$35) -> 15.192721 | H81: =H61*(Inputs!$C$34+Inputs!$C$35) -> 14.378263
A82: Capex and acquisition facility interest | B82: €m | D82: =(D64+D65)*(Inputs!$C$34+Inputs!$C$36) -> 0 | E82: =(E64+E65)*(Inputs!$C$34+Inputs!$C$36) -> 3.426192 | F82: =(F64+F65)*(Inputs!$C$34+Inputs!$C$36) -> 5.929092 | G82: =(G64+G65)*(Inputs!$C$34+Inputs!$C$36) -> 5.929092 | H82: =(H64+H65)*(Inputs!$C$34+Inputs!$C$36) -> 5.929092
A83: RCF interest | B83: €m | D83: =D67*(Inputs!$C$34+Inputs!$C$37) -> 0 | E83: =E67*(Inputs!$C$34+Inputs!$C$37) -> 0 | F83: =F67*(Inputs!$C$34+Inputs!$C$37) -> 0 | G83: =G67*(Inputs!$C$34+Inputs!$C$37) -> 1.1255466 | H83: =H67*(Inputs!$C$34+Inputs!$C$37) -> 0
A84: Commitment fees on undrawn facilities | B84: €m | D84: =Inputs!$C$38*(Inputs!$C$36*(Inputs!$C$31-D64-D65)+Inputs!$C$37*(Inputs!$C$32-D67)) -> 2.24875 | E84: =Inputs!$C$38*(Inputs!$C$36*(Inputs!$C$31-E64-E65)+Inputs!$C$37*(Inputs!$C$32-E67)) -> 1.4048916 | F84: =Inputs!$C$38*(Inputs!$C$36*(Inputs!$C$31-F64-F65)+Inputs!$C$37*(Inputs!$C$32-F67)) -> 0.7884366 | G84: =Inputs!$C$38*(Inputs!$C$36*(Inputs!$C$31-G64-G65)+Inputs!$C$37*(Inputs!$C$32-G67)) -> 0.52580907 | H84: =Inputs!$C$38*(Inputs!$C$36*(Inputs!$C$31-H64-H65)+Inputs!$C$37*(Inputs!$C$32-H67)) -> 0.7884366
A85: Interest income on cash | B85: €m | D85: =-D71*Inputs!$C$39 -> -0.15 | E85: =-E71*Inputs!$C$39 -> -0.15 | F85: =-F71*Inputs!$C$39 -> -0.15 | G85: =-G71*Inputs!$C$39 -> -0.15 | H85: =-H71*Inputs!$C$39 -> -0.15
A86: Net interest expense | B86: €m | D86: =SUM(D81:D85) -> 18.29875 | E86: =SUM(E81:E85) -> 20.580143 | F86: =SUM(F81:F85) -> 21.76025 | G86: =SUM(G81:G85) -> 22.623169 | H86: =SUM(H81:H85) -> 20.945792
A88: Credit statistics
A89: Total debt | B89: €m | C89: =C63+C66+C70 -> 240 | D89: =D63+D66+D70 -> 235.54163 | E89: =E63+E66+E70 -> 275.83575 | F89: =F63+F66+F70 -> 331.67486 | G89: =G63+G66+G70 -> 300.84971 | H89: =H63+H66+H70 -> 263.04699
A90: Net debt | B90: €m | C90: =C89-C78 -> 230 | D90: =D89-D78 -> 225.54163 | E90: =E89-E78 -> 265.83575 | F90: =F89-F78 -> 321.67486 | G90: =G89-G78 -> 290.84971 | H90: =H89-H78 -> 253.04699
A91: Net debt / EBITDA | B91: x | C91: =C90/C24 -> 5.75 | D91: =D90/D24 -> 4.887672 | E91: =E90/E24 -> 4.3705302 | F91: =F90/F24 -> 4.2587675 | G91: =G90/G24 -> 3.3611796 | H91: =H90/H24 -> 2.6189541
A92: EBITDA / net interest | B92: x | D92: =D24/D86 -> 2.521757 | E92: =E24/E86 -> 2.9554993 | F92: =F24/F86 -> 3.4711175 | G92: =G24/G86 -> 3.8249299 | H92: =H24/H86 -> 4.6129261
A93: Covenant headroom (EBITDA could fall by) | B93: % | C93: =1-C91/Inputs!$C$41 -> 0.3030303 | D93: =1-D91/Inputs!$C$41 -> 0.40755491 | E93: =1-E91/Inputs!$C$41 -> 0.47023877 | F93: =1-F91/Inputs!$C$41 -> 0.48378576 | G93: =1-G91/Inputs!$C$41 -> 0.59258429 | H93: =1-H91/Inputs!$C$41 -> 0.68255101 | I93: How far EBITDA could fall before breaching the leverage covenant
A94: Check: net debt roll-forward (should be 0) | B94: €m | D94: =D90-(C90-D40) -> 0 | E94: =E90-(D90-E40) -> 0 | F94: =F90-(E90-F40) -> 0 | G94: =G90-(F90-G40) -> 0 | H94: =H90-(G90-H40) -> 0
A96: Returns – exit at the end of FY2031
A97: Exit-year EBITDA (FY2031) | B97: €m | C97: =H24 -> 96.621391
A98: Exit EV / EBITDA | B98: x | C98: =INDEX(Inputs!$D$59:$F$59,$C$3) -> 13.5
A99: Exit enterprise value | B99: €m | C99: =C97*C98 -> 1304.3888
A100: Exit costs | B100: €m | C100: =-C99*Inputs!$C$70 -> -19.565832
A101: Net debt at exit | B101: €m | C101: =-H90 -> -253.04699
A102: Exit equity value (100%) | B102: €m | C102: =SUM(C99:C101) -> 1031.776
A103: Equity invested at closing | B103: €m | C103: =Transaction!$C$20 -> 328.2 | I103: Total equity strip from Transaction sheet (ARCHIMED + founder + management)
A104: Capital gain before MIP | B104: €m | C104: =C102-C103 -> 703.57596
A105: MIP payout to management | B105: €m | C105: =-Inputs!$C$20*MAX(0,C104) -> -70.357596
A106: Exit equity to investors | B106: €m | C106: =C102+C105 -> 961.41836
A107: MOIC (investors) | B107: x | C107: =C106/C103 -> 2.9293673
A108: Investor cash flows | B108: €m | C108: =-C103 -> -328.2 | D108: 0 | E108: 0 | F108: 0 | G108: 0 | H108: =$C$106 -> 961.41836
A109: IRR (investors) | B109: % | C109: =IRR(C108:H108) -> 0.23980895 | I109: Single entry and exit cash flow: no interim equity injections or dividends
A110: Check: IRR equals MOIC^(1/5) – 1 (should be 0) | B110: % | C110: =C109-(C107^(1/H$6)-1) -> 0
...

Sheet LBO_Down
A1: Project Lumière – LBO model: Downside case
A2: €m unless stated · financial year to December · closing 31 December 2026 · exit 31 December 2031
A3: Case index (1 = Base, 2 = Management, 3 = Downside) | C3: 3
A5: €m | B5: Unit | C5: FY2026E | D5: FY2027 | E5: FY2028 | F5: FY2029 | G5: FY2030 | H5: FY2031
A6: Years from closing | C6: 0 | D6: =C6+1 -> 1 | E6: =D6+1 -> 2 | F6: =E6+1 -> 3 | G6: =F6+1 -> 4 | H6: =G6+1 -> 5
A7: Financial year | C7: 2026 | D7: =C7+1 -> 2027 | E7: =D7+1 -> 2028 | F7: =E7+1 -> 2029 | G7: =F7+1 -> 2030 | H7: =G7+1 -> 2031
A9: Revenue
A10: Organic revenue growth | B10: % | D10: =INDEX(Inputs!D$45:D$47,$C$3)+Inputs!$C$52 -> 0.04 | E10: =INDEX(Inputs!E$45:E$47,$C$3)+Inputs!$C$52 -> 0.04 | F10: =INDEX(Inputs!F$45:F$47,$C$3)+Inputs!$C$52 -> 0.045 | G10: =INDEX(Inputs!G$45:G$47,$C$3)+Inputs!$C$52 -> 0.045 | H10: =INDEX(Inputs!H$45:H$47,$C$3)+Inputs!$C$52 -> 0.045 | I10: Inputs rows 45–47 picked by case index, plus the flex delta
A11: Organic revenue | B11: €m | C11: =Inputs!$C$5 -> 150 | D11: =C11*(1+D10) -> 156 | E11: =D11*(1+E10) -> 162.24 | F11: =E11*(1+F10) -> 169.5408 | G11: =F11*(1+G10) -> 177.17014 | H11: =G11*(1+H10) -> 185.14279
A12: Add-on A revenue (Germany) | B12: €m | C12: 0 | D12: =IF(AND(INDEX(Inputs!$D$57:$F$57,$C$3)=1,D$7>=Inputs!$D$74),Inputs!$D$75*(1+Inputs!$D$76)^(D$7-Inputs!$D$74+1),0) -> 0 | E12: =IF(AND(INDEX(Inputs!$D$57:$F$57,$C$3)=1,E$7>=Inputs!$D$74),Inputs!$D$75*(1+Inputs!$D$76)^(E$7-Inputs!$D$74+1),0) -> 0 | F12: =IF(AND(INDEX(Inputs!$D$57:$F$57,$C$3)=1,F$7>=Inputs!$D$74),Inputs!$D$75*(1+Inputs!$D$76)^(F$7-Inputs!$D$74+1),0) -> 0 | G12: =IF(AND(INDEX(Inputs!$D$57:$F$57,$C$3)=1,G$7>=Inputs!$D$74),Inputs!$D$75*(1+Inputs!$D$76)^(G$7-Inputs!$D$74+1),0) -> 0 | H12: =IF(AND(INDEX(Inputs!$D$57:$F$57,$C$3)=1,H$7>=Inputs!$D$74),Inputs!$D$75*(1+Inputs!$D$76)^(H$7-Inputs!$D$74+1),0) -> 0 | I12: Consolidated from 1 January of the acquisition year
A13: Add-on B revenue (US) | B13: €m | C13: 0 | D13: =IF(AND(INDEX(Inputs!$D$58:$F$58,$C$3)=1,D$7>=Inputs!$E$74),Inputs!$E$75*(1+Inputs!$E$76)^(D$7-Inputs!$E$74+1),0) -> 0 | E13: =IF(AND(INDEX(Inputs!$D$58:$F$58,$C$3)=1,E$7>=Inputs!$E$74),Inputs!$E$75*(1+Inputs!$E$76)^(E$7-Inputs!$E$74+1),0) -> 0 | F13: =IF(AND(INDEX(Inputs!$D$58:$F$58,$C$3)=1,F$7>=Inputs!$E$74),Inputs!$E$75*(1+Inputs!$E$76)^(F$7-Inputs!$E$74+1),0) -> 0 | G13: =IF(AND(INDEX(Inputs!$D$58:$F$58,$C$3)=1,G$7>=Inputs!$E$74),Inputs!$E$75*(1+Inputs!$E$76)^(G$7-Inputs!$E$74+1),0) -> 0 | H13: =IF(AND(INDEX(Inputs!$D$58:$F$58,$C$3)=1,H$7>=Inputs!$E$74),Inputs!$E$75*(1+Inputs!$E$76)^(H$7-Inputs!$E$74+1),0) -> 0
A14: Total revenue | B14: €m | C14: =SUM(C11:C13) -> 150 | D14: =SUM(D11:D13) -> 156 | E14: =SUM(E11:E13) -> 162.24 | F14: =SUM(F11:F13) -> 169.5408 | G14: =SUM(G11:G13) -> 177.17014 | H14: =SUM(H11:H13) -> 185.14279
A15: Total revenue growth | B15: % | D15: =D14/C14-1 -> 0.04 | E15: =E14/D14-1 -> 0.04 | F15: =F14/E14-1 -> 0.045 | G15: =G14/F14-1 -> 0.045 | H15: =H14/G14-1 -> 0.045
A17: EBITDA (ARCHIMED definition: pre-IFRS 16, fully loaded)
A18: Organic EBITDA margin | B18: % | C18: =C19/C11 -> 0.26666667 | D18: =INDEX(Inputs!D$48:D$50,$C$3)+Inputs!$C$53 -> 0.265 | E18: =INDEX(Inputs!E$48:E$50,$C$3)+Inputs!$C$53 -> 0.265 | F18: =INDEX(Inputs!F$48:F$50,$C$3)+Inputs!$C$53 -> 0.265 | G18: =INDEX(Inputs!G$48:G$50,$C$3)+Inputs!$C$53 -> 0.265 | H18: =INDEX(Inputs!H$48:H$50,$C$3)+Inputs!$C$53 -> 0.265
A19: Organic EBITDA | B19: €m | C19: =Inputs!$C$8 -> 40 | D19: =D11*D18 -> 41.34 | E19: =E11*E18 -> 42.9936 | F19: =F11*F18 -> 44.928312 | G19: =G11*G18 -> 46.950086 | H19: =H11*H18 -> 49.06284
A20: Add-on A EBITDA (standalone) | B20: €m | C20: 0 | D20: =D12*Inputs!$D$77 -> 0 | E20: =E12*Inputs!$D$77 -> 0 | F20: =F12*Inputs!$D$77 -> 0 | G20: =G12*Inputs!$D$77 -> 0 | H20: =H12*Inputs!$D$77 -> 0
A21: Add-on A cost synergies | B21: €m | C21: 0 | D21: =IF(D12>0,Inputs!$D$81*IF(D$7-Inputs!$D$74=0,Inputs!$D$82,IF(D$7-Inputs!$D$74=1,Inputs!$D$83,Inputs!$D$84)),0) -> 0 | E21: =IF(E12>0,Inputs!$D$81*IF(E$7-Inputs!$D$74=0,Inputs!$D$82,IF(E$7-Inputs!$D$74=1,Inputs!$D$83,Inputs!$D$84)),0) -> 0 | F21: =IF(F12>0,Inputs!$D$81*IF(F$7-Inputs!$D$74=0,Inputs!$D$82,IF(F$7-Inputs!$D$74=1,Inputs!$D$83,Inputs!$D$84)),0) -> 0 | G21: =IF(G12>0,Inputs!$D$81*IF(G$7-Inputs!$D$74=0,Inputs!$D$82,IF(G$7-Inputs!$D$74=1,Inputs!$D$83,Inputs!$D$84)),0) -> 0 | H21: =IF(H12>0,Inputs!$D$81*IF(H$7-Inputs!$D$74=0,Inputs!$D$82,IF(H$7-Inputs!$D$74=1,Inputs!$D$83,Inputs!$D$84)),0) -> 0
A22: Add-on B EBITDA (standalone) | B22: €m | C22: 0 | D22: =D13*Inputs!$E$77 -> 0 | E22: =E13*Inputs!$E$77 -> 0 | F22: =F13*Inputs!$E$77 -> 0 | G22: =G13*Inputs!$E$77 -> 0 | H22: =H13*Inputs!$E$77 -> 0
A23: Add-on B cost synergies | B23: €m | C23: 0 | D23: =IF(D13>0,Inputs!$E$81*IF(D$7-Inputs!$E$74=0,Inputs!$E$82,IF(D$7-Inputs!$E$74=1,Inputs!$E$83,Inputs!$E$84)),0) -> 0 | E23: =IF(E13>0,Inputs!$E$81*IF(E$7-Inputs!$E$74=0,Inputs!$E$82,IF(E$7-Inputs!$E$74=1,Inputs!$E$83,Inputs!$E$84)),0) -> 0 | F23: =IF(F13>0,Inputs!$E$81*IF(F$7-Inputs!$E$74=0,Inputs!$E$82,IF(F$7-Inputs!$E$74=1,Inputs!$E$83,Inputs!$E$84)),0) -> 0 | G23: =IF(G13>0,Inputs!$E$81*IF(G$7-Inputs!$E$74=0,Inputs!$E$82,IF(G$7-Inputs!$E$74=1,Inputs!$E$83,Inputs!$E$84)),0) -> 0 | H23: =IF(H13>0,Inputs!$E$81*IF(H$7-Inputs!$E$74=0,Inputs!$E$82,IF(H$7-Inputs!$E$74=1,Inputs!$E$83,Inputs!$E$84)),0) -> 0
A24: Total EBITDA | B24: €m | C24: =SUM(C19:C23) -> 40 | D24: =SUM(D19:D23) -> 41.34 | E24: =SUM(E19:E23) -> 42.9936 | F24: =SUM(F19:F23) -> 44.928312 | G24: =SUM(G19:G23) -> 46.950086 | H24: =SUM(H19:H23) -> 49.06284
A25: EBITDA margin | B25: % | C25: =C24/C14 -> 0.26666667 | D25: =D24/D14 -> 0.265 | E25: =E24/E14 -> 0.265 | F25: =F24/F14 -> 0.265 | G25: =G24/G14 -> 0.265 | H25: =H24/H14 -> 0.265
A26: EBITDA growth | B26: % | D26: =D24/C24-1 -> 0.0335 | E26: =E24/D24-1 -> 0.04 | F26: =F24/E24-1 -> 0.045 | G26: =G24/F24-1 -> 0.045 | H26: =H24/G24-1 -> 0.045
A28: Free cash flow
A29: EBITDA | B29: €m | D29: =D24 -> 41.34 | E29: =E24 -> 42.9936 | F29: =F24 -> 44.928312 | G29: =G24 -> 46.950086 | H29: =H24 -> 49.06284
A30: One-off integration costs | B30: €m | D30: =-(IF(AND(INDEX(Inputs!$D$57:$F$57,$C$3)=1,D$7=Inputs!$D$74),Inputs!$D$80,0)+IF(AND(INDEX(Inputs!$D$58:$F$58,$C$3)=1,D$7=Inputs!$E$74),Inputs!$E$80,0)) -> 0 | E30: =-(IF(AND(INDEX(Inputs!$D$57:$F$57,$C$3)=1,E$7=Inputs!$D$74),Inputs!$D$80,0)+IF(AND(INDEX(Inputs!$D$58:$F$58,$C$3)=1,E$7=Inputs!$E$74),Inputs!$E$80,0)) -> 0 | F30: =-(IF(AND(INDEX(Inputs!$D$57:$F$57,$C$3)=1,F$7=Inputs!$D$74),Inputs!$D$80,0)+IF(AND(INDEX(Inputs!$D$58:$F$58,$C$3)=1,F$7=Inputs!$E$74),Inputs!$E$80,0)) -> 0 | G30: =-(IF(AND(INDEX(Inputs!$D$57:$F$57,$C$3)=1,G$7=Inputs!$D$74),Inputs!$D$80,0)+IF(AND(INDEX(Inputs!$D$58:$F$58,$C$3)=1,G$7=Inputs!$E$74),Inputs!$E$80,0)) -> 0 | H30: =-(IF(AND(INDEX(Inputs!$D$57:$F$57,$C$3)=1,H$7=Inputs!$D$74),Inputs!$D$80,0)+IF(AND(INDEX(Inputs!$D$58:$F$58,$C$3)=1,H$7=Inputs!$E$74),Inputs!$E$80,0)) -> 0
A31: Maintenance and placed-analyzer capex | B31: €m | D31: =-D14*Inputs!$C$63 -> -6.24 | E31: =-E14*Inputs!$C$63 -> -6.4896 | F31: =-F14*Inputs!$C$63 -> -6.781632 | G31: =-G14*Inputs!$C$63 -> -7.0868054 | H31: =-H14*Inputs!$C$63 -> -7.4057117
A32: Capitalised R&D | B32: €m | D32: =-D14*Inputs!$C$64 -> -2.34 | E32: =-E14*Inputs!$C$64 -> -2.4336 | F32: =-F14*Inputs!$C$64 -> -2.543112 | G32: =-G14*Inputs!$C$64 -> -2.657552 | H32: =-H14*Inputs!$C$64 -> -2.7771419
A33: Growth capex | B33: €m | D33: =-Inputs!D$65 -> -5 | E33: =-Inputs!E$65 -> -4 | F33: =-Inputs!F$65 -> -2 | G33: =-Inputs!G$65 -> 0 | H33: =-Inputs!H$65 -> 0
A34: Change in net working capital | B34: €m | D34: =-(D57-C57-D58) -> -1.32 | E34: =-(E57-D57-E58) -> -1.3728 | F34: =-(F57-E57-F58) -> -1.606176 | G34: =-(G57-F57-G58) -> -1.6784539 | H34: =-(H57-G57-H58) -> -1.7539843 | I34: Excludes the working capital bought with add-ons (paid for in the purchase price)
A35: Cash taxes | B35: €m | D35: =-D54 -> -5.2845 | E35: =-E54 -> -5.49588 | F35: =-F54 -> -5.7431946 | G35: =-G54 -> -6.0016384 | H35: =-H54 -> -6.2717121
A36: Net interest expense | B36: €m | D36: =-D86 -> -18.29875 | E36: =-E86 -> -18.105919 | F36: =-F86 -> -17.761953 | G36: =-G86 -> -17.188726 | H36: =-H86 -> -16.355985
A37: Free cash flow | B37: €m | D37: =SUM(D29:D36) -> 2.85675 | E37: =SUM(E29:E36) -> 5.0958006 | F37: =SUM(F29:F36) -> 8.4922446 | G37: =SUM(G29:G36) -> 12.33691 | H37: =SUM(H29:H36) -> 14.498305
A38: Earn-out paid to the vendor | B38: €m | D38: =-IF(D$7=Inputs!$C$23,$C$137,0) -> 0 | E38: =-IF(E$7=Inputs!$C$23,$C$137,0) -> 0 | F38: =-IF(F$7=Inputs!$C$23,$C$137,0) -> 0 | G38: =-IF(G$7=Inputs!$C$23,$C$137,0) -> 0 | H38: =-IF(H$7=Inputs!$C$23,$C$137,0) -> 0 | I38: Paid by the company in the payment year; reduces debt paydown
A39: Add-on acquisitions incl. deal costs | B39: €m | D39: =-(IF(AND(INDEX(Inputs!$D$57:$F$57,$C$3)=1,D$7=Inputs!$D$74),Inputs!$D$86,0)+IF(AND(INDEX(Inputs!$D$58:$F$58,$C$3)=1,D$7=Inputs!$E$74),Inputs!$E$86,0)) -> 0 | E39: =-(IF(AND(INDEX(Inputs!$D$57:$F$57,$C$3)=1,E$7=Inputs!$D$74),Inputs!$D$86,0)+IF(AND(INDEX(Inputs!$D$58:$F$58,$C$3)=1,E$7=Inputs!$E$74),Inputs!$E$86,0)) -> 0 | F39: =-(IF(AND(INDEX(Inputs!$D$57:$F$57,$C$3)=1,F$7=Inputs!$D$74),Inputs!$D$86,0)+IF(AND(INDEX(Inputs!$D$58:$F$58,$C$3)=1,F$7=Inputs!$E$74),Inputs!$E$86,0)) -> 0 | G39: =-(IF(AND(INDEX(Inputs!$D$57:$F$57,$C$3)=1,G$7=Inputs!$D$74),Inputs!$D$86,0)+IF(AND(INDEX(Inputs!$D$58:$F$58,$C$3)=1,G$7=Inputs!$E$74),Inputs!$E$86,0)) -> 0 | H39: =-(IF(AND(INDEX(Inputs!$D$57:$F$57,$C$3)=1,H$7=Inputs!$D$74),Inputs!$D$86,0)+IF(AND(INDEX(Inputs!$D$58:$F$58,$C$3)=1,H$7=Inputs!$E$74),Inputs!$E$86,0)) -> 0
A40: Cash flow before debt movements | B40: €m | D40: =D37+D38+D39 -> 2.85675 | E40: =E37+E38+E39 -> 5.0958006 | F40: =F37+F38+F39 -> 8.4922446 | G40: =G37+G38+G39 -> 12.33691 | H40: =H37+H38+H39 -> 14.498305
A41: Cash conversion: (EBITDA – capex – ΔNWC) / EBITDA | B41: % | D41: =(D29+D31+D32+D33+D34)/D29 -> 0.63957426 | E41: =(E29+E31+E32+E33+E34)/E29 -> 0.66748539 | F41: =(F29+F31+F32+F33+F34)/F29 -> 0.71218772 | G41: =(G29+G31+G32+G33+G34)/G29 -> 0.75670308 | H41: =(H29+H31+H32+H33+H34)/H29 -> 0.75670308
A43: Corporate tax (French interest cap)
A44: EBITDA | B44: €m | D44: =D24 -> 41.34 | E44: =E24 -> 42.9936 | F44: =F24 -> 44.928312 | G44: =G24 -> 46.950086 | H44: =H24 -> 49.06284
A45: One-off integration costs | B45: €m | D45: =D30 -> 0 | E45: =E30 -> 0 | F45: =F30 -> 0 | G45: =G30 -> 0 | H45: =H30 -> 0
A46: Depreciation and amortisation | B46: €m | D46: =-D14*Inputs!$C$62 -> -7.8 | E46: =-E14*Inputs!$C$62 -> -8.112 | F46: =-F14*Inputs!$C$62 -> -8.47704 | G46: =-G14*Inputs!$C$62 -> -8.8585068 | H46: =-H14*Inputs!$C$62 -> -9.2571396
A47: EBIT | B47: €m | D47: =SUM(D44:D46) -> 33.54 | E47: =SUM(E44:E46) -> 34.8816 | F47: =SUM(F44:F46) -> 36.451272 | G47: =SUM(G44:G46) -> 38.091579 | H47: =SUM(H44:H46) -> 39.8057
A48: Net interest expense | B48: €m | D48: =D86 -> 18.29875 | E48: =E86 -> 18.105919 | F48: =F86 -> 17.761953 | G48: =G86 -> 17.188726 | H48: =H86 -> 16.355985
A49: Interest deduction capacity (higher of 30% of EBITDA or €3m) | B49: €m | D49: =MAX(Inputs!$C$69,Inputs!$C$68*D44) -> 12.402 | E49: =MAX(Inputs!$C$69,Inputs!$C$68*E44) -> 12.89808 | F49: =MAX(Inputs!$C$69,Inputs!$C$68*F44) -> 13.478494 | G49: =MAX(Inputs!$C$69,Inputs!$C$68*G44) -> 14.085026 | H49: =MAX(Inputs!$C$69,Inputs!$C$68*H44) -> 14.718852 | I49: French rule: net interest deductible up to the higher of 30% of tax EBITDA or €3m; excess carried forward
A50: Disallowed interest brought forward | B50: €m | D50: =C52 -> 0 | E50: =D52 -> 5.89675 | F50: =E52 -> 11.104589 | G50: =F52 -> 15.388049 | H50: =G52 -> 18.491749
A51: Deductible interest | B51: €m | D51: =MAX(0,MIN(D48+D50,D49)) -> 12.402 | E51: =MAX(0,MIN(E48+E50,E49)) -> 12.89808 | F51: =MAX(0,MIN(F48+F50,F49)) -> 13.478494 | G51: =MAX(0,MIN(G48+G50,G49)) -> 14.085026 | H51: =MAX(0,MIN(H48+H50,H49)) -> 14.718852
A52: Disallowed interest carried forward | B52: €m | C52: 0 | D52: =MAX(0,D48+D50-D51) -> 5.89675 | E52: =MAX(0,E48+E50-E51) -> 11.104589 | F52: =MAX(0,F48+F50-F51) -> 15.388049 | G52: =MAX(0,G48+G50-G51) -> 18.491749 | H52: =MAX(0,H48+H50-H51) -> 20.128882
A53: Taxable income | B53: €m | D53: =MAX(0,D47-D51) -> 21.138 | E53: =MAX(0,E47-E51) -> 21.98352 | F53: =MAX(0,F47-F51) -> 22.972778 | G53: =MAX(0,G47-G51) -> 24.006553 | H53: =MAX(0,H47-H51) -> 25.086848
A54: Cash tax | B54: €m | D54: =D53*Inputs!$C$67 -> 5.2845 | E54: =E53*Inputs!$C$67 -> 5.49588 | F54: =F53*Inputs!$C$67 -> 5.7431946 | G54: =G53*Inputs!$C$67 -> 6.0016384 | H54: =H53*Inputs!$C$67 -> 6.2717121
A56: Net working capital (memo)
A57: Net working capital | B57: €m | C57: =C14*Inputs!$C$66 -> 33 | D57: =D14*Inputs!$C$66 -> 34.32 | E57: =E14*Inputs!$C$66 -> 35.6928 | F57: =F14*Inputs!$C$66 -> 37.298976 | G57: =G14*Inputs!$C$66 -> 38.97743 | H57: =H14*Inputs!$C$66 -> 40.731414
A58: Net working capital acquired with add-ons | B58: €m | D58: =(IF(AND(INDEX(Inputs!$D$57:$F$57,$C$3)=1,D$7=Inputs!$D$74),Inputs!$D$75,0)+IF(AND(INDEX(Inputs!$D$58:$F$58,$C$3)=1,D$7=Inputs!$E$74),Inputs!$E$75,0))*Inputs!$C$66 -> 0 | E58: =(IF(AND(INDEX(Inputs!$D$57:$F$57,$C$3)=1,E$7=Inputs!$D$74),Inputs!$D$75,0)+IF(AND(INDEX(Inputs!$D$58:$F$58,$C$3)=1,E$7=Inputs!$E$74),Inputs!$E$75,0))*Inputs!$C$66 -> 0 | F58: =(IF(AND(INDEX(Inputs!$D$57:$F$57,$C$3)=1,F$7=Inputs!$D$74),Inputs!$D$75,0)+IF(AND(INDEX(Inputs!$D$58:$F$58,$C$3)=1,F$7=Inputs!$E$74),Inputs!$E$75,0))*Inputs!$C$66 -> 0 | G58: =(IF(AND(INDEX(Inputs!$D$57:$F$57,$C$3)=1,G$7=Inputs!$D$74),Inputs!$D$75,0)+IF(AND(INDEX(Inputs!$D$58:$F$58,$C$3)=1,G$7=Inputs!$E$74),Inputs!$E$75,0))*Inputs!$C$66 -> 0 | H58: =(IF(AND(INDEX(Inputs!$D$57:$F$57,$C$3)=1,H$7=Inputs!$D$74),Inputs!$D$75,0)+IF(AND(INDEX(Inputs!$D$58:$F$58,$C$3)=1,H$7=Inputs!$E$74),Inputs!$E$75,0))*Inputs!$C$66 -> 0
A60: Debt and cash (interest on opening balances, so no circularity)
A61: Unitranche – opening | B61: €m | D61: =C63 -> 240 | E61: =D63 -> 237.14325 | F61: =E63 -> 232.04745 | G61: =F63 -> 223.5552 | H61: =G63 -> 211.21829
A62: Unitranche – prepayment from excess cash | B62: €m | D62: =D77 -> -2.85675 | E62: =E77 -> -5.0958006 | F62: =F77 -> -8.4922446 | G62: =G77 -> -12.33691 | H62: =H77 -> -14.498305
A63: Unitranche – closing | B63: €m | C63: =Inputs!$C$29 -> 240 | D63: =D61+D62 -> 237.14325 | E63: =E61+E62 -> 232.04745 | F63: =F61+F62 -> 223.5552 | G63: =G61+G62 -> 211.21829 | H63: =H61+H62 -> 196.71999
A64: Capex and acquisition facility – opening | B64: €m | D64: =C66 -> 0 | E64: =D66 -> 0 | F64: =E66 -> 0 | G64: =F66 -> 0 | H64: =G66 -> 0
A65: Capex and acquisition facility – drawdown | B65: €m | D65: =MIN(-D39,Inputs!$C$31-D64) -> 0 | E65: =MIN(-E39,Inputs!$C$31-E64) -> 0 | F65: =MIN(-F39,Inputs!$C$31-F64) -> 0 | G65: =MIN(-G39,Inputs!$C$31-G64) -> 0 | H65: =MIN(-H39,Inputs!$C$31-H64) -> 0 | I65: Add-ons funded 100% by the CAF; any shortfall falls to cash and the RCF
A66: Capex and acquisition facility – closing | B66: €m | C66: 0 | D66: =D64+D65 -> 0 | E66: =E64+E65 -> 0 | F66: =F64+F65 -> 0 | G66: =G64+G65 -> 0 | H66: =H64+H65 -> 0
A67: Revolving credit facility – opening | B67: €m | D67: =C70 -> 0 | E67: =D70 -> 0 | F67: =E70 -> 0 | G67: =F70 -> 0 | H67: =G70 -> 0
A68: Revolving credit facility – drawdown | B68: €m | D68: =MIN(MAX(0,Inputs!$C$17-D74),Inputs!$C$32-D67) -> 0 | E68: =MIN(MAX(0,Inputs!$C$17-E74),Inputs!$C$32-E67) -> 0 | F68: =MIN(MAX(0,Inputs!$C$17-F74),Inputs!$C$32-F67) -> 0 | G68: =MIN(MAX(0,Inputs!$C$17-G74),Inputs!$C$32-G67) -> 0 | H68: =MIN(MAX(0,Inputs!$C$17-H74),Inputs!$C$32-H67) -> 0
A69: Revolving credit facility – repayment | B69: €m | D69: =-MIN(D67,MAX(0,D74-Inputs!$C$17)) -> 0 | E69: =-MIN(E67,MAX(0,E74-Inputs!$C$17)) -> 0 | F69: =-MIN(F67,MAX(0,F74-Inputs!$C$17)) -> 0 | G69: =-MIN(G67,MAX(0,G74-Inputs!$C$17)) -> 0 | H69: =-MIN(H67,MAX(0,H74-Inputs!$C$17)) -> 0
A70: Revolving credit facility – closing | B70: €m | C70: 0 | D70: =D67+D68+D69 -> 0 | E70: =E67+E68+E69 -> 0 | F70: =F67+F68+F69 -> 0 | G70: =G67+G68+G69 -> 0 | H70: =H67+H68+H69 -> 0
A71: Cash – opening | B71: €m | D71: =C78 -> 10 | E71: =D78 -> 10 | F71: =E78 -> 10 | G71: =F78 -> 10 | H71: =G78 -> 10
A72: Cash flow before debt movements | B72: €m | D72: =D40 -> 2.85675 | E72: =E40 -> 5.0958006 | F72: =F40 -> 8.4922446 | G72: =G40 -> 12.33691 | H72: =H40 -> 14.498305
A73: Drawdown of capex and acquisition facility | B73: €m | D73: =D65 -> 0 | E73: =E65 -> 0 | F73: =F65 -> 0 | G73: =G65 -> 0 | H73: =H65 -> 0
A74: Cash available before RCF | B74: €m | D74: =D71+D72+D73 -> 12.85675 | E74: =E71+E72+E73 -> 15.095801 | F74: =F71+F72+F73 -> 18.492245 | G74: =G71+G72+G73 -> 22.33691 | H74: =H71+H72+H73 -> 24.498305
A75: RCF drawdown / (repayment) | B75: €m | D75: =D68+D69 -> 0 | E75: =E68+E69 -> 0 | F75: =F68+F69 -> 0 | G75: =G68+G69 -> 0 | H75: =H68+H69 -> 0
A76: Cash available before prepayment | B76: €m | D76: =D74+D75 -> 12.85675 | E76: =E74+E75 -> 15.095801 | F76: =F74+F75 -> 18.492245 | G76: =G74+G75 -> 22.33691 | H76: =H74+H75 -> 24.498305
A77: Unitranche prepayment | B77: €m | D77: =-MIN(D61,MAX(0,D76-Inputs!$C$17)*Inputs!$C$40) -> -2.85675 | E77: =-MIN(E61,MAX(0,E76-Inputs!$C$17)*Inputs!$C$40) -> -5.0958006 | F77: =-MIN(F61,MAX(0,F76-Inputs!$C$17)*Inputs!$C$40) -> -8.4922446 | G77: =-MIN(G61,MAX(0,G76-Inputs!$C$17)*Inputs!$C$40) -> -12.33691 | H77: =-MIN(H61,MAX(0,H76-Inputs!$C$17)*Inputs!$C$40) -> -14.498305 | I77: Cash above the minimum prepays the unitranche (Inputs C40)
A78: Cash – closing | B78: €m | C78: =Inputs!$C$17 -> 10 | D78: =D76+D77 -> 10 | E78: =E76+E77 -> 10 | F78: =F76+F77 -> 10 | G78: =G76+G77 -> 10 | H78: =H76+H77 -> 10
A80: Interest
A81: Unitranche interest | B81: €m | D81: =D61*(Inputs!$C$34+Inputs!$C$35) -> 16.2 | E81: =E61*(Inputs!$C$34+Inputs!$C$35) -> 16.007169 | F81: =F61*(Inputs!$C$34+Inputs!$C$35) -> 15.663203 | G81: =G61*(Inputs!$C$34+Inputs!$C$35) -> 15.089976 | H81: =H61*(Inputs!$C$34+Inputs!$C$35) -> 14.257235
A82: Capex and acquisition facility interest | B82: €m | D82: =(D64+D65)*(Inputs!$C$34+Inputs!$C$36) -> 0 | E82: =(E64+E65)*(Inputs!$C$34+Inputs!$C$36) -> 0 | F82: =(F64+F65)*(Inputs!$C$34+Inputs!$C$36) -> 0 | G82: =(G64+G65)*(Inputs!$C$34+Inputs!$C$36) -> 0 | H82: =(H64+H65)*(Inputs!$C$34+Inputs!$C$36) -> 0
A83: RCF interest | B83: €m | D83: =D67*(Inputs!$C$34+Inputs!$C$37) -> 0 | E83: =E67*(Inputs!$C$34+Inputs!$C$37) -> 0 | F83: =F67*(Inputs!$C$34+Inputs!$C$37) -> 0 | G83: =G67*(Inputs!$C$34+Inputs!$C$37) -> 0 | H83: =H67*(Inputs!$C$34+Inputs!$C$37) -> 0
A84: Commitment fees on undrawn facilities | B84: €m | D84: =Inputs!$C$38*(Inputs!$C$36*(Inputs!$C$31-D64-D65)+Inputs!$C$37*(Inputs!$C$32-D67)) -> 2.24875 | E84: =Inputs!$C$38*(Inputs!$C$36*(Inputs!$C$31-E64-E65)+Inputs!$C$37*(Inputs!$C$32-E67)) -> 2.24875 | F84: =Inputs!$C$38*(Inputs!$C$36*(Inputs!$C$31-F64-F65)+Inputs!$C$37*(Inputs!$C$32-F67)) -> 2.24875 | G84: =Inputs!$C$38*(Inputs!$C$36*(Inputs!$C$31-G64-G65)+Inputs!$C$37*(Inputs!$C$32-G67)) -> 2.24875 | H84: =Inputs!$C$38*(Inputs!$C$36*(Inputs!$C$31-H64-H65)+Inputs!$C$37*(Inputs!$C$32-H67)) -> 2.24875
A85: Interest income on cash | B85: €m | D85: =-D71*Inputs!$C$39 -> -0.15 | E85: =-E71*Inputs!$C$39 -> -0.15 | F85: =-F71*Inputs!$C$39 -> -0.15 | G85: =-G71*Inputs!$C$39 -> -0.15 | H85: =-H71*Inputs!$C$39 -> -0.15
A86: Net interest expense | B86: €m | D86: =SUM(D81:D85) -> 18.29875 | E86: =SUM(E81:E85) -> 18.105919 | F86: =SUM(F81:F85) -> 17.761953 | G86: =SUM(G81:G85) -> 17.188726 | H86: =SUM(H81:H85) -> 16.355985
A88: Credit statistics
A89: Total debt | B89: €m | C89: =C63+C66+C70 -> 240 | D89: =D63+D66+D70 -> 237.14325 | E89: =E63+E66+E70 -> 232.04745 | F89: =F63+F66+F70 -> 223.5552 | G89: =G63+G66+G70 -> 211.21829 | H89: =H63+H66+H70 -> 196.71999
A90: Net debt | B90: €m | C90: =C89-C78 -> 230 | D90: =D89-D78 -> 227.14325 | E90: =E89-E78 -> 222.04745 | F90: =F89-F78 -> 213.5552 | G90: =G89-G78 -> 201.21829 | H90: =H89-H78 -> 186.71999
A91: Net debt / EBITDA | B91: x | C91: =C90/C24 -> 5.75 | D91: =D90/D24 -> 5.494515 | E91: =E90/E24 -> 5.1646629 | F91: =F90/F24 -> 4.7532435 | G91: =G90/G24 -> 4.2857918 | H91: =H90/H24 -> 3.8057314
A92: EBITDA / net interest | B92: x | D92: =D24/D86 -> 2.2591707 | E92: =E24/E86 -> 2.3745604 | F92: =F24/F86 -> 2.5294692 | G92: =G24/G86 -> 2.7314465 | H92: =H24/H86 -> 2.9996873
A93: Covenant headroom (EBITDA could fall by) | B93: % | C93: =1-C91/Inputs!$C$41 -> 0.3030303 | D93: =1-D91/Inputs!$C$41 -> 0.33399818 | E93: =1-E91/Inputs!$C$41 -> 0.37398026 | F93: =1-F91/Inputs!$C$41 -> 0.42384928 | G93: =1-G91/Inputs!$C$41 -> 0.48051008 | H93: =1-H91/Inputs!$C$41 -> 0.53869923 | I93: How far EBITDA could fall before breaching the leverage covenant
A94: Check: net debt roll-forward (should be 0) | B94: €m | D94: =D90-(C90-D40) -> 0 | E94: =E90-(D90-E40) -> 0 | F94: =F90-(E90-F40) -> 0 | G94: =G90-(F90-G40) -> 0 | H94: =H90-(G90-H40) -> 0
A96: Returns – exit at the end of FY2031
A97: Exit-year EBITDA (FY2031) | B97: €m | C97: =H24 -> 49.06284
A98: Exit EV / EBITDA | B98: x | C98: =INDEX(Inputs!$D$59:$F$59,$C$3) -> 12
A99: Exit enterprise value | B99: €m | C99: =C97*C98 -> 588.75408
A100: Exit costs | B100: €m | C100: =-C99*Inputs!$C$70 -> -8.8313112
A101: Net debt at exit | B101: €m | C101: =-H90 -> -186.71999
A102: Exit equity value (100%) | B102: €m | C102: =SUM(C99:C101) -> 393.20278
A103: Equity invested at closing | B103: €m | C103: =Transaction!$C$20 -> 328.2 | I103: Total equity strip from Transaction sheet (ARCHIMED + founder + management)
A104: Capital gain before MIP | B104: €m | C104: =C102-C103 -> 65.002778
A105: MIP payout to management | B105: €m | C105: =-Inputs!$C$20*MAX(0,C104) -> -6.5002778
A106: Exit equity to investors | B106: €m | C106: =C102+C105 -> 386.7025
A107: MOIC (investors) | B107: x | C107: =C106/C103 -> 1.1782526
A108: Investor cash flows | B108: €m | C108: =-C103 -> -328.2 | D108: 0 | E108: 0 | F108: 0 | G108: 0 | H108: =$C$106 -> 386.7025
A109: IRR (investors) | B109: % | C109: =IRR(C108:H108) -> 0.033350564 | I109: Single entry and exit cash flow: no interim equity injections or dividends
A110: Check: IRR equals MOIC^(1/5) – 1 (should be 0) | B110: % | C110: =C109-(C107^(1/H$6)-1) -> 0
...

Sheet Returns
A1: Project Lumière – returns summary and sensitivities
A2: Investor returns = gross to the equity strip, after the management MIP, before fund fees and carry. €m unless stated.
A4: 1. Returns by case (exit at the end of FY2031)
A5: Metric | B5: Unit | C5: Base | D5: Management | E5: Downside
A6: FY2031 revenue | B6: €m | C6: =LBO_Base!H14 -> 279.45958 | D6: =LBO_Mgmt!H14 -> 310.78803 | E6: =LBO_Down!H14 -> 185.14279
A7: FY2031 EBITDA | B7: €m | C7: =LBO_Base!H24 -> 82.759838 | D7: =LBO_Mgmt!H24 -> 96.621391 | E7: =LBO_Down!H24 -> 49.06284
A8: FY2031 EBITDA margin | B8: % | C8: =LBO_Base!H25 -> 0.29614243 | D8: =LBO_Mgmt!H25 -> 0.31089161 | E8: =LBO_Down!H25 -> 0.265
A9: EBITDA CAGR FY2026E–FY2031 (incl. add-ons) | B9: % | C9: =(LBO_Base!H24/LBO_Base!C24)^(1/5)-1 -> 0.15651675 | D9: =(LBO_Mgmt!H24/LBO_Mgmt!C24)^(1/5)-1 -> 0.19289621 | E9: =(LBO_Down!H24/LBO_Down!C24)^(1/5)-1 -> 0.041690104
A10: Exit EV / EBITDA | B10: x | C10: =LBO_Base!C98 -> 13.5 | D10: =LBO_Mgmt!C98 -> 13.5 | E10: =LBO_Down!C98 -> 12
A11: Exit enterprise value | B11: €m | C11: =LBO_Base!C99 -> 1117.2578 | D11: =LBO_Mgmt!C99 -> 1304.3888 | E11: =LBO_Down!C99 -> 588.75408
A12: Net debt at exit | B12: €m | C12: =-LBO_Base!C101 -> 230.1109 | D12: =-LBO_Mgmt!C101 -> 253.04699 | E12: =-LBO_Down!C101 -> 186.71999
A13: Exit equity value (100%) | B13: €m | C13: =LBO_Base!C102 -> 870.38804 | D13: =LBO_Mgmt!C102 -> 1031.776 | E13: =LBO_Down!C102 -> 393.20278
A14: MIP payout to management | B14: €m | C14: =-LBO_Base!C105 -> 54.218804 | D14: =-LBO_Mgmt!C105 -> 70.357596 | E14: =-LBO_Down!C105 -> 6.5002778
A15: Exit equity to investors | B15: €m | C15: =LBO_Base!C106 -> 816.16924 | D15: =LBO_Mgmt!C106 -> 961.41836 | E15: =LBO_Down!C106 -> 386.7025
A16: Equity invested at closing | B16: €m | C16: =LBO_Base!C103 -> 328.2 | D16: =LBO_Mgmt!C103 -> 328.2 | E16: =LBO_Down!C103 -> 328.2
A17: MOIC | B17: x | C17: =LBO_Base!C107 -> 2.4868045 | D17: =LBO_Mgmt!C107 -> 2.9293673 | E17: =LBO_Down!C107 -> 1.1782526
A18: IRR | B18: % | C18: =LBO_Base!C109 -> 0.19985379 | D18: =LBO_Mgmt!C109 -> 0.23980895 | E18: =LBO_Down!C109 -> 0.033350564
A19: Earn-out paid to vendor | B19: €m | C19: =-LBO_Base!C128 -> 0 | D19: =-LBO_Mgmt!C128 -> 40 | E19: =-LBO_Down!C128 -> 0
A20: Add-ons acquired (price incl. costs) | B20: €m | C20: =-LBO_Base!C127 -> 87.8384 | D20: =-LBO_Mgmt!C127 -> 87.8384 | E20: =-LBO_Down!C127 -> 0
A21: Peak net leverage, FY2027–FY2031 | B21: x | C21: =MAX(LBO_Base!D91:H91) -> 5.0975229 | D21: =MAX(LBO_Mgmt!D91:H91) -> 4.887672 | E21: =MAX(LBO_Down!D91:H91) -> 5.494515
A22: Lowest EBITDA / net interest | B22: x | C22: =MIN(LBO_Base!D92:H92) -> 2.4233213 | D22: =MIN(LBO_Mgmt!D92:H92) -> 2.521757 | E22: =MIN(LBO_Down!D92:H92) -> 2.2591707
A23: Lowest covenant headroom | B23: % | C23: =MIN(LBO_Base!D93:H93) -> 0.38211844 | D23: =MIN(LBO_Mgmt!D93:H93) -> 0.40755491 | E23: =MIN(LBO_Down!D93:H93) -> 0.33399818
A24: ARCHIMED equity invested | B24: €m | C24: =Transaction!$C$15 -> 282.2 | D24: =Transaction!$C$15 -> 282.2 | E24: =Transaction!$C$15 -> 282.2
A25: ARCHIMED exit proceeds | B25: €m | C25: =C15*Transaction!$D$21 -> 701.77623 | D25: =D15*Transaction!$D$21 -> 826.66747 | E25: =E15*Transaction!$D$21 -> 332.50288
A26: ARCHIMED capital gain | B26: €m | C26: =C25-C24 -> 419.57623 | D26: =D25-D24 -> 544.46747 | E26: =E25-E24 -> 50.302881
A28: 2. Equity value bridge – Base case
A29: Step | B29: Unit | C29: €m | D29: % of gain
A30: Equity invested at closing | B30: €m | C30: =LBO_Base!C123 -> 328.2
A31: Organic EBITDA growth × entry multiple | B31: €m | C31: =LBO_Base!C124 -> 380.64287 | D31: =C31/($C$40-$C$30) -> 0.78005506
A32: Add-on EBITDA incl. synergies × entry multiple | B32: €m | C32: =LBO_Base!C125 -> 196.61494 | D32: =C32/($C$40-$C$30) -> 0.40292486
A33: Exit vs. entry multiple | B33: €m | C33: =LBO_Base!C126 -> 0 | D33: =C33/($C$40-$C$30) -> 0
A34: Add-on purchase prices (debt-funded) | B34: €m | C34: =LBO_Base!C127 -> -87.8384 | D34: =C34/($C$40-$C$30) -> -0.18000807
A35: Earn-out paid | B35: €m | C35: =LBO_Base!C128 -> 0 | D35: =C35/($C$40-$C$30) -> 0
A36: Cumulative free cash flow (debt paydown) | B36: €m | C36: =LBO_Base!C129 -> 87.727498 | D36: =C36/($C$40-$C$30) -> 0.1797808
A37: Transaction and financing fees | B37: €m | C37: =LBO_Base!C130 -> -18.2 | D37: =C37/($C$40-$C$30) -> -0.037297433
A38: Exit costs | B38: €m | C38: =LBO_Base!C131 -> -16.758867 | D38: =C38/($C$40-$C$30) -> -0.034344106
A39: MIP payout | B39: €m | C39: =LBO_Base!C132 -> -54.218804 | D39: =C39/($C$40-$C$30) -> -0.11111111
A40: Exit equity to investors | B40: €m | C40: =LBO_Base!C133 -> 816.16924
A42: 3. Bid ladder – returns by entry price (each case at its own exit multiple)
A43: Price point (€m) | B43: Entry EV | C43: x UW EBITDA | D43: x vendor EBITDA | E43: Equity in | F43: Base IRR | G43: Base MOIC | H43: Mgmt IRR | I43: Mgmt MOIC | J43: Down IRR | K43: Down MOIC
B44: 500 | C44: =B44/Inputs!$C$8 -> 12.5 | D44: =B44/Inputs!$C$7 -> 11.494253 | E44: =B44*(1+Inputs!$C$16)+Transaction!$C$7+Inputs!$C$17-Inputs!$C$29 -> 287.4 | F44: =G44^(1/LBO_Base!$H$6)-1 -> 0.23090178 | G44: =(LBO_Base!$C$102-Inputs!$C$20*MAX(0,LBO_Base!$C$102-E44))/E44 -> 2.8256411 | H44: =I44^(1/LBO_Base!$H$6)-1 -> 0.27208385 | I44: =(LBO_Mgmt!$C$102-Inputs!$C$20*MAX(0,LBO_Mgmt!$C$102-E44))/E44 -> 3.3310312 | J44: =K44^(1/LBO_Base!$H$6)-1 -> 0.058904389 | K44: =(LBO_Down!$C$102-Inputs!$C$20*MAX(0,LBO_Down!$C$102-E44))/E44 -> 1.3313239
B45: 520 | C45: =B45/Inputs!$C$8 -> 13 | D45: =B45/Inputs!$C$7 -> 11.954023 | E45: =B45*(1+Inputs!$C$16)+Transaction!$C$7+Inputs!$C$17-Inputs!$C$29 -> 307.8 | F45: =G45^(1/LBO_Base!$H$6)-1 -> 0.21474452 | G45: =(LBO_Base!$C$102-Inputs!$C$20*MAX(0,LBO_Base!$C$102-E45))/E45 -> 2.6449943 | H45: =I45^(1/LBO_Base!$H$6)-1 -> 0.25529055 | I45: =(LBO_Mgmt!$C$102-Inputs!$C$20*MAX(0,LBO_Mgmt!$C$102-E45))/E45 -> 3.1168888 | J45: =K45^(1/LBO_Base!$H$6)-1 -> 0.045591988 | K45: =(LBO_Down!$C$102-Inputs!$C$20*MAX(0,LBO_Down!$C$102-E45))/E45 -> 1.2497157
A46: Recommended upfront price | B46: 540 | C46: =B46/Inputs!$C$8 -> 13.5 | D46: =B46/Inputs!$C$7 -> 12.413793 | E46: =B46*(1+Inputs!$C$16)+Transaction!$C$7+Inputs!$C$17-Inputs!$C$29 -> 328.2 | F46: =G46^(1/LBO_Base!$H$6)-1 -> 0.19985379 | G46: =(LBO_Base!$C$102-Inputs!$C$20*MAX(0,LBO_Base!$C$102-E46))/E46 -> 2.4868045 | H46: =I46^(1/LBO_Base!$H$6)-1 -> 0.23980895 | I46: =(LBO_Mgmt!$C$102-Inputs!$C$20*MAX(0,LBO_Mgmt!$C$102-E46))/E46 -> 2.9293673 | J46: =K46^(1/LBO_Base!$H$6)-1 -> 0.033350564 | K46: =(LBO_Down!$C$102-Inputs!$C$20*MAX(0,LBO_Down!$C$102-E46))/E46 -> 1.1782526
A47: Walk-away upfront price | B47: 560 | C47: =B47/Inputs!$C$8 -> 14 | D47: =B47/Inputs!$C$7 -> 12.873563 | E47: =B47*(1+Inputs!$C$16)+Transaction!$C$7+Inputs!$C$17-Inputs!$C$29 -> 348.6 | F47: =G47^(1/LBO_Base!$H$6)-1 -> 0.18606202 | G47: =(LBO_Base!$C$102-Inputs!$C$20*MAX(0,LBO_Base!$C$102-E47))/E47 -> 2.3471292 | H47: =I47^(1/LBO_Base!$H$6)-1 -> 0.22546557 | I47: =(LBO_Mgmt!$C$102-Inputs!$C$20*MAX(0,LBO_Mgmt!$C$102-E47))/E47 -> 2.7637934 | J47: =K47^(1/LBO_Base!$H$6)-1 -> 0.022037729 | K47: =(LBO_Down!$C$102-Inputs!$C$20*MAX(0,LBO_Down!$C$102-E47))/E47 -> 1.1151535
A48: Headline incl. earn-out, if paid upfront | B48: 580 | C48: =B48/Inputs!$C$8 -> 14.5 | D48: =B48/Inputs!$C$7 -> 13.333333 | E48: =B48*(1+Inputs!$C$16)+Transaction!$C$7+Inputs!$C$17-Inputs!$C$29 -> 369 | F48: =G48^(1/LBO_Base!$H$6)-1 -> 0.17323198 | G48: =(LBO_Base!$C$102-Inputs!$C$20*MAX(0,LBO_Base!$C$102-E48))/E48 -> 2.2228977 | H48: =I48^(1/LBO_Base!$H$6)-1 -> 0.21211838 | I48: =(LBO_Mgmt!$C$102-Inputs!$C$20*MAX(0,LBO_Mgmt!$C$102-E48))/E48 -> 2.6165267 | J48: =K48^(1/LBO_Base!$H$6)-1 -> 0.011536942 | K48: =(LBO_Down!$C$102-Inputs!$C$20*MAX(0,LBO_Down!$C$102-E48))/E48 -> 1.0590312
A49: Vendor expectation | B49: 600 | C49: =B49/Inputs!$C$8 -> 15 | D49: =B49/Inputs!$C$7 -> 13.793103 | E49: =B49*(1+Inputs!$C$16)+Transaction!$C$7+Inputs!$C$17-Inputs!$C$29 -> 389.4 | F49: =G49^(1/LBO_Base!$H$6)-1 -> 0.16125001 | G49: =(LBO_Base!$C$102-Inputs!$C$20*MAX(0,LBO_Base!$C$102-E49))/E49 -> 2.1116827 | H49: =I49^(1/LBO_Base!$H$6)-1 -> 0.1996497 | I49: =(LBO_Mgmt!$C$102-Inputs!$C$20*MAX(0,LBO_Mgmt!$C$102-E49))/E49 -> 2.4846902 | J49: =K49^(1/LBO_Base!$H$6)-1 -> 0.0017516851 | K49: =(LBO_Down!$C$102-Inputs!$C$20*MAX(0,LBO_Down!$C$102-E49))/E49 -> 1.0087892
B50: 620 | C50: =B50/Inputs!$C$8 -> 15.5 | D50: =B50/Inputs!$C$7 -> 14.252874 | E50: =B50*(1+Inputs!$C$16)+Transaction!$C$7+Inputs!$C$17-Inputs!$C$29 -> 409.8 | F50: =G50^(1/LBO_Base!$H$6)-1 -> 0.15002094 | G50: =(LBO_Base!$C$102-Inputs!$C$20*MAX(0,LBO_Base!$C$102-E50))/E50 -> 2.0115404 | H50: =I50^(1/LBO_Base!$H$6)-1 -> 0.18796102 | I50: =(LBO_Mgmt!$C$102-Inputs!$C$20*MAX(0,LBO_Mgmt!$C$102-E50))/E50 -> 2.3659794 | J50: =K50^(1/LBO_Base!$H$6)-1 -> -0.0082346644 | K50: =(LBO_Down!$C$102-Inputs!$C$20*MAX(0,LBO_Down!$C$102-E50))/E50 -> 0.95949921
A51: Check: ladder formula at the model entry EV equals model IRR (should be 0) | F51: =((LBO_Base!$C$102-Inputs!$C$20*MAX(0,LBO_Base!$C$102-(Inputs!$C$10*(1+Inputs!$C$16)+Transaction!$C$7+Inputs!$C$17-Inputs!$C$29)))/(Inputs!$C$10*(1+Inputs!$C$16)+Transaction!$C$7+Inputs!$C$17-Inputs!$C$29))^(1/LBO_Base!$H$6)-1-LBO_Base!$C$109 -> 0
A52: Each case’s exit equity and net debt do not depend on the entry price (debt is sized on EBITDA), so the ladder is exact. Management case figures include the earn-out (Inputs C21).
A54: 4. Base case IRR – entry multiple (rows) × exit multiple (columns)
A55: Entry EV / underwritten EBITDA | B55: Entry EV | C55: 12 | D55: 12.5 | E55: 13 | F55: 13.5 | G55: 14 | H55: 14.5 | I55: 15
A56: 12.5 | B56: =A56*Inputs!$C$8 -> 500 | C56: =(((LBO_Base!$C$97*C$55*(1-Inputs!$C$70)-LBO_Base!$H$90)-Inputs!$C$20*MAX(0,(LBO_Base!$C$97*C$55*(1-Inputs!$C$70)-LBO_Base!$H$90)-($A56*Inputs!$C$8*(1+Inputs!$C$16)+Transaction!$C$7+Inputs!$C$17-Inputs!$C$29)))/($A56*Inputs!$C$8*(1+Inputs!$C$16)+Transaction!$C$7+Inputs!$C$17-Inputs!$C$29))^(1/LBO_Base!$H$6)-1 -> 0.1955698 | D56: =(((LBO_Base!$C$97*D$55*(1-Inputs!$C$70)-LBO_Base!$H$90)-Inputs!$C$20*MAX(0,(LBO_Base!$C$97*D$55*(1-Inputs!$C$70)-LBO_Base!$H$90)-($A56*Inputs!$C$8*(1+Inputs!$C$16)+Transaction!$C$7+Inputs!$C$17-Inputs!$C$29)))/($A56*Inputs!$C$8*(1+Inputs!$C$16)+Transaction!$C$7+Inputs!$C$17-Inputs!$C$29))^(1/LBO_Base!$H$6)-1 -> 0.20781086 | E56: =(((LBO_Base!$C$97*E$55*(1-Inputs!$C$70)-LBO_Base!$H$90)-Inputs!$C$20*MAX(0,(LBO_Base!$C$97*E$55*(1-Inputs!$C$70)-LBO_Base!$H$90)-($A56*Inputs!$C$8*(1+Inputs!$C$16)+Transaction!$C$7+Inputs!$C$17-Inputs!$C$29)))/($A56*Inputs!$C$8*(1+Inputs!$C$16)+Transaction!$C$7+Inputs!$C$17-Inputs!$C$29))^(1/LBO_Base!$H$6)-1 -> 0.21957488 | F56: =(((LBO_Base!$C$97*F$55*(1-Inputs!$C$70)-LBO_Base!$H$90)-Inputs!$C$20*MAX(0,(LBO_Base!$C$97*F$55*(1-Inputs!$C$70)-LBO_Base!$H$90)-($A56*Inputs!$C$8*(1+Inputs!$C$16)+Transaction!$C$7+Inputs!$C$17-Inputs!$C$29)))/($A56*Inputs!$C$8*(1+Inputs!$C$16)+Transaction!$C$7+Inputs!$C$17-Inputs!$C$29))^(1/LBO_Base!$H$6)-1 -> 0.23090178 | G56: =(((LBO_Base!$C$97*G$55*(1-Inputs!$C$70)-LBO_Base!$H$90)-Inputs!$C$20*MAX(0,(LBO_Base!$C$97*G$55*(1-Inputs!$C$70)-LBO_Base!$H$90)-($A56*Inputs!$C$8*(1+Inputs!$C$16)+Transaction!$C$7+Inputs!$C$17-Inputs!$C$29)))/($A56*Inputs!$C$8*(1+Inputs!$C$16)+Transaction!$C$7+Inputs!$C$17-Inputs!$C$29))^(1/LBO_Base!$H$6)-1 -> 0.24182647 | H56: =(((LBO_Base!$C$97*H$55*(1-Inputs!$C$70)-LBO_Base!$H$90)-Inputs!$C$20*MAX(0,(LBO_Base!$C$97*H$55*(1-Inputs!$C$70)-LBO_Base!$H$90)-($A56*Inputs!$C$8*(1+Inputs!$C$16)+Transaction!$C$7+Inputs!$C$17-Inputs!$C$29)))/($A56*Inputs!$C$8*(1+Inputs!$C$16)+Transaction!$C$7+Inputs!$C$17-Inputs!$C$29))^(1/LBO_Base!$H$6)-1 -> 0.25237972 | I56: =(((LBO_Base!$C$97*I$55*(1-Inputs!$C$70)-LBO_Base!$H$90)-Inputs!$C$20*MAX(0,(LBO_Base!$C$97*I$55*(1-Inputs!$C$70)-LBO_Base!$H$90)-($A56*Inputs!$C$8*(1+Inputs!$C$16)+Transaction!$C$7+Inputs!$C$17-Inputs!$C$29)))/($A56*Inputs!$C$8*(1+Inputs!$C$16)+Transaction!$C$7+Inputs!$C$17-Inputs!$C$29))^(1/LBO_Base!$H$6)-1 -> 0.26258882
A57: 13 | B57: =A57*Inputs!$C$8 -> 520 | C57: =(((LBO_Base!$C$97*C$55*(1-Inputs!$C$70)-LBO_Base!$H$90)-Inputs!$C$20*MAX(0,(LBO_Base!$C$97*C$55*(1-Inputs!$C$70)-LBO_Base!$H$90)-($A57*Inputs!$C$8*(1+Inputs!$C$16)+Transaction!$C$7+Inputs!$C$17-Inputs!$C$29)))/($A57*Inputs!$C$8*(1+Inputs!$C$16)+Transaction!$C$7+Inputs!$C$17-Inputs!$C$29))^(1/LBO_Base!$H$6)-1 -> 0.179969 | D57: =(((LBO_Base!$C$97*D$55*(1-Inputs!$C$70)-LBO_Base!$H$90)-Inputs!$C$20*MAX(0,(LBO_Base!$C$97*D$55*(1-Inputs!$C$70)-LBO_Base!$H$90)-($A57*Inputs!$C$8*(1+Inputs!$C$16)+Transaction!$C$7+Inputs!$C$17-Inputs!$C$29)))/($A57*Inputs!$C$8*(1+Inputs!$C$16)+Transaction!$C$7+Inputs!$C$17-Inputs!$C$29))^(1/LBO_Base!$H$6)-1 -> 0.19201602 | E57: =(((LBO_Base!$C$97*E$55*(1-Inputs!$C$70)-LBO_Base!$H$90)-Inputs!$C$20*MAX(0,(LBO_Base!$C$97*E$55*(1-Inputs!$C$70)-LBO_Base!$H$90)-($A57*Inputs!$C$8*(1+Inputs!$C$16)+Transaction!$C$7+Inputs!$C$17-Inputs!$C$29)))/($A57*Inputs!$C$8*(1+Inputs!$C$16)+Transaction!$C$7+Inputs!$C$17-Inputs!$C$29))^(1/LBO_Base!$H$6)-1 -> 0.20359484 | F57: =(((LBO_Base!$C$97*F$55*(1-Inputs!$C$70)-LBO_Base!$H$90)-Inputs!$C$20*MAX(0,(LBO_Base!$C$97*F$55*(1-Inputs!$C$70)-LBO_Base!$H$90)-($A57*Inputs!$C$8*(1+Inputs!$C$16)+Transaction!$C$7+Inputs!$C$17-Inputs!$C$29)))/($A57*Inputs!$C$8*(1+Inputs!$C$16)+Transaction!$C$7+Inputs!$C$17-Inputs!$C$29))^(1/LBO_Base!$H$6)-1 -> 0.21474452 | G57: =(((LBO_Base!$C$97*G$55*(1-Inputs!$C$70)-LBO_Base!$H$90)-Inputs!$C$20*MAX(0,(LBO_Base!$C$97*G$55*(1-Inputs!$C$70)-LBO_Base!$H$90)-($A57*Inputs!$C$8*(1+Inputs!$C$16)+Transaction!$C$7+Inputs!$C$17-Inputs!$C$29)))/($A57*Inputs!$C$8*(1+Inputs!$C$16)+Transaction!$C$7+Inputs!$C$17-Inputs!$C$29))^(1/LBO_Base!$H$6)-1 -> 0.22549926 | H57: =(((LBO_Base!$C$97*H$55*(1-Inputs!$C$70)-LBO_Base!$H$90)-Inputs!$C$20*MAX(0,(LBO_Base!$C$97*H$55*(1-Inputs!$C$70)-LBO_Base!$H$90)-($A57*Inputs!$C$8*(1+Inputs!$C$16)+Transaction!$C$7+Inputs!$C$17-Inputs!$C$29)))/($A57*Inputs!$C$8*(1+Inputs!$C$16)+Transaction!$C$7+Inputs!$C$17-Inputs!$C$29))^(1/LBO_Base!$H$6)-1 -> 0.23588921 | I57: =(((LBO_Base!$C$97*I$55*(1-Inputs!$C$70)-LBO_Base!$H$90)-Inputs!$C$20*MAX(0,(LBO_Base!$C$97*I$55*(1-Inputs!$C$70)-LBO_Base!$H$90)-($A57*Inputs!$C$8*(1+Inputs!$C$16)+Transaction!$C$7+Inputs!$C$17-Inputs!$C$29)))/($A57*Inputs!$C$8*(1+Inputs!$C$16)+Transaction!$C$7+Inputs!$C$17-Inputs!$C$29))^(1/LBO_Base!$H$6)-1 -> 0.24594109
A58: 13.5 | B58: =A58*Inputs!$C$8 -> 540 | C58: =(((LBO_Base!$C$97*C$55*(1-Inputs!$C$70)-LBO_Base!$H$90)-Inputs!$C$20*MAX(0,(LBO_Base!$C$97*C$55*(1-Inputs!$C$70)-LBO_Base!$H$90)-($A58*Inputs!$C$8*(1+Inputs!$C$16)+Transaction!$C$7+Inputs!$C$17-Inputs!$C$29)))/($A58*Inputs!$C$8*(1+Inputs!$C$16)+Transaction!$C$7+Inputs!$C$17-Inputs!$C$29))^(1/LBO_Base!$H$6)-1 -> 0.16559562 | D58: =(((LBO_Base!$C$97*D$55*(1-Inputs!$C$70)-LBO_Base!$H$90)-Inputs!$C$20*MAX(0,(LBO_Base!$C$97*D$55*(1-Inputs!$C$70)-LBO_Base!$H$90)-($A58*Inputs!$C$8*(1+Inputs!$C$16)+Transaction!$C$7+Inputs!$C$17-Inputs!$C$29)))/($A58*Inputs!$C$8*(1+Inputs!$C$16)+Transaction!$C$7+Inputs!$C$17-Inputs!$C$29))^(1/LBO_Base!$H$6)-1 -> 0.1774622 | E58: =(((LBO_Base!$C$97*E$55*(1-Inputs!$C$70)-LBO_Base!$H$90)-Inputs!$C$20*MAX(0,(LBO_Base!$C$97*E$55*(1-Inputs!$C$70)-LBO_Base!$H$90)-($A58*Inputs!$C$8*(1+Inputs!$C$16)+Transaction!$C$7+Inputs!$C$17-Inputs!$C$29)))/($A58*Inputs!$C$8*(1+Inputs!$C$16)+Transaction!$C$7+Inputs!$C$17-Inputs!$C$29))^(1/LBO_Base!$H$6)-1 -> 0.18886883 | F58: =(((LBO_Base!$C$97*F$55*(1-Inputs!$C$70)-LBO_Base!$H$90)-Inputs!$C$20*MAX(0,(LBO_Base!$C$97*F$55*(1-Inputs!$C$70)-LBO_Base!$H$90)-($A58*Inputs!$C$8*(1+Inputs!$C$16)+Transaction!$C$7+Inputs!$C$17-Inputs!$C$29)))/($A58*Inputs!$C$8*(1+Inputs!$C$16)+Transaction!$C$7+Inputs!$C$17-Inputs!$C$29))^(1/LBO_Base!$H$6)-1 -> 0.19985379 | G58: =(((LBO_Base!$C$97*G$55*(1-Inputs!$C$70)-LBO_Base!$H$90)-Inputs!$C$20*MAX(0,(LBO_Base!$C$97*G$55*(1-Inputs!$C$70)-LBO_Base!$H$90)-($A58*Inputs!$C$8*(1+Inputs!$C$16)+Transaction!$C$7+Inputs!$C$17-Inputs!$C$29)))/($A58*Inputs!$C$8*(1+Inputs!$C$16)+Transaction!$C$7+Inputs!$C$17-Inputs!$C$29))^(1/LBO_Base!$H$6)-1 -> 0.21045061 | H58: =(((LBO_Base!$C$97*H$55*(1-Inputs!$C$70)-LBO_Base!$H$90)-Inputs!$C$20*MAX(0,(LBO_Base!$C$97*H$55*(1-Inputs!$C$70)-LBO_Base!$H$90)-($A58*Inputs!$C$8*(1+Inputs!$C$16)+Transaction!$C$7+Inputs!$C$17-Inputs!$C$29)))/($A58*Inputs!$C$8*(1+Inputs!$C$16)+Transaction!$C$7+Inputs!$C$17-Inputs!$C$29))^(1/LBO_Base!$H$6)-1 -> 0.22068884 | I58: =(((LBO_Base!$C$97*I$55*(1-Inputs!$C$70)-LBO_Base!$H$90)-Inputs!$C$20*MAX(0,(LBO_Base!$C$97*I$55*(1-Inputs!$C$70)-LBO_Base!$H$90)-($A58*Inputs!$C$8*(1+Inputs!$C$16)+Transaction!$C$7+Inputs!$C$17-Inputs!$C$29)))/($A58*Inputs!$C$8*(1+Inputs!$C$16)+Transaction!$C$7+Inputs!$C$17-Inputs!$C$29))^(1/LBO_Base!$H$6)-1 -> 0.23059468
A59: 14 | B59: =A59*Inputs!$C$8 -> 560 | C59: =(((LBO_Base!$C$97*C$55*(1-Inputs!$C$70)-LBO_Base!$H$90)-Inputs!$C$20*MAX(0,(LBO_Base!$C$97*C$55*(1-Inputs!$C$70)-LBO_Base!$H$90)-($A59*Inputs!$C$8*(1+Inputs!$C$16)+Transaction!$C$7+Inputs!$C$17-Inputs!$C$29)))/($A59*Inputs!$C$8*(1+Inputs!$C$16)+Transaction!$C$7+Inputs!$C$17-Inputs!$C$29))^(1/LBO_Base!$H$6)-1 -> 0.15228716 | D59: =(((LBO_Base!$C$97*D$55*(1-Inputs!$C$70)-LBO_Base!$H$90)-Inputs!$C$20*MAX(0,(LBO_Base!$C$97*D$55*(1-Inputs!$C$70)-LBO_Base!$H$90)-($A59*Inputs!$C$8*(1+Inputs!$C$16)+Transaction!$C$7+Inputs!$C$17-Inputs!$C$29)))/($A59*Inputs!$C$8*(1+Inputs!$C$16)+Transaction!$C$7+Inputs!$C$17-Inputs!$C$29))^(1/LBO_Base!$H$6)-1 -> 0.16398512 | E59: =(((LBO_Base!$C$97*E$55*(1-Inputs!$C$70)-LBO_Base!$H$90)-Inputs!$C$20*MAX(0,(LBO_Base!$C$97*E$55*(1-Inputs!$C$70)-LBO_Base!$H$90)-($A59*Inputs!$C$8*(1+Inputs!$C$16)+Transaction!$C$7+Inputs!$C$17-Inputs!$C$29)))/($A59*Inputs!$C$8*(1+Inputs!$C$16)+Transaction!$C$7+Inputs!$C$17-Inputs!$C$29))^(1/LBO_Base!$H$6)-1 -> 0.1752309 | F59: =(((LBO_Base!$C$97*F$55*(1-Inputs!$C$70)-LBO_Base!$H$90)-Inputs!$C$20*MAX(0,(LBO_Base!$C$97*F$55*(1-Inputs!$C$70)-LBO_Base!$H$90)-($A59*Inputs!$C$8*(1+Inputs!$C$16)+Transaction!$C$7+Inputs!$C$17-Inputs!$C$29)))/($A59*Inputs!$C$8*(1+Inputs!$C$16)+Transaction!$C$7+Inputs!$C$17-Inputs!$C$29))^(1/LBO_Base!$H$6)-1 -> 0.18606202 | G59: =(((LBO_Base!$C$97*G$55*(1-Inputs!$C$70)-LBO_Base!$H$90)-Inputs!$C$20*MAX(0,(LBO_Base!$C$97*G$55*(1-Inputs!$C$70)-LBO_Base!$H$90)-($A59*Inputs!$C$8*(1+Inputs!$C$16)+Transaction!$C$7+Inputs!$C$17-Inputs!$C$29)))/($A59*Inputs!$C$8*(1+Inputs!$C$16)+Transaction!$C$7+Inputs!$C$17-Inputs!$C$29))^(1/LBO_Base!$H$6)-1 -> 0.19651137 | H59: =(((LBO_Base!$C$97*H$55*(1-Inputs!$C$70)-LBO_Base!$H$90)-Inputs!$C$20*MAX(0,(LBO_Base!$C$97*H$55*(1-Inputs!$C$70)-LBO_Base!$H$90)-($A59*Inputs!$C$8*(1+Inputs!$C$16)+Transaction!$C$7+Inputs!$C$17-Inputs!$C$29)))/($A59*Inputs!$C$8*(1+Inputs!$C$16)+Transaction!$C$7+Inputs!$C$17-Inputs!$C$29))^(1/LBO_Base!$H$6)-1 -> 0.20660795 | I59: =(((LBO_Base!$C$97*I$55*(1-Inputs!$C$70)-LBO_Base!$H$90)-Inputs!$C$20*MAX(0,(LBO_Base!$C$97*I$55*(1-Inputs!$C$70)-LBO_Base!$H$90)-($A59*Inputs!$C$8*(1+Inputs!$C$16)+Transaction!$C$7+Inputs!$C$17-Inputs!$C$29)))/($A59*Inputs!$C$8*(1+Inputs!$C$16)+Transaction!$C$7+Inputs!$C$17-Inputs!$C$29))^(1/LBO_Base!$H$6)-1 -> 0.21637748
A60: 14.5 | B60: =A60*Inputs!$C$8 -> 580 | C60: =(((LBO_Base!$C$97*C$55*(1-Inputs!$C$70)-LBO_Base!$H$90)-Inputs!$C$20*MAX(0,(LBO_Base!$C$97*C$55*(1-Inputs!$C$70)-LBO_Base!$H$90)-($A60*Inputs!$C$8*(1+Inputs!$C$16)+Transaction!$C$7+Inputs!$C$17-Inputs!$C$29)))/($A60*Inputs!$C$8*(1+Inputs!$C$16)+Transaction!$C$7+Inputs!$C$17-Inputs!$C$29))^(1/LBO_Base!$H$6)-1 -> 0.13991057 | D60: =(((LBO_Base!$C$97*D$55*(1-Inputs!$C$70)-LBO_Base!$H$90)-Inputs!$C$20*MAX(0,(LBO_Base!$C$97*D$55*(1-Inputs!$C$70)-LBO_Base!$H$90)-($A60*Inputs!$C$8*(1+Inputs!$C$16)+Transaction!$C$7+Inputs!$C$17-Inputs!$C$29)))/($A60*Inputs!$C$8*(1+Inputs!$C$16)+Transaction!$C$7+Inputs!$C$17-Inputs!$C$29))^(1/LBO_Base!$H$6)-1 -> 0.15145031 | E60: =(((LBO_Base!$C$97*E$55*(1-Inputs!$C$70)-LBO_Base!$H$90)-Inputs!$C$20*MAX(0,(LBO_Base!$C$97*E$55*(1-Inputs!$C$70)-LBO_Base!$H$90)-($A60*Inputs!$C$8*(1+Inputs!$C$16)+Transaction!$C$7+Inputs!$C$17-Inputs!$C$29)))/($A60*Inputs!$C$8*(1+Inputs!$C$16)+Transaction!$C$7+Inputs!$C$17-Inputs!$C$29))^(1/LBO_Base!$H$6)-1 -> 0.16254517 | F60: =(((LBO_Base!$C$97*F$55*(1-Inputs!$C$70)-LBO_Base!$H$90)-Inputs!$C$20*MAX(0,(LBO_Base!$C$97*F$55*(1-Inputs!$C$70)-LBO_Base!$H$90)-($A60*Inputs!$C$8*(1+Inputs!$C$16)+Transaction!$C$7+Inputs!$C$17-Inputs!$C$29)))/($A60*Inputs!$C$8*(1+Inputs!$C$16)+Transaction!$C$7+Inputs!$C$17-Inputs!$C$29))^(1/LBO_Base!$H$6)-1 -> 0.17323198 | G60: =(((LBO_Base!$C$97*G$55*(1-Inputs!$C$70)-LBO_Base!$H$90)-Inputs!$C$20*MAX(0,(LBO_Base!$C$97*G$55*(1-Inputs!$C$70)-LBO_Base!$H$90)-($A60*Inputs!$C$8*(1+Inputs!$C$16)+Transaction!$C$7+Inputs!$C$17-Inputs!$C$29)))/($A60*Inputs!$C$8*(1+Inputs!$C$16)+Transaction!$C$7+Inputs!$C$17-Inputs!$C$29))^(1/LBO_Base!$H$6)-1 -> 0.18354303 | H60: =(((LBO_Base!$C$97*H$55*(1-Inputs!$C$70)-LBO_Base!$H$90)-Inputs!$C$20*MAX(0,(LBO_Base!$C$97*H$55*(1-Inputs!$C$70)-LBO_Base!$H$90)-($A60*Inputs!$C$8*(1+Inputs!$C$16)+Transaction!$C$7+Inputs!$C$17-Inputs!$C$29)))/($A60*Inputs!$C$8*(1+Inputs!$C$16)+Transaction!$C$7+Inputs!$C$17-Inputs!$C$29))^(1/LBO_Base!$H$6)-1 -> 0.1935068 | I60: =(((LBO_Base!$C$97*I$55*(1-Inputs!$C$70)-LBO_Base!$H$90)-Inputs!$C$20*MAX(0,(LBO_Base!$C$97*I$55*(1-Inputs!$C$70)-LBO_Base!$H$90)-($A60*Inputs!$C$8*(1+Inputs!$C$16)+Transaction!$C$7+Inputs!$C$17-Inputs!$C$29)))/($A60*Inputs!$C$8*(1+Inputs!$C$16)+Transaction!$C$7+Inputs!$C$17-Inputs!$C$29))^(1/LBO_Base!$H$6)-1 -> 0.20314854
A61: 15 | B61: =A61*Inputs!$C$8 -> 600 | C61: =(((LBO_Base!$C$97*C$55*(1-Inputs!$C$70)-LBO_Base!$H$90)-Inputs!$C$20*MAX(0,(LBO_Base!$C$97*C$55*(1-Inputs!$C$70)-LBO_Base!$H$90)-($A61*Inputs!$C$8*(1+Inputs!$C$16)+Transaction!$C$7+Inputs!$C$17-Inputs!$C$29)))/($A61*Inputs!$C$8*(1+Inputs!$C$16)+Transaction!$C$7+Inputs!$C$17-Inputs!$C$29))^(1/LBO_Base!$H$6)-1 -> 0.12835564 | D61: =(((LBO_Base!$C$97*D$55*(1-Inputs!$C$70)-LBO_Base!$H$90)-Inputs!$C$20*MAX(0,(LBO_Base!$C$97*D$55*(1-Inputs!$C$70)-LBO_Base!$H$90)-($A61*Inputs!$C$8*(1+Inputs!$C$16)+Transaction!$C$7+Inputs!$C$17-Inputs!$C$29)))/($A61*Inputs!$C$8*(1+Inputs!$C$16)+Transaction!$C$7+Inputs!$C$17-Inputs!$C$29))^(1/LBO_Base!$H$6)-1 -> 0.13974633 | E61: =(((LBO_Base!$C$97*E$55*(1-Inputs!$C$70)-LBO_Base!$H$90)-Inputs!$C$20*MAX(0,(LBO_Base!$C$97*E$55*(1-Inputs!$C$70)-LBO_Base!$H$90)-($A61*Inputs!$C$8*(1+Inputs!$C$16)+Transaction!$C$7+Inputs!$C$17-Inputs!$C$29)))/($A61*Inputs!$C$8*(1+Inputs!$C$16)+Transaction!$C$7+Inputs!$C$17-Inputs!$C$29))^(1/LBO_Base!$H$6)-1 -> 0.15069907 | F61: =(((LBO_Base!$C$97*F$55*(1-Inputs!$C$70)-LBO_Base!$H$90)-Inputs!$C$20*MAX(0,(LBO_Base!$C$97*F$55*(1-Inputs!$C$70)-LBO_Base!$H$90)-($A61*Inputs!$C$8*(1+Inputs!$C$16)+Transaction!$C$7+Inputs!$C$17-Inputs!$C$29)))/($A61*Inputs!$C$8*(1+Inputs!$C$16)+Transaction!$C$7+Inputs!$C$17-Inputs!$C$29))^(1/LBO_Base!$H$6)-1 -> 0.16125001 | G61: =(((LBO_Base!$C$97*G$55*(1-Inputs!$C$70)-LBO_Base!$H$90)-Inputs!$C$20*MAX(0,(LBO_Base!$C$97*G$55*(1-Inputs!$C$70)-LBO_Base!$H$90)-($A61*Inputs!$C$8*(1+Inputs!$C$16)+Transaction!$C$7+Inputs!$C$17-Inputs!$C$29)))/($A61*Inputs!$C$8*(1+Inputs!$C$16)+Transaction!$C$7+Inputs!$C$17-Inputs!$C$29))^(1/LBO_Base!$H$6)-1 -> 0.17143087 | H61: =(((LBO_Base!$C$97*H$55*(1-Inputs!$C$70)-LBO_Base!$H$90)-Inputs!$C$20*MAX(0,(LBO_Base!$C$97*H$55*(1-Inputs!$C$70)-LBO_Base!$H$90)-($A61*Inputs!$C$8*(1+Inputs!$C$16)+Transaction!$C$7+Inputs!$C$17-Inputs!$C$29)))/($A61*Inputs!$C$8*(1+Inputs!$C$16)+Transaction!$C$7+Inputs!$C$17-Inputs!$C$29))^(1/LBO_Base!$H$6)-1 -> 0.18126964 | I61: =(((LBO_Base!$C$97*I$55*(1-Inputs!$C$70)-LBO_Base!$H$90)-Inputs!$C$20*MAX(0,(LBO_Base!$C$97*I$55*(1-Inputs!$C$70)-LBO_Base!$H$90)-($A61*Inputs!$C$8*(1+Inputs!$C$16)+Transaction!$C$7+Inputs!$C$17-Inputs!$C$29)))/($A61*Inputs!$C$8*(1+Inputs!$C$16)+Transaction!$C$7+Inputs!$C$17-Inputs!$C$29))^(1/LBO_Base!$H$6)-1 -> 0.19079114
A63: 5. Base case MOIC – entry multiple (rows) × exit multiple (columns)
A64: Entry EV / underwritten EBITDA | B64: Entry EV | C64: 12 | D64: 12.5 | E64: 13 | F64: 13.5 | G64: 14 | H64: 14.5 | I64: 15
A65: 12.5 | B65: =A65*Inputs!$C$8 -> 500 | C65: =((LBO_Base!$C$97*C$64*(1-Inputs!$C$70)-LBO_Base!$H$90)-Inputs!$C$20*MAX(0,(LBO_Base!$C$97*C$64*(1-Inputs!$C$70)-LBO_Base!$H$90)-($A65*Inputs!$C$8*(1+Inputs!$C$16)+Transaction!$C$7+Inputs!$C$17-Inputs!$C$29)))/($A65*Inputs!$C$8*(1+Inputs!$C$16)+Transaction!$C$7+Inputs!$C$17-Inputs!$C$29) -> 2.4427256 | D65: =((LBO_Base!$C$97*D$64*(1-Inputs!$C$70)-LBO_Base!$H$90)-Inputs!$C$20*MAX(0,(LBO_Base!$C$97*D$64*(1-Inputs!$C$70)-LBO_Base!$H$90)-($A65*Inputs!$C$8*(1+Inputs!$C$16)+Transaction!$C$7+Inputs!$C$17-Inputs!$C$29)))/($A65*Inputs!$C$8*(1+Inputs!$C$16)+Transaction!$C$7+Inputs!$C$17-Inputs!$C$29) -> 2.5703641 | E65: =((LBO_Base!$C$97*E$64*(1-Inputs!$C$70)-LBO_Base!$H$90)-Inputs!$C$20*MAX(0,(LBO_Base!$C$97*E$64*(1-Inputs!$C$70)-LBO_Base!$H$90)-($A65*Inputs!$C$8*(1+Inputs!$C$16)+Transaction!$C$7+Inputs!$C$17-Inputs!$C$29)))/($A65*Inputs!$C$8*(1+Inputs!$C$16)+Transaction!$C$7+Inputs!$C$17-Inputs!$C$29) -> 2.6980026 | F65: =((LBO_Base!$C$97*F$64*(1-Inputs!$C$70)-LBO_Base!$H$90)-Inputs!$C$20*MAX(0,(LBO_Base!$C$97*F$64*(1-Inputs!$C$70)-LBO_Base!$H$90)-($A65*Inputs!$C$8*(1+Inputs!$C$16)+Transaction!$C$7+Inputs!$C$17-Inputs!$C$29)))/($A65*Inputs!$C$8*(1+Inputs!$C$16)+Transaction!$C$7+Inputs!$C$17-Inputs!$C$29) -> 2.8256411 | G65: =((LBO_Base!$C$97*G$64*(1-Inputs!$C$70)-LBO_Base!$H$90)-Inputs!$C$20*MAX(0,(LBO_Base!$C$97*G$64*(1-Inputs!$C$70)-LBO_Base!$H$90)-($A65*Inputs!$C$8*(1+Inputs!$C$16)+Transaction!$C$7+Inputs!$C$17-Inputs!$C$29)))/($A65*Inputs!$C$8*(1+Inputs!$C$16)+Transaction!$C$7+Inputs!$C$17-Inputs!$C$29) -> 2.9532795 | H65: =((LBO_Base!$C$97*H$64*(1-Inputs!$C$70)-LBO_Base!$H$90)-Inputs!$C$20*MAX(0,(LBO_Base!$C$97*H$64*(1-Inputs!$C$70)-LBO_Base!$H$90)-($A65*Inputs!$C$8*(1+Inputs!$C$16)+Transaction!$C$7+Inputs!$C$17-Inputs!$C$29)))/($A65*Inputs!$C$8*(1+Inputs!$C$16)+Transaction!$C$7+Inputs!$C$17-Inputs!$C$29) -> 3.080918 | I65: =((LBO_Base!$C$97*I$64*(1-Inputs!$C$70)-LBO_Base!$H$90)-Inputs!$C$20*MAX(0,(LBO_Base!$C$97*I$64*(1-Inputs!$C$70)-LBO_Base!$H$90)-($A65*Inputs!$C$8*(1+Inputs!$C$16)+Transaction!$C$7+Inputs!$C$17-Inputs!$C$29)))/($A65*Inputs!$C$8*(1+Inputs!$C$16)+Transaction!$C$7+Inputs!$C$17-Inputs!$C$29) -> 3.2085565
A66: 13 | B66: =A66*Inputs!$C$8 -> 520 | C66: =((LBO_Base!$C$97*C$64*(1-Inputs!$C$70)-LBO_Base!$H$90)-Inputs!$C$20*MAX(0,(LBO_Base!$C$97*C$64*(1-Inputs!$C$70)-LBO_Base!$H$90)-($A66*Inputs!$C$8*(1+Inputs!$C$16)+Transaction!$C$7+Inputs!$C$17-Inputs!$C$29)))/($A66*Inputs!$C$8*(1+Inputs!$C$16)+Transaction!$C$7+Inputs!$C$17-Inputs!$C$29) -> 2.2874573 | D66: =((LBO_Base!$C$97*D$64*(1-Inputs!$C$70)-LBO_Base!$H$90)-Inputs!$C$20*MAX(0,(LBO_Base!$C$97*D$64*(1-Inputs!$C$70)-LBO_Base!$H$90)-($A66*Inputs!$C$8*(1+Inputs!$C$16)+Transaction!$C$7+Inputs!$C$17-Inputs!$C$29)))/($A66*Inputs!$C$8*(1+Inputs!$C$16)+Transaction!$C$7+Inputs!$C$17-Inputs!$C$29) -> 2.4066363 | E66: =((LBO_Base!$C$97*E$64*(1-Inputs!$C$70)-LBO_Base!$H$90)-Inputs!$C$20*MAX(0,(LBO_Base!$C$97*E$64*(1-Inputs!$C$70)-LBO_Base!$H$90)-($A66*Inputs!$C$8*(1+Inputs!$C$16)+Transaction!$C$7+Inputs!$C$17-Inputs!$C$29)))/($A66*Inputs!$C$8*(1+Inputs!$C$16)+Transaction!$C$7+Inputs!$C$17-Inputs!$C$29) -> 2.5258153 | F66: =((LBO_Base!$C$97*F$64*(1-Inputs!$C$70)-LBO_Base!$H$90)-Inputs!$C$20*MAX(0,(LBO_Base!$C$97*F$64*(1-Inputs!$C$70)-LBO_Base!$H$90)-($A66*Inputs!$C$8*(1+Inputs!$C$16)+Transaction!$C$7+Inputs!$C$17-Inputs!$C$29)))/($A66*Inputs!$C$8*(1+Inputs!$C$16)+Transaction!$C$7+Inputs!$C$17-Inputs!$C$29) -> 2.6449943 | G66: =((LBO_Base!$C$97*G$64*(1-Inputs!$C$70)-LBO_Base!$H$90)-Inputs!$C$20*MAX(0,(LBO_Base!$C$97*G$64*(1-Inputs!$C$70)-LBO_Base!$H$90)-($A66*Inputs!$C$8*(1+Inputs!$C$16)+Transaction!$C$7+Inputs!$C$17-Inputs!$C$29)))/($A66*Inputs!$C$8*(1+Inputs!$C$16)+Transaction!$C$7+Inputs!$C$17-Inputs!$C$29) -> 2.7641733 | H66: =((LBO_Base!$C$97*H$64*(1-Inputs!$C$70)-LBO_Base!$H$90)-Inputs!$C$20*MAX(0,(LBO_Base!$C$97*H$64*(1-Inputs!$C$70)-LBO_Base!$H$90)-($A66*Inputs!$C$8*(1+Inputs!$C$16)+Transaction!$C$7+Inputs!$C$17-Inputs!$C$29)))/($A66*Inputs!$C$8*(1+Inputs!$C$16)+Transaction!$C$7+Inputs!$C$17-Inputs!$C$29) -> 2.8833523 | I66: =((LBO_Base!$C$97*I$64*(1-Inputs!$C$70)-LBO_Base!$H$90)-Inputs!$C$20*MAX(0,(LBO_Base!$C$97*I$64*(1-Inputs!$C$70)-LBO_Base!$H$90)-($A66*Inputs!$C$8*(1+Inputs!$C$16)+Transaction!$C$7+Inputs!$C$17-Inputs!$C$29)))/($A66*Inputs!$C$8*(1+Inputs!$C$16)+Transaction!$C$7+Inputs!$C$17-Inputs!$C$29) -> 3.0025313
A67: 13.5 | B67: =A67*Inputs!$C$8 -> 540 | C67: =((LBO_Base!$C$97*C$64*(1-Inputs!$C$70)-LBO_Base!$H$90)-Inputs!$C$20*MAX(0,(LBO_Base!$C$97*C$64*(1-Inputs!$C$70)-LBO_Base!$H$90)-($A67*Inputs!$C$8*(1+Inputs!$C$16)+Transaction!$C$7+Inputs!$C$17-Inputs!$C$29)))/($A67*Inputs!$C$8*(1+Inputs!$C$16)+Transaction!$C$7+Inputs!$C$17-Inputs!$C$29) -> 2.151491 | D67: =((LBO_Base!$C$97*D$64*(1-Inputs!$C$70)-LBO_Base!$H$90)-Inputs!$C$20*MAX(0,(LBO_Base!$C$97*D$64*(1-Inputs!$C$70)-LBO_Base!$H$90)-($A67*Inputs!$C$8*(1+Inputs!$C$16)+Transaction!$C$7+Inputs!$C$17-Inputs!$C$29)))/($A67*Inputs!$C$8*(1+Inputs!$C$16)+Transaction!$C$7+Inputs!$C$17-Inputs!$C$29) -> 2.2632622 | E67: =((LBO_Base!$C$97*E$64*(1-Inputs!$C$70)-LBO_Base!$H$90)-Inputs!$C$20*MAX(0,(LBO_Base!$C$97*E$64*(1-Inputs!$C$70)-LBO_Base!$H$90)-($A67*Inputs!$C$8*(1+Inputs!$C$16)+Transaction!$C$7+Inputs!$C$17-Inputs!$C$29)))/($A67*Inputs!$C$8*(1+Inputs!$C$16)+Transaction!$C$7+Inputs!$C$17-Inputs!$C$29) -> 2.3750333 | F67: =((LBO_Base!$C$97*F$64*(1-Inputs!$C$70)-LBO_Base!$H$90)-Inputs!$C$20*MAX(0,(LBO_Base!$C$97*F$64*(1-Inputs!$C$70)-LBO_Base!$H$90)-($A67*Inputs!$C$8*(1+Inputs!$C$16)+Transaction!$C$7+Inputs!$C$17-Inputs!$C$29)))/($A67*Inputs!$C$8*(1+Inputs!$C$16)+Transaction!$C$7+Inputs!$C$17-Inputs!$C$29) -> 2.4868045 | G67: =((LBO_Base!$C$97*G$64*(1-Inputs!$C$70)-LBO_Base!$H$90)-Inputs!$C$20*MAX(0,(LBO_Base!$C$97*G$64*(1-Inputs!$C$70)-LBO_Base!$H$90)-($A67*Inputs!$C$8*(1+Inputs!$C$16)+Transaction!$C$7+Inputs!$C$17-Inputs!$C$29)))/($A67*Inputs!$C$8*(1+Inputs!$C$16)+Transaction!$C$7+Inputs!$C$17-Inputs!$C$29) -> 2.5985757 | H67: =((LBO_Base!$C$97*H$64*(1-Inputs!$C$70)-LBO_Base!$H$90)-Inputs!$C$20*MAX(0,(LBO_Base!$C$97*H$64*(1-Inputs!$C$70)-LBO_Base!$H$90)-($A67*Inputs!$C$8*(1+Inputs!$C$16)+Transaction!$C$7+Inputs!$C$17-Inputs!$C$29)))/($A67*Inputs!$C$8*(1+Inputs!$C$16)+Transaction!$C$7+Inputs!$C$17-Inputs!$C$29) -> 2.7103468 | I67: =((LBO_Base!$C$97*I$64*(1-Inputs!$C$70)-LBO_Base!$H$90)-Inputs!$C$20*MAX(0,(LBO_Base!$C$97*I$64*(1-Inputs!$C$70)-LBO_Base!$H$90)-($A67*Inputs!$C$8*(1+Inputs!$C$16)+Transaction!$C$7+Inputs!$C$17-Inputs!$C$29)))/($A67*Inputs!$C$8*(1+Inputs!$C$16)+Transaction!$C$7+Inputs!$C$17-Inputs!$C$29) -> 2.822118
A68: 14 | B68: =A68*Inputs!$C$8 -> 560 | C68: =((LBO_Base!$C$97*C$64*(1-Inputs!$C$70)-LBO_Base!$H$90)-Inputs!$C$20*MAX(0,(LBO_Base!$C$97*C$64*(1-Inputs!$C$70)-LBO_Base!$H$90)-($A68*Inputs!$C$8*(1+Inputs!$C$16)+Transaction!$C$7+Inputs!$C$17-Inputs!$C$29)))/($A68*Inputs!$C$8*(1+Inputs!$C$16)+Transaction!$C$7+Inputs!$C$17-Inputs!$C$29) -> 2.0314382 | D68: =((LBO_Base!$C$97*D$64*(1-Inputs!$C$70)-LBO_Base!$H$90)-Inputs!$C$20*MAX(0,(LBO_Base!$C$97*D$64*(1-Inputs!$C$70)-LBO_Base!$H$90)-($A68*Inputs!$C$8*(1+Inputs!$C$16)+Transaction!$C$7+Inputs!$C$17-Inputs!$C$29)))/($A68*Inputs!$C$8*(1+Inputs!$C$16)+Transaction!$C$7+Inputs!$C$17-Inputs!$C$29) -> 2.1366685 | E68: =((LBO_Base!$C$97*E$64*(1-Inputs!$C$70)-LBO_Base!$H$90)-Inputs!$C$20*MAX(0,(LBO_Base!$C$97*E$64*(1-Inputs!$C$70)-LBO_Base!$H$90)-($A68*Inputs!$C$8*(1+Inputs!$C$16)+Transaction!$C$7+Inputs!$C$17-Inputs!$C$29)))/($A68*Inputs!$C$8*(1+Inputs!$C$16)+Transaction!$C$7+Inputs!$C$17-Inputs!$C$29) -> 2.2418989 | F68: =((LBO_Base!$C$97*F$64*(1-Inputs!$C$70)-LBO_Base!$H$90)-Inputs!$C$20*MAX(0,(LBO_Base!$C$97*F$64*(1-Inputs!$C$70)-LBO_Base!$H$90)-($A68*Inputs!$C$8*(1+Inputs!$C$16)+Transaction!$C$7+Inputs!$C$17-Inputs!$C$29)))/($A68*Inputs!$C$8*(1+Inputs!$C$16)+Transaction!$C$7+Inputs!$C$17-Inputs!$C$29) -> 2.3471292 | G68: =((LBO_Base!$C$97*G$64*(1-Inputs!$C$70)-LBO_Base!$H$90)-Inputs!$C$20*MAX(0,(LBO_Base!$C$97*G$64*(1-Inputs!$C$70)-LBO_Base!$H$90)-($A68*Inputs!$C$8*(1+Inputs!$C$16)+Transaction!$C$7+Inputs!$C$17-Inputs!$C$29)))/($A68*Inputs!$C$8*(1+Inputs!$C$16)+Transaction!$C$7+Inputs!$C$17-Inputs!$C$29) -> 2.4523595 | H68: =((LBO_Base!$C$97*H$64*(1-Inputs!$C$70)-LBO_Base!$H$90)-Inputs!$C$20*MAX(0,(LBO_Base!$C$97*H$64*(1-Inputs!$C$70)-LBO_Base!$H$90)-($A68*Inputs!$C$8*(1+Inputs!$C$16)+Transaction!$C$7+Inputs!$C$17-Inputs!$C$29)))/($A68*Inputs!$C$8*(1+Inputs!$C$16)+Transaction!$C$7+Inputs!$C$17-Inputs!$C$29) -> 2.5575899 | I68: =((LBO_Base!$C$97*I$64*(1-Inputs!$C$70)-LBO_Base!$H$90)-Inputs!$C$20*MAX(0,(LBO_Base!$C$97*I$64*(1-Inputs!$C$70)-LBO_Base!$H$90)-($A68*Inputs!$C$8*(1+Inputs!$C$16)+Transaction!$C$7+Inputs!$C$17-Inputs!$C$29)))/($A68*Inputs!$C$8*(1+Inputs!$C$16)+Transaction!$C$7+Inputs!$C$17-Inputs!$C$29) -> 2.6628202
A69: 14.5 | B69: =A69*Inputs!$C$8 -> 580 | C69: =((LBO_Base!$C$97*C$64*(1-Inputs!$C$70)-LBO_Base!$H$90)-Inputs!$C$20*MAX(0,(LBO_Base!$C$97*C$64*(1-Inputs!$C$70)-LBO_Base!$H$90)-($A69*Inputs!$C$8*(1+Inputs!$C$16)+Transaction!$C$7+Inputs!$C$17-Inputs!$C$29)))/($A69*Inputs!$C$8*(1+Inputs!$C$16)+Transaction!$C$7+Inputs!$C$17-Inputs!$C$29) -> 1.9246595 | D69: =((LBO_Base!$C$97*D$64*(1-Inputs!$C$70)-LBO_Base!$H$90)-Inputs!$C$20*MAX(0,(LBO_Base!$C$97*D$64*(1-Inputs!$C$70)-LBO_Base!$H$90)-($A69*Inputs!$C$8*(1+Inputs!$C$16)+Transaction!$C$7+Inputs!$C$17-Inputs!$C$29)))/($A69*Inputs!$C$8*(1+Inputs!$C$16)+Transaction!$C$7+Inputs!$C$17-Inputs!$C$29) -> 2.0240722 | E69: =((LBO_Base!$C$97*E$64*(1-Inputs!$C$70)-LBO_Base!$H$90)-Inputs!$C$20*MAX(0,(LBO_Base!$C$97*E$64*(1-Inputs!$C$70)-LBO_Base!$H$90)-($A69*Inputs!$C$8*(1+Inputs!$C$16)+Transaction!$C$7+Inputs!$C$17-Inputs!$C$29)))/($A69*Inputs!$C$8*(1+Inputs!$C$16)+Transaction!$C$7+Inputs!$C$17-Inputs!$C$29) -> 2.1234849 | F69: =((LBO_Base!$C$97*F$64*(1-Inputs!$C$70)-LBO_Base!$H$90)-Inputs!$C$20*MAX(0,(LBO_Base!$C$97*F$64*(1-Inputs!$C$70)-LBO_Base!$H$90)-($A69*Inputs!$C$8*(1+Inputs!$C$16)+Transaction!$C$7+Inputs!$C$17-Inputs!$C$29)))/($A69*Inputs!$C$8*(1+Inputs!$C$16)+Transaction!$C$7+Inputs!$C$17-Inputs!$C$29) -> 2.2228977 | G69: =((LBO_Base!$C$97*G$64*(1-Inputs!$C$70)-LBO_Base!$H$90)-Inputs!$C$20*MAX(0,(LBO_Base!$C$97*G$64*(1-Inputs!$C$70)-LBO_Base!$H$90)-($A69*Inputs!$C$8*(1+Inputs!$C$16)+Transaction!$C$7+Inputs!$C$17-Inputs!$C$29)))/($A69*Inputs!$C$8*(1+Inputs!$C$16)+Transaction!$C$7+Inputs!$C$17-Inputs!$C$29) -> 2.3223104 | H69: =((LBO_Base!$C$97*H$64*(1-Inputs!$C$70)-LBO_Base!$H$90)-Inputs!$C$20*MAX(0,(LBO_Base!$C$97*H$64*(1-Inputs!$C$70)-LBO_Base!$H$90)-($A69*Inputs!$C$8*(1+Inputs!$C$16)+Transaction!$C$7+Inputs!$C$17-Inputs!$C$29)))/($A69*Inputs!$C$8*(1+Inputs!$C$16)+Transaction!$C$7+Inputs!$C$17-Inputs!$C$29) -> 2.4217231 | I69: =((LBO_Base!$C$97*I$64*(1-Inputs!$C$70)-LBO_Base!$H$90)-Inputs!$C$20*MAX(0,(LBO_Base!$C$97*I$64*(1-Inputs!$C$70)-LBO_Base!$H$90)-($A69*Inputs!$C$8*(1+Inputs!$C$16)+Transaction!$C$7+Inputs!$C$17-Inputs!$C$29)))/($A69*Inputs!$C$8*(1+Inputs!$C$16)+Transaction!$C$7+Inputs!$C$17-Inputs!$C$29) -> 2.5211359
A70: 15 | B70: =A70*Inputs!$C$8 -> 600 | C70: =((LBO_Base!$C$97*C$64*(1-Inputs!$C$70)-LBO_Base!$H$90)-Inputs!$C$20*MAX(0,(LBO_Base!$C$97*C$64*(1-Inputs!$C$70)-LBO_Base!$H$90)-($A70*Inputs!$C$8*(1+Inputs!$C$16)+Transaction!$C$7+Inputs!$C$17-Inputs!$C$29)))/($A70*Inputs!$C$8*(1+Inputs!$C$16)+Transaction!$C$7+Inputs!$C$17-Inputs!$C$29) -> 1.8290687 | D70: =((LBO_Base!$C$97*D$64*(1-Inputs!$C$70)-LBO_Base!$H$90)-Inputs!$C$20*MAX(0,(LBO_Base!$C$97*D$64*(1-Inputs!$C$70)-LBO_Base!$H$90)-($A70*Inputs!$C$8*(1+Inputs!$C$16)+Transaction!$C$7+Inputs!$C$17-Inputs!$C$29)))/($A70*Inputs!$C$8*(1+Inputs!$C$16)+Transaction!$C$7+Inputs!$C$17-Inputs!$C$29) -> 1.9232734 | E70: =((LBO_Base!$C$97*E$64*(1-Inputs!$C$70)-LBO_Base!$H$90)-Inputs!$C$20*MAX(0,(LBO_Base!$C$97*E$64*(1-Inputs!$C$70)-LBO_Base!$H$90)-($A70*Inputs!$C$8*(1+Inputs!$C$16)+Transaction!$C$7+Inputs!$C$17-Inputs!$C$29)))/($A70*Inputs!$C$8*(1+Inputs!$C$16)+Transaction!$C$7+Inputs!$C$17-Inputs!$C$29) -> 2.017478 | F70: =((LBO_Base!$C$97*F$64*(1-Inputs!$C$70)-LBO_Base!$H$90)-Inputs!$C$20*MAX(0,(LBO_Base!$C$97*F$64*(1-Inputs!$C$70)-LBO_Base!$H$90)-($A70*Inputs!$C$8*(1+Inputs!$C$16)+Transaction!$C$7+Inputs!$C$17-Inputs!$C$29)))/($A70*Inputs!$C$8*(1+Inputs!$C$16)+Transaction!$C$7+Inputs!$C$17-Inputs!$C$29) -> 2.1116827 | G70: =((LBO_Base!$C$97*G$64*(1-Inputs!$C$70)-LBO_Base!$H$90)-Inputs!$C$20*MAX(0,(LBO_Base!$C$97*G$64*(1-Inputs!$C$70)-LBO_Base!$H$90)-($A70*Inputs!$C$8*(1+Inputs!$C$16)+Transaction!$C$7+Inputs!$C$17-Inputs!$C$29)))/($A70*Inputs!$C$8*(1+Inputs!$C$16)+Transaction!$C$7+Inputs!$C$17-Inputs!$C$29) -> 2.2058874 | H70: =((LBO_Base!$C$97*H$64*(1-Inputs!$C$70)-LBO_Base!$H$90)-Inputs!$C$20*MAX(0,(LBO_Base!$C$97*H$64*(1-Inputs!$C$70)-LBO_Base!$H$90)-($A70*Inputs!$C$8*(1+Inputs!$C$16)+Transaction!$C$7+Inputs!$C$17-Inputs!$C$29)))/($A70*Inputs!$C$8*(1+Inputs!$C$16)+Transaction!$C$7+Inputs!$C$17-Inputs!$C$29) -> 2.300092 | I70: =((LBO_Base!$C$97*I$64*(1-Inputs!$C$70)-LBO_Base!$H$90)-Inputs!$C$20*MAX(0,(LBO_Base!$C$97*I$64*(1-Inputs!$C$70)-LBO_Base!$H$90)-($A70*Inputs!$C$8*(1+Inputs!$C$16)+Transaction!$C$7+Inputs!$C$17-Inputs!$C$29)))/($A70*Inputs!$C$8*(1+Inputs!$C$16)+Transaction!$C$7+Inputs!$C$17-Inputs!$C$29) -> 2.3942967
A72: 6. Base case IRR – exit year (rows) × exit multiple (columns), at the model entry price
A73: Exit at the end of | B73: Years held | C73: 12 | D73: 12.5 | E73: 13 | F73: 13.5 | G73: 14 | H73: 14.5 | I73: 15
A74: FY2029 | B74: 3 | C74: =(((INDEX(LBO_Base!$D$24:$H$24,$B74)*C$73*(1-Inputs!$C$70)-INDEX(LBO_Base!$D$90:$H$90,$B74))-Inputs!$C$20*MAX(0,(INDEX(LBO_Base!$D$24:$H$24,$B74)*C$73*(1-Inputs!$C$70)-INDEX(LBO_Base!$D$90:$H$90,$B74))-Transaction!$C$20))/Transaction!$C$20)^(1/$B74)-1 -> 0.14480792 | D74: =(((INDEX(LBO_Base!$D$24:$H$24,$B74)*D$73*(1-Inputs!$C$70)-INDEX(LBO_Base!$D$90:$H$90,$B74))-Inputs!$C$20*MAX(0,(INDEX(LBO_Base!$D$24:$H$24,$B74)*D$73*(1-Inputs!$C$70)-INDEX(LBO_Base!$D$90:$H$90,$B74))-Transaction!$C$20))/Transaction!$C$20)^(1/$B74)-1 -> 0.16759177 | E74: =(((INDEX(LBO_Base!$D$24:$H$24,$B74)*E$73*(1-Inputs!$C$70)-INDEX(LBO_Base!$D$90:$H$90,$B74))-Inputs!$C$20*MAX(0,(INDEX(LBO_Base!$D$24:$H$24,$B74)*E$73*(1-Inputs!$C$70)-INDEX(LBO_Base!$D$90:$H$90,$B74))-Transaction!$C$20))/Transaction!$C$20)^(1/$B74)-1 -> 0.18951952 | F74: =(((INDEX(LBO_Base!$D$24:$H$24,$B74)*F$73*(1-Inputs!$C$70)-INDEX(LBO_Base!$D$90:$H$90,$B74))-Inputs!$C$20*MAX(0,(INDEX(LBO_Base!$D$24:$H$24,$B74)*F$73*(1-Inputs!$C$70)-INDEX(LBO_Base!$D$90:$H$90,$B74))-Transaction!$C$20))/Transaction!$C$20)^(1/$B74)-1 -> 0.21066734 | G74: =(((INDEX(LBO_Base!$D$24:$H$24,$B74)*G$73*(1-Inputs!$C$70)-INDEX(LBO_Base!$D$90:$H$90,$B74))-Inputs!$C$20*MAX(0,(INDEX(LBO_Base!$D$24:$H$24,$B74)*G$73*(1-Inputs!$C$70)-INDEX(LBO_Base!$D$90:$H$90,$B74))-Transaction!$C$20))/Transaction!$C$20)^(1/$B74)-1 -> 0.23110107 | H74: =(((INDEX(LBO_Base!$D$24:$H$24,$B74)*H$73*(1-Inputs!$C$70)-INDEX(LBO_Base!$D$90:$H$90,$B74))-Inputs!$C$20*MAX(0,(INDEX(LBO_Base!$D$24:$H$24,$B74)*H$73*(1-Inputs!$C$70)-INDEX(LBO_Base!$D$90:$H$90,$B74))-Transaction!$C$20))/Transaction!$C$20)^(1/$B74)-1 -> 0.25087812 | I74: =(((INDEX(LBO_Base!$D$24:$H$24,$B74)*I$73*(1-Inputs!$C$70)-INDEX(LBO_Base!$D$90:$H$90,$B74))-Inputs!$C$20*MAX(0,(INDEX(LBO_Base!$D$24:$H$24,$B74)*I$73*(1-Inputs!$C$70)-INDEX(LBO_Base!$D$90:$H$90,$B74))-Transaction!$C$20))/Transaction!$C$20)^(1/$B74)-1 -> 0.27004882
A75: FY2030 | B75: 4 | C75: =(((INDEX(LBO_Base!$D$24:$H$24,$B75)*C$73*(1-Inputs!$C$70)-INDEX(LBO_Base!$D$90:$H$90,$B75))-Inputs!$C$20*MAX(0,(INDEX(LBO_Base!$D$24:$H$24,$B75)*C$73*(1-Inputs!$C$70)-INDEX(LBO_Base!$D$90:$H$90,$B75))-Transaction!$C$20))/Transaction!$C$20)^(1/$B75)-1 -> 0.16222875 | D75: =(((INDEX(LBO_Base!$D$24:$H$24,$B75)*D$73*(1-Inputs!$C$70)-INDEX(LBO_Base!$D$90:$H$90,$B75))-Inputs!$C$20*MAX(0,(INDEX(LBO_Base!$D$24:$H$24,$B75)*D$73*(1-Inputs!$C$70)-INDEX(LBO_Base!$D$90:$H$90,$B75))-Transaction!$C$20))/Transaction!$C$20)^(1/$B75)-1 -> 0.17812729 | E75: =(((INDEX(LBO_Base!$D$24:$H$24,$B75)*E$73*(1-Inputs!$C$70)-INDEX(LBO_Base!$D$90:$H$90,$B75))-Inputs!$C$20*MAX(0,(INDEX(LBO_Base!$D$24:$H$24,$B75)*E$73*(1-Inputs!$C$70)-INDEX(LBO_Base!$D$90:$H$90,$B75))-Transaction!$C$20))/Transaction!$C$20)^(1/$B75)-1 -> 0.19340707 | F75: =(((INDEX(LBO_Base!$D$24:$H$24,$B75)*F$73*(1-Inputs!$C$70)-INDEX(LBO_Base!$D$90:$H$90,$B75))-Inputs!$C$20*MAX(0,(INDEX(LBO_Base!$D$24:$H$24,$B75)*F$73*(1-Inputs!$C$70)-INDEX(LBO_Base!$D$90:$H$90,$B75))-Transaction!$C$20))/Transaction!$C$20)^(1/$B75)-1 -> 0.2081215 | G75: =(((INDEX(LBO_Base!$D$24:$H$24,$B75)*G$73*(1-Inputs!$C$70)-INDEX(LBO_Base!$D$90:$H$90,$B75))-Inputs!$C$20*MAX(0,(INDEX(LBO_Base!$D$24:$H$24,$B75)*G$73*(1-Inputs!$C$70)-INDEX(LBO_Base!$D$90:$H$90,$B75))-Transaction!$C$20))/Transaction!$C$20)^(1/$B75)-1 -> 0.22231712 | H75: =(((INDEX(LBO_Base!$D$24:$H$24,$B75)*H$73*(1-Inputs!$C$70)-INDEX(LBO_Base!$D$90:$H$90,$B75))-Inputs!$C$20*MAX(0,(INDEX(LBO_Base!$D$24:$H$24,$B75)*H$73*(1-Inputs!$C$70)-INDEX(LBO_Base!$D$90:$H$90,$B75))-Transaction!$C$20))/Transaction!$C$20)^(1/$B75)-1 -> 0.23603471 | I75: =(((INDEX(LBO_Base!$D$24:$H$24,$B75)*I$73*(1-Inputs!$C$70)-INDEX(LBO_Base!$D$90:$H$90,$B75))-Inputs!$C$20*MAX(0,(INDEX(LBO_Base!$D$24:$H$24,$B75)*I$73*(1-Inputs!$C$70)-INDEX(LBO_Base!$D$90:$H$90,$B75))-Transaction!$C$20))/Transaction!$C$20)^(1/$B75)-1 -> 0.2493102
A76: FY2031 | B76: 5 | C76: =(((INDEX(LBO_Base!$D$24:$H$24,$B76)*C$73*(1-Inputs!$C$70)-INDEX(LBO_Base!$D$90:$H$90,$B76))-Inputs!$C$20*MAX(0,(INDEX(LBO_Base!$D$24:$H$24,$B76)*C$73*(1-Inputs!$C$70)-INDEX(LBO_Base!$D$90:$H$90,$B76))-Transaction!$C$20))/Transaction!$C$20)^(1/$B76)-1 -> 0.16559562 | D76: =(((INDEX(LBO_Base!$D$24:$H$24,$B76)*D$73*(1-Inputs!$C$70)-INDEX(LBO_Base!$D$90:$H$90,$B76))-Inputs!$C$20*MAX(0,(INDEX(LBO_Base!$D$24:$H$24,$B76)*D$73*(1-Inputs!$C$70)-INDEX(LBO_Base!$D$90:$H$90,$B76))-Transaction!$C$20))/Transaction!$C$20)^(1/$B76)-1 -> 0.1774622 | E76: =(((INDEX(LBO_Base!$D$24:$H$24,$B76)*E$73*(1-Inputs!$C$70)-INDEX(LBO_Base!$D$90:$H$90,$B76))-Inputs!$C$20*MAX(0,(INDEX(LBO_Base!$D$24:$H$24,$B76)*E$73*(1-Inputs!$C$70)-INDEX(LBO_Base!$D$90:$H$90,$B76))-Transaction!$C$20))/Transaction!$C$20)^(1/$B76)-1 -> 0.18886883 | F76: =(((INDEX(LBO_Base!$D$24:$H$24,$B76)*F$73*(1-Inputs!$C$70)-INDEX(LBO_Base!$D$90:$H$90,$B76))-Inputs!$C$20*MAX(0,(INDEX(LBO_Base!$D$24:$H$24,$B76)*F$73*(1-Inputs!$C$70)-INDEX(LBO_Base!$D$90:$H$90,$B76))-Transaction!$C$20))/Transaction!$C$20)^(1/$B76)-1 -> 0.19985379 | G76: =(((INDEX(LBO_Base!$D$24:$H$24,$B76)*G$73*(1-Inputs!$C$70)-INDEX(LBO_Base!$D$90:$H$90,$B76))-Inputs!$C$20*MAX(0,(INDEX(LBO_Base!$D$24:$H$24,$B76)*G$73*(1-Inputs!$C$70)-INDEX(LBO_Base!$D$90:$H$90,$B76))-Transaction!$C$20))/Transaction!$C$20)^(1/$B76)-1 -> 0.21045061 | H76: =(((INDEX(LBO_Base!$D$24:$H$24,$B76)*H$73*(1-Inputs!$C$70)-INDEX(LBO_Base!$D$90:$H$90,$B76))-Inputs!$C$20*MAX(0,(INDEX(LBO_Base!$D$24:$H$24,$B76)*H$73*(1-Inputs!$C$70)-INDEX(LBO_Base!$D$90:$H$90,$B76))-Transaction!$C$20))/Transaction!$C$20)^(1/$B76)-1 -> 0.22068884 | I76: =(((INDEX(LBO_Base!$D$24:$H$24,$B76)*I$73*(1-Inputs!$C$70)-INDEX(LBO_Base!$D$90:$H$90,$B76))-Inputs!$C$20*MAX(0,(INDEX(LBO_Base!$D$24:$H$24,$B76)*I$73*(1-Inputs!$C$70)-INDEX(LBO_Base!$D$90:$H$90,$B76))-Transaction!$C$20))/Transaction!$C$20)^(1/$B76)-1 -> 0.23059468
A78: 7. Model checks
A79: Sources equal uses | B79: flag | C79: =IF(ABS(Transaction!C17)<0.001,1,0) -> 1
A80: Equity bridges reconcile (all cases) | B80: flag | C80: =IF(ABS(LBO_Base!C134)+ABS(LBO_Mgmt!C134)+ABS(LBO_Down!C134)<0.001,1,0) -> 1
A81: Net debt roll-forwards reconcile (all cases) | B81: flag | C81: =IF(SUMPRODUCT(ABS(LBO_Base!D94:H94))+SUMPRODUCT(ABS(LBO_Mgmt!D94:H94))+SUMPRODUCT(ABS(LBO_Down!D94:H94))<0.001,1,0) -> 1
A82: Cash never below minimum (all cases) | B82: flag | C82: =MIN(LBO_Base!C138,LBO_Mgmt!C138,LBO_Down!C138) -> 1
A83: Add-ons fully funded by the CAF (all cases) | B83: flag | C83: =MIN(LBO_Base!C139,LBO_Mgmt!C139,LBO_Down!C139) -> 1
A84: RCF within commitment (all cases) | B84: flag | C84: =MIN(LBO_Base!C140,LBO_Mgmt!C140,LBO_Down!C140) -> 1
A85: IRR formula consistent with MOIC (all cases) | B85: flag | C85: =IF(ABS(LBO_Base!C110)+ABS(LBO_Mgmt!C110)+ABS(LBO_Down!C110)<0.0001,1,0) -> 1
A86: Bid ladder consistent with model | B86: flag | C86: =IF(ABS(F51)<0.0001,1,0) -> 1
A87: All checks OK (1 = yes) | C87: =MIN(C79:C86) -> 1
